Workbook
Name _MailAutoSig: '06_發行案件'!#REF!
Name _MailAutoSig: '07_董事會決議'!#REF!
Name AUpdate: 1
Name BUpdate: 1
Name GUpdate: 0
Name NoUpdate: ""
Name Sheet1.漲跌幅: "round(((cast([6^6] as real)/cast([0^0] as real))-1),2)"
Name Sheet1.漲跌幅old: "I6,C6"
Name Sheet1.漲跌幅where: "(cast([0^6] as real)<>0)"
Name TUpdate: 1
Name XX_TEJ1: #REF!
Name XX_TEJ2: #REF!
Name 股票名稱: #REF!
Name 泰金二KY: #REF!
Name 富貴50: #REF!
Name 資料庫.股本: "round(cast([39^0] as real)/10,1)"
Name 資料庫.股本.億: "round(cast([39^0] as real)/100,1)"
Name 資料庫.股本.億old: "AP6"
Name 資料庫.股本.億where: "(100<>0)"
Name 資料庫.股本old: "AP6"
Name 資料庫.股本where: "(10<>0)"

Sheet 00_CB代號名稱過濾及掛牌高低_20251031
A1: 股票代號 | B1: 代號 | C1: 名稱 | D1: 掛牌最高 | E1: 掛牌最低 | F1: 資金用途 | G1: 掛牌日期 | H1: 資金用途分類
A2: 1101 | B2: 11011 | C2: 台泥一永 | D2: =IFERROR(VLOOKUP(B2,[1]最高價!$A:$C,3,FALSE),"") -> 108.1 | E2: =IFERROR(VLOOKUP(B2,[1]最低價!$A:$C,3,FALSE),"") -> 94.4 | F2: 轉投資海外子公司 TCC Dutch131.6億，償還銀行借款61.54億，共計193.15億 | G2: =VLOOKUP(B2,'[2]01_ALLCB基本資料'!C:U,16,FALSE) -> 45636 | H2: 償還銀行借款
A3: 1210 | B3: 12101 | C3: 大成一 | D3: =IFERROR(VLOOKUP(B3,[1]最高價!$A:$C,3,FALSE),"") -> 127 | E3: =IFERROR(VLOOKUP(B3,[1]最低價!$A:$C,3,FALSE),"") -> 72.5 | G3: =VLOOKUP(B3,'[2]01_ALLCB基本資料'!C:U,16,FALSE) -> 39336
A4: 1216 | B4: 12161 | C4: 統一一 | D4: =IFERROR(VLOOKUP(B4,[1]最高價!$A:$C,3,FALSE),"") -> 106.75 | E4: =IFERROR(VLOOKUP(B4,[1]最低價!$A:$C,3,FALSE),"") -> 91.2 | G4: =VLOOKUP(B4,'[2]01_ALLCB基本資料'!C:U,16,FALSE) -> 39370
A5: 1217 | B5: 12171 | C5: 愛之味一 | D5: =IFERROR(VLOOKUP(B5,[1]最高價!$A:$C,3,FALSE),"") -> 123 | E5: =IFERROR(VLOOKUP(B5,[1]最低價!$A:$C,3,FALSE),"") -> 100 | G5: =VLOOKUP(B5,'[2]01_ALLCB基本資料'!C:U,16,FALSE) -> 40664
A6: 1217 | B6: 12172 | C6: 愛之味二 | D6: =IFERROR(VLOOKUP(B6,[1]最高價!$A:$C,3,FALSE),"") -> 112 | E6: =IFERROR(VLOOKUP(B6,[1]最低價!$A:$C,3,FALSE),"") -> 89 | G6: =VLOOKUP(B6,'[2]01_ALLCB基本資料'!C:U,16,FALSE) -> 40675
A7: 1217 | B7: 12173 | C7: 愛之味三 | D7: =IFERROR(VLOOKUP(B7,[1]最高價!$A:$C,3,FALSE),"") -> 105 | E7: =IFERROR(VLOOKUP(B7,[1]最低價!$A:$C,3,FALSE),"") -> 99.6 | F7: 償還銀行借款6億，充實營運資金3億，購置設備1億 | G7: =VLOOKUP(B7,'[2]01_ALLCB基本資料'!C:U,16,FALSE) -> 41340 | H7: 償還+充實
A8: 1218 | B8: 12181 | C8: 泰山一 | D8: =IFERROR(VLOOKUP(B8,[1]最高價!$A:$C,3,FALSE),"") -> 109.9 | E8: =IFERROR(VLOOKUP(B8,[1]最低價!$A:$C,3,FALSE),"") -> 99 | F8: 償還銀行借款5億 | G8: =VLOOKUP(B8,'[2]01_ALLCB基本資料'!C:U,16,FALSE) -> 41417 | H8: 償還銀行借款
A9: 1225 | B9: 12251 | C9: 福脂一 | D9: =IFERROR(VLOOKUP(B9,[1]最高價!$A:$C,3,FALSE),"") -> 233 | E9: =IFERROR(VLOOKUP(B9,[1]最低價!$A:$C,3,FALSE),"") -> 101 | G9: =VLOOKUP(B9,'[2]01_ALLCB基本資料'!C:U,16,FALSE) -> 40158
A10: 1258 | B10: 12581 | C10: 其祥一KY | D10: =IFERROR(VLOOKUP(B10,[1]最高價!$A:$C,3,FALSE),"") -> 124.25 | E10: =IFERROR(VLOOKUP(B10,[1]最低價!$A:$C,3,FALSE),"") -> 99.1 | G10: =VLOOKUP(B10,'[2]01_ALLCB基本資料'!C:U,16,FALSE) -> 42262
A11: 1258 | B11: 12582 | C11: 其祥二KY | D11: =IFERROR(VLOOKUP(B11,[1]最高價!$A:$C,3,FALSE),"") -> 101.3 | E11: =IFERROR(VLOOKUP(B11,[1]最低價!$A:$C,3,FALSE),"") -> 76.2 | G11: =VLOOKUP(B11,'[2]01_ALLCB基本資料'!C:U,16,FALSE) -> 43353
A12: 1312 | B12: 13121 | C12: 國喬一 | D12: =IFERROR(VLOOKUP(B12,[1]最高價!$A:$C,3,FALSE),"") -> 171 | E12: =IFERROR(VLOOKUP(B12,[1]最低價!$A:$C,3,FALSE),"") -> 90 | G12: =VLOOKUP(B12,'[2]01_ALLCB基本資料'!C:U,16,FALSE)
A13: 1316 | B13: 13161 | C13: 上曜一 | D13: =IFERROR(VLOOKUP(B13,[1]最高價!$A:$C,3,FALSE),"") -> 122 | E13: =IFERROR(VLOOKUP(B13,[1]最低價!$A:$C,3,FALSE),"") -> 99.65 | F13: 償還銀行借款0.8億，購置機器設備1億，充實營運資金1.2億 | G13: =VLOOKUP(B13,'[2]01_ALLCB基本資料'!C:U,16,FALSE) -> 40757 | H13: 償還+充實
A14: 1316 | B14: 13162 | C14: 上曜二 | D14: =IFERROR(VLOOKUP(B14,[1]最高價!$A:$C,3,FALSE),"") -> 177 | E14: =IFERROR(VLOOKUP(B14,[1]最低價!$A:$C,3,FALSE),"") -> 104 | F14: 現金增資3億，上曜二募得2億，充實營運資金5億 | G14: =VLOOKUP(B14,'[2]01_ALLCB基本資料'!C:U,16,FALSE) -> 41996 | H14: 充實營運資金
A15: 1316 | B15: 13163 | C15: 上曜三 | D15: =IFERROR(VLOOKUP(B15,[1]最高價!$A:$C,3,FALSE),"") -> 117.95 | E15: =IFERROR(VLOOKUP(B15,[1]最低價!$A:$C,3,FALSE),"") -> 99.6 | F15: 充實營運資金13億 | G15: =VLOOKUP(B15,'[2]01_ALLCB基本資料'!C:U,16,FALSE) -> 43411 | H15: 充實營運資金
A16: 1316 | B16: 13164 | C16: 上曜四 | D16: =IFERROR(VLOOKUP(B16,[1]最高價!$A:$C,3,FALSE),"") -> 189 | E16: =IFERROR(VLOOKUP(B16,[1]最低價!$A:$C,3,FALSE),"") -> 101.5 | F16: 充實營運資金7.04億，償還銀行借款1億，與上曜五同時發行 | G16: =VLOOKUP(B16,'[2]01_ALLCB基本資料'!C:U,16,FALSE) -> 44225 | H16: 償還+充實
A17: 1316 | B17: 13165 | C17: 上曜五 | D17: =IFERROR(VLOOKUP(B17,[1]最高價!$A:$C,3,FALSE),"") -> 232 | E17: =IFERROR(VLOOKUP(B17,[1]最低價!$A:$C,3,FALSE),"") -> 99.6 | F17: 充實營運資金7.04億，償還銀行借款1億，與上曜四同時發行 | G17: =VLOOKUP(B17,'[2]01_ALLCB基本資料'!C:U,16,FALSE) -> 44228 | H17: 償還+充實
A18: 1316 | B18: 13166 | C18: 上曜六 | D18: =IFERROR(VLOOKUP(B18,[1]最高價!$A:$C,3,FALSE),"") -> 125.5 | E18: =IFERROR(VLOOKUP(B18,[1]最低價!$A:$C,3,FALSE),"") -> 102.8 | F18: 充實營運資金共計11.8億，CB6發行4000張，現增65000張，認購價12元 | G18: =VLOOKUP(B18,'[2]01_ALLCB基本資料'!C:U,16,FALSE) -> 45653 | H18: 充實營運資金
A19: 1319 | B19: 13191 | C19: 東陽一 | D19: =IFERROR(VLOOKUP(B19,[1]最高價!$A:$C,3,FALSE),"") -> 115 | E19: =IFERROR(VLOOKUP(B19,[1]最低價!$A:$C,3,FALSE),"") -> 95.4 | G19: =VLOOKUP(B19,'[2]01_ALLCB基本資料'!C:U,16,FALSE) -> 40536
A20: 1336 | B20: 13361 | C20: 台翰一 | D20: =IFERROR(VLOOKUP(B20,[1]最高價!$A:$C,3,FALSE),"") -> 116 | E20: =IFERROR(VLOOKUP(B20,[1]最低價!$A:$C,3,FALSE),"") -> 101.1 | F20: 償還銀行借款及商業本票2.74億，充實營運資金0.77億 | G20: =VLOOKUP(B20,'[2]01_ALLCB基本資料'!C:U,16,FALSE) -> 41892 | H20: 償還+充實
A21: 1337 | B21: 13371 | C21: 再生一 | D21: =IFERROR(VLOOKUP(B21,[1]最高價!$A:$C,3,FALSE),"") -> 120.5 | E21: =IFERROR(VLOOKUP(B21,[1]最低價!$A:$C,3,FALSE),"") -> 82.95 | F21: 現金增資13.69億，再生一KY募得6億，擴廠18.83億，購買機器設備11.63億 | G21: =VLOOKUP(B21,'[2]01_ALLCB基本資料'!C:U,16,FALSE) -> 41193 | H21: 資本支出
A22: 1338 | B22: 13381 | C22: 廣華一KY | D22: =IFERROR(VLOOKUP(B22,[1]最高價!$A:$C,3,FALSE),"") -> 117 | E22: =IFERROR(VLOOKUP(B22,[1]最低價!$A:$C,3,FALSE),"") -> 97.1 | F22: 償還銀行借款4.95億及充實營運資金1.05億，共計6億元。 | G22: =VLOOKUP(B22,'[2]01_ALLCB基本資料'!C:U,16,FALSE) -> 44215 | H22: 償還+充實
A23: 1338 | B23: 13382 | C23: 廣華二KY | D23: =IFERROR(VLOOKUP(B23,[1]最高價!$A:$C,3,FALSE),"") -> 115.5 | E23: =IFERROR(VLOOKUP(B23,[1]最低價!$A:$C,3,FALSE),"") -> 93.05 | F23: 償還第一次轉換公司債6.09億 | G23: =VLOOKUP(B23,'[2]01_ALLCB基本資料'!C:U,16,FALSE) -> 45261 | H23: 借新還舊
A24: 1341 | B24: 13411 | C24: 富林一KY | D24: =IFERROR(VLOOKUP(B24,[1]最高價!$A:$C,3,FALSE),"") -> 116.9 | E24: =IFERROR(VLOOKUP(B24,[1]最低價!$A:$C,3,FALSE),"") -> 100.8 | F24: 現金增資0.5億，1000張/50元，富林一募得1.72億，充實營運資金2.22億 | G24: =VLOOKUP(B24,'[2]01_ALLCB基本資料'!C:U,16,FALSE) -> 44329 | H24: 充實營運資金
A25: 1342 | B25: 13421 | C25: 八貫一 | D25: =IFERROR(VLOOKUP(B25,[1]最高價!$A:$C,3,FALSE),"") -> 243 | E25: =IFERROR(VLOOKUP(B25,[1]最低價!$A:$C,3,FALSE),"") -> 106.5 | F25: 充實營運資金2.25億 | G25: =VLOOKUP(B25,'[2]01_ALLCB基本資料'!C:U,16,FALSE) -> 44714 | H25: 充實營運資金
A26: 1409 | B26: 14093 | C26: 新纖三 | D26: =IFERROR(VLOOKUP(B26,[1]最高價!$A:$C,3,FALSE),"") -> 180 | E26: =IFERROR(VLOOKUP(B26,[1]最低價!$A:$C,3,FALSE),"") -> 77 | G26: =VLOOKUP(B26,'[2]01_ALLCB基本資料'!C:U,16,FALSE) -> 39189
A27: 1432 | B27: 14321 | C27: 大魯閣一 | D27: =IFERROR(VLOOKUP(B27,[1]最高價!$A:$C,3,FALSE),"") -> 119 | E27: =IFERROR(VLOOKUP(B27,[1]最低價!$A:$C,3,FALSE),"") -> 100.5 | F27: 轉投資大魯閣開發股分有限公司5億，與大魯閣二同時發行 | G27: =VLOOKUP(B27,'[2]01_ALLCB基本資料'!C:U,16,FALSE) -> 42047 | H27: 轉投資
A28: 1432 | B28: 14322 | C28: 大魯閣二 | D28: =IFERROR(VLOOKUP(B28,[1]最高價!$A:$C,3,FALSE),"") -> 119.1 | E28: =IFERROR(VLOOKUP(B28,[1]最低價!$A:$C,3,FALSE),"") -> 92.3 | F28: 轉投資大魯閣開發股分有限公司5億，與大魯閣一同時發行 | G28: =VLOOKUP(B28,'[2]01_ALLCB基本資料'!C:U,16,FALSE) -> 42048 | H28: 轉投資
A29: 1436 | B29: 14361 | C29: 華友聯一 | D29: =IFERROR(VLOOKUP(B29,[1]最高價!$A:$C,3,FALSE),"") -> 695 | E29: =IFERROR(VLOOKUP(B29,[1]最低價!$A:$C,3,FALSE),"") -> 106 | F29: 償還銀行借款3.78億 | G29: =VLOOKUP(B29,'[2]01_ALLCB基本資料'!C:U,16,FALSE) -> 43847 | H29: 償還銀行借款
A30: 1436 | B30: 14362 | C30: 華友聯二 | D30: =IFERROR(VLOOKUP(B30,[1]最高價!$A:$C,3,FALSE),"") -> 600 | E30: =IFERROR(VLOOKUP(B30,[1]最低價!$A:$C,3,FALSE),"") -> 111.1 | F30: 償還銀行借款10.14億 | G30: =VLOOKUP(B30,'[2]01_ALLCB基本資料'!C:U,16,FALSE) -> 44166 | H30: 償還銀行借款
A31: 1436 | B31: 14363 | C31: 華友聯三 | D31: =IFERROR(VLOOKUP(B31,[1]最高價!$A:$C,3,FALSE),"") -> 124.25 | E31: =IFERROR(VLOOKUP(B31,[1]最低價!$A:$C,3,FALSE),"") -> 93.6 | F31: 償還銀行借款6億 | G31: =VLOOKUP(B31,'[2]01_ALLCB基本資料'!C:U,16,FALSE) -> 45531 | H31: 償還銀行借款
A32: 1436 | B32: 14364 | C32: 華友聯四 | D32: =IFERROR(VLOOKUP(B32,[1]最高價!$A:$C,3,FALSE),"") -> 104.95 | E32: =IFERROR(VLOOKUP(B32,[1]最低價!$A:$C,3,FALSE),"") -> 92.5 | F32: 償還銀行借款20.2億，發行CB4共20000張，詢圈101元 | G32: =VLOOKUP(B32,'[2]01_ALLCB基本資料'!C:U,16,FALSE) -> 45734 | H32: 借新還舊
A33: 1437 | B33: 14371 | C33: 勤益一 | D33: =IFERROR(VLOOKUP(B33,[1]最高價!$A:$C,3,FALSE),"") -> 266 | E33: =IFERROR(VLOOKUP(B33,[1]最低價!$A:$C,3,FALSE),"") -> 92 | G33: =VLOOKUP(B33,'[2]01_ALLCB基本資料'!C:U,16,FALSE)
A34: 1438 | B34: 14381 | C34: 三地開發一 | D34: =IFERROR(VLOOKUP(B34,[1]最高價!$A:$C,3,FALSE),"") -> 134 | E34: =IFERROR(VLOOKUP(B34,[1]最低價!$A:$C,3,FALSE),"") -> 119 | F34: 償還銀行借款7.64億，支付營建工程款-艾美新時代(台南市平實段)24.84億，支付營建工程款-艾美‧柏(高雄市後港東段)9.87億。 | G34: =VLOOKUP(B34,'[2]01_ALLCB基本資料'!C:U,16,FALSE) -> 45645 | H34: 償還銀行借款
A35: 1442 | B35: 14422 | C35: 名軒二 | D35: =IFERROR(VLOOKUP(B35,[1]最高價!$A:$C,3,FALSE),"") -> 165 | E35: =IFERROR(VLOOKUP(B35,[1]最低價!$A:$C,3,FALSE),"") -> 105.55 | F35: 償還銀行借款8億 | G35: =VLOOKUP(B35,'[2]01_ALLCB基本資料'!C:U,16,FALSE) -> 41122 | H35: 償還銀行借款
A36: 1442 | B36: 14423 | C36: 名軒三 | D36: =IFERROR(VLOOKUP(B36,[1]最高價!$A:$C,3,FALSE),"") -> 188 | E36: =IFERROR(VLOOKUP(B36,[1]最低價!$A:$C,3,FALSE),"") -> 105 | F36: 償還銀行借款6.26億 | G36: =VLOOKUP(B36,'[2]01_ALLCB基本資料'!C:U,16,FALSE) -> 42339 | H36: 償還銀行借款
A37: 1457 | B37: 14571 | C37: 宜進一 | D37: =IFERROR(VLOOKUP(B37,[1]最高價!$A:$C,3,FALSE),"") -> 109.8 | E37: =IFERROR(VLOOKUP(B37,[1]最低價!$A:$C,3,FALSE),"") -> 90 | F37: 現金增資4.5億，宜進一募得3億，購置土地、廠房及生產設備21.67億 | G37: =VLOOKUP(B37,'[2]01_ALLCB基本資料'!C:U,16,FALSE) -> 40724 | H37: 資本支出
A38: 1464 | B38: 14641 | C38: 得力一 | D38: =IFERROR(VLOOKUP(B38,[1]最高價!$A:$C,3,FALSE),"") -> 172 | E38: =IFERROR(VLOOKUP(B38,[1]最低價!$A:$C,3,FALSE),"") -> 107 | F38: 償還銀行借款4.5億，與得力二同時發行 | G38: =VLOOKUP(B38,'[2]01_ALLCB基本資料'!C:U,16,FALSE) -> 42144 | H38: 償還銀行借款
A39: 1464 | B39: 14642 | C39: 得力二 | D39: =IFERROR(VLOOKUP(B39,[1]最高價!$A:$C,3,FALSE),"") -> 177 | E39: =IFERROR(VLOOKUP(B39,[1]最低價!$A:$C,3,FALSE),"") -> 103 | F39: 償還銀行借款4.5億，與得力一同時發行 | G39: =VLOOKUP(B39,'[2]01_ALLCB基本資料'!C:U,16,FALSE) -> 42145 | H39: 償還銀行借款
A40: 1466 | B40: 14661 | C40: 聚隆一 | D40: =IFERROR(VLOOKUP(B40,[1]最高價!$A:$C,3,FALSE),"") -> 127 | E40: =IFERROR(VLOOKUP(B40,[1]最低價!$A:$C,3,FALSE),"") -> 98 | F40: 機器設備及增設附屬工程1.09億，償還銀行借款1.9億 | G40: =VLOOKUP(B40,'[2]01_ALLCB基本資料'!C:U,16,FALSE) -> 40693 | H40: 償還銀行借款
A41: 1466 | B41: 14662 | C41: 聚隆二 | D41: =IFERROR(VLOOKUP(B41,[1]最高價!$A:$C,3,FALSE),"") -> 147.5 | E41: =IFERROR(VLOOKUP(B41,[1]最低價!$A:$C,3,FALSE),"") -> 102.75 | F41: 償還銀行借款3億 | G41: =VLOOKUP(B41,'[2]01_ALLCB基本資料'!C:U,16,FALSE) -> 41288 | H41: 償還銀行借款
A42: 1466 | B42: 14663 | C42: 聚隆三 | D42: =IFERROR(VLOOKUP(B42,[1]最高價!$A:$C,3,FALSE),"") -> 109 | E42: =IFERROR(VLOOKUP(B42,[1]最低價!$A:$C,3,FALSE),"") -> 98 | F42: 現金增資1億，5000張/20元，聚隆三募得4億，償還銀行借款3億，轉投資子公司2億 | G42: =VLOOKUP(B42,'[2]01_ALLCB基本資料'!C:U,16,FALSE) -> 41906 | H42: 償還銀行借款
A43: 1467 | B43: 14671 | C43: 南緯一 | D43: =IFERROR(VLOOKUP(B43,[1]最高價!$A:$C,3,FALSE),"") -> 142.2 | E43: =IFERROR(VLOOKUP(B43,[1]最低價!$A:$C,3,FALSE),"") -> 101.5 | G43: =VLOOKUP(B43,'[2]01_ALLCB基本資料'!C:U,16,FALSE)
A44: 1472 | B44: 14721 | C44: 三洋實業一 | D44: =IFERROR(VLOOKUP(B44,[1]最高價!$A:$C,3,FALSE),"") -> 124.5 | E44: =IFERROR(VLOOKUP(B44,[1]最低價!$A:$C,3,FALSE),"") -> 99.1 | F44: 償還銀行借款3.72億 | G44: =VLOOKUP(B44,'[2]01_ALLCB基本資料'!C:U,16,FALSE) -> 43495 | H44: 償還銀行借款
A45: 1474 | B45: 14741 | C45: 弘裕一 | D45: =IFERROR(VLOOKUP(B45,[1]最高價!$A:$C,3,FALSE),"") -> 125 | E45: =IFERROR(VLOOKUP(B45,[1]最低價!$A:$C,3,FALSE),"") -> 100 | G45: =VLOOKUP(B45,'[2]01_ALLCB基本資料'!C:U,16,FALSE)
A46: 1474 | B46: 14742 | C46: 弘裕二 | D46: =IFERROR(VLOOKUP(B46,[1]最高價!$A:$C,3,FALSE),"") -> 117 | E46: =IFERROR(VLOOKUP(B46,[1]最低價!$A:$C,3,FALSE),"") -> 96 | F46: 購置機器設備1.06億，償還銀行借款2.21億 | G46: =VLOOKUP(B46,'[2]01_ALLCB基本資料'!C:U,16,FALSE) -> 44587 | H46: 償還銀行借款
A47: 1474 | B47: 14743 | C47: 弘裕三 | D47: =IFERROR(VLOOKUP(B47,[1]最高價!$A:$C,3,FALSE),"") -> 99.95 | E47: =IFERROR(VLOOKUP(B47,[1]最低價!$A:$C,3,FALSE),"") -> 89.5 | F47: 償還國內第二次無擔保轉換公司債到期所需資金3.04億，發行CB3共3000張 | G47: =VLOOKUP(B47,'[2]01_ALLCB基本資料'!C:U,16,FALSE) -> 45747 | H47: 借新還舊
A48: 1477 | B48: 14771 | C48: 聚陽一 | D48: =IFERROR(VLOOKUP(B48,[1]最高價!$A:$C,3,FALSE),"") -> 386 | E48: =IFERROR(VLOOKUP(B48,[1]最低價!$A:$C,3,FALSE),"") -> 110 | G48: =VLOOKUP(B48,'[2]01_ALLCB基本資料'!C:U,16,FALSE)
A49: 1477 | B49: 14772 | C49: 聚陽二 | D49: =IFERROR(VLOOKUP(B49,[1]最高價!$A:$C,3,FALSE),"") -> 292 | E49: =IFERROR(VLOOKUP(B49,[1]最低價!$A:$C,3,FALSE),"") -> 100 | G49: =VLOOKUP(B49,'[2]01_ALLCB基本資料'!C:U,16,FALSE)
A50: 1477 | B50: 14773 | C50: 聚陽三 | D50: =IFERROR(VLOOKUP(B50,[1]最高價!$A:$C,3,FALSE),"") -> 495 | E50: =IFERROR(VLOOKUP(B50,[1]最低價!$A:$C,3,FALSE),"") -> 106.5 | G50: =VLOOKUP(B50,'[2]01_ALLCB基本資料'!C:U,16,FALSE) -> 39976
A51: 1477 | B51: 14774 | C51: 聚陽四 | D51: =IFERROR(VLOOKUP(B51,[1]最高價!$A:$C,3,FALSE),"") -> 401 | E51: =IFERROR(VLOOKUP(B51,[1]最低價!$A:$C,3,FALSE),"") -> 106.2 | F51: 償還銀行借款7億 | G51: =VLOOKUP(B51,'[2]01_ALLCB基本資料'!C:U,16,FALSE) -> 41145 | H51: 償還銀行借款
A52: 1504 | B52: 15043 | C52: 東元三 | D52: =IFERROR(VLOOKUP(B52,[1]最高價!$A:$C,3,FALSE),"") -> 167 | E52: =IFERROR(VLOOKUP(B52,[1]最低價!$A:$C,3,FALSE),"") -> 99.05 | F52: 償還銀行借款 30億 | G52: =VLOOKUP(B52,'[2]01_ALLCB基本資料'!C:U,16,FALSE) -> 41102 | H52: 償還銀行借款
A53: 1506 | B53: 15061 | C53: 正道一 | D53: =IFERROR(VLOOKUP(B53,[1]最高價!$A:$C,3,FALSE),"") -> 121 | E53: =IFERROR(VLOOKUP(B53,[1]最低價!$A:$C,3,FALSE),"") -> 96.95 | F53: 償還銀行借款2億，轉投資正道福州1.5億，正道馬來0.8億，興建廠房購置設備2.1億，充實營運資金0.6億。 | G53: =VLOOKUP(B53,'[2]01_ALLCB基本資料'!C:U,16,FALSE) -> 42027 | H53: 償還+充實
A54: 1513 | B54: 15131 | C54: 中興電一 | D54: =IFERROR(VLOOKUP(B54,[1]最高價!$A:$C,3,FALSE),"") -> 213 | E54: =IFERROR(VLOOKUP(B54,[1]最低價!$A:$C,3,FALSE),"") -> 101 | F54: 償還銀行借款15億 | G54: =VLOOKUP(B54,'[2]01_ALLCB基本資料'!C:U,16,FALSE) -> 43846 | H54: 償還銀行借款
A55: 1513 | B55: 15132 | C55: 中興電二 | D55: =IFERROR(VLOOKUP(B55,[1]最高價!$A:$C,3,FALSE),"") -> 231 | E55: =IFERROR(VLOOKUP(B55,[1]最低價!$A:$C,3,FALSE),"") -> 106 | F55: 償還銀行借款15.06億 | G55: =VLOOKUP(B55,'[2]01_ALLCB基本資料'!C:U,16,FALSE) -> 44182 | H55: 償還銀行借款
A56: 1514 | B56: 15141 | C56: 亞力一 | D56: =IFERROR(VLOOKUP(B56,[1]最高價!$A:$C,3,FALSE),"") -> 276 | E56: =IFERROR(VLOOKUP(B56,[1]最低價!$A:$C,3,FALSE),"") -> 103.8 | F56: 償還金融機構借款10.05億 | G56: =VLOOKUP(B56,'[2]01_ALLCB基本資料'!C:U,16,FALSE) -> 45155 | H56: 償還銀行借款
A57: 1514 | B57: 15142 | C57: 亞力二 | D57: =IFERROR(VLOOKUP(B57,[1]最高價!$A:$C,3,FALSE),"") -> 127 | E57: =IFERROR(VLOOKUP(B57,[1]最低價!$A:$C,3,FALSE),"") -> 99.45 | F57: 償還銀行借款12.06億，發行第二次CB 12000張。 | G57: =VLOOKUP(B57,'[2]01_ALLCB基本資料'!C:U,16,FALSE) -> 45670 | H57: 借新還舊
A58: 1515 | B58: 15151 | C58: 力山一 | D58: =IFERROR(VLOOKUP(B58,[1]最高價!$A:$C,3,FALSE),"") -> 131 | E58: =IFERROR(VLOOKUP(B58,[1]最低價!$A:$C,3,FALSE),"") -> 122 | G58: =VLOOKUP(B58,'[2]01_ALLCB基本資料'!C:U,16,FALSE)
A59: 1522 | B59: 15221 | C59: 堤維西一 | D59: =IFERROR(VLOOKUP(B59,[1]最高價!$A:$C,3,FALSE),"") -> 142 | E59: =IFERROR(VLOOKUP(B59,[1]最低價!$A:$C,3,FALSE),"") -> 92 | G59: =VLOOKUP(B59,'[2]01_ALLCB基本資料'!C:U,16,FALSE)
A60: 1524 | B60: 15241 | C60: 耿鼎一 | D60: =IFERROR(VLOOKUP(B60,[1]最高價!$A:$C,3,FALSE),"") -> 195 | E60: =IFERROR(VLOOKUP(B60,[1]最低價!$A:$C,3,FALSE),"") -> 103.2 | G60: =VLOOKUP(B60,'[2]01_ALLCB基本資料'!C:U,16,FALSE)
A61: 1524 | B61: 15242 | C61: 耿鼎二 | D61: =IFERROR(VLOOKUP(B61,[1]最高價!$A:$C,3,FALSE),"") -> 100 | E61: =IFERROR(VLOOKUP(B61,[1]最低價!$A:$C,3,FALSE),"") -> 100 | G61: =VLOOKUP(B61,'[2]01_ALLCB基本資料'!C:U,16,FALSE) -> 38374
A62: 1524 | B62: 15243 | C62: 耿鼎三 | D62: =IFERROR(VLOOKUP(B62,[1]最高價!$A:$C,3,FALSE),"") -> 127 | E62: =IFERROR(VLOOKUP(B62,[1]最低價!$A:$C,3,FALSE),"") -> 101 | F62: 償還銀行借款3億 | G62: =VLOOKUP(B62,'[2]01_ALLCB基本資料'!C:U,16,FALSE) -> 40910 | H62: 償還銀行借款
A63: 1526 | B63: 15261 | C63: 日馳一 | D63: =IFERROR(VLOOKUP(B63,[1]最高價!$A:$C,3,FALSE),"") -> 104.8 | E63: =IFERROR(VLOOKUP(B63,[1]最低價!$A:$C,3,FALSE),"") -> 90.1 | F63: 充實營運資金1.69億，償還銀行借款3.5億 | G63: =VLOOKUP(B63,'[2]01_ALLCB基本資料'!C:U,16,FALSE) -> 45188 | H63: 償還+充實
A64: 1528 | B64: 15281 | C64: 恩德一 | D64: =IFERROR(VLOOKUP(B64,[1]最高價!$A:$C,3,FALSE),"") -> 132 | E64: =IFERROR(VLOOKUP(B64,[1]最低價!$A:$C,3,FALSE),"") -> 78.3 | G64: =VLOOKUP(B64,'[2]01_ALLCB基本資料'!C:U,16,FALSE)
A65: 1528 | B65: 15282 | C65: 恩德二 | D65: =IFERROR(VLOOKUP(B65,[1]最高價!$A:$C,3,FALSE),"") -> 149 | E65: =IFERROR(VLOOKUP(B65,[1]最低價!$A:$C,3,FALSE),"") -> 102 | G65: =VLOOKUP(B65,'[2]01_ALLCB基本資料'!C:U,16,FALSE) -> 40375
A66: 1529 | B66: 15291 | C66: 樂士一 | D66: =IFERROR(VLOOKUP(B66,[1]最高價!$A:$C,3,FALSE),"") -> 179 | E66: =IFERROR(VLOOKUP(B66,[1]最低價!$A:$C,3,FALSE),"") -> 54 | G66: =VLOOKUP(B66,'[2]01_ALLCB基本資料'!C:U,16,FALSE)
A67: 1530 | B67: 15301 | C67: 亞崴一 | D67: =IFERROR(VLOOKUP(B67,[1]最高價!$A:$C,3,FALSE),"") -> 115 | E67: =IFERROR(VLOOKUP(B67,[1]最低價!$A:$C,3,FALSE),"") -> 103 | G67: =VLOOKUP(B67,'[2]01_ALLCB基本資料'!C:U,16,FALSE)
A68: 1530 | B68: 15302 | C68: 亞崴二 | D68: =IFERROR(VLOOKUP(B68,[1]最高價!$A:$C,3,FALSE),"") -> 105 | E68: =IFERROR(VLOOKUP(B68,[1]最低價!$A:$C,3,FALSE),"") -> 98 | F68: 償還銀行借款4億 | G68: =VLOOKUP(B68,'[2]01_ALLCB基本資料'!C:U,16,FALSE) -> 42138 | H68: 償還銀行借款
A69: 1532 | B69: 15321 | C69: 勤美一 | D69: =IFERROR(VLOOKUP(B69,[1]最高價!$A:$C,3,FALSE),"") -> 225 | E69: =IFERROR(VLOOKUP(B69,[1]最低價!$A:$C,3,FALSE),"") -> 123 | G69: =VLOOKUP(B69,'[2]01_ALLCB基本資料'!C:U,16,FALSE)
A70: 1532 | B70: 15322 | C70: 勤美二 | D70: =IFERROR(VLOOKUP(B70,[1]最高價!$A:$C,3,FALSE),"") -> 211 | E70: =IFERROR(VLOOKUP(B70,[1]最低價!$A:$C,3,FALSE),"") -> 102.5 | G70: =VLOOKUP(B70,'[2]01_ALLCB基本資料'!C:U,16,FALSE)
A71: 1532 | B71: 15323 | C71: 勤美三 | D71: =IFERROR(VLOOKUP(B71,[1]最高價!$A:$C,3,FALSE),"") -> 338 | E71: =IFERROR(VLOOKUP(B71,[1]最低價!$A:$C,3,FALSE),"") -> 102 | G71: =VLOOKUP(B71,'[2]01_ALLCB基本資料'!C:U,16,FALSE)
A72: 1532 | B72: 15324 | C72: 勤美四 | D72: =IFERROR(VLOOKUP(B72,[1]最高價!$A:$C,3,FALSE),"") -> 184 | E72: =IFERROR(VLOOKUP(B72,[1]最低價!$A:$C,3,FALSE),"") -> 99.75 | F72: 償還銀行借款15億 | G72: =VLOOKUP(B72,'[2]01_ALLCB基本資料'!C:U,16,FALSE) -> 44585 | H72: 償還銀行借款
A73: 1533 | B73: 15331 | C73: 車王電一 | D73: =IFERROR(VLOOKUP(B73,[1]最高價!$A:$C,3,FALSE),"") -> 132 | E73: =IFERROR(VLOOKUP(B73,[1]最低價!$A:$C,3,FALSE),"") -> 103 | G73: =VLOOKUP(B73,'[2]01_ALLCB基本資料'!C:U,16,FALSE)
A74: 1533 | B74: 15332 | C74: 車王電二 | D74: =IFERROR(VLOOKUP(B74,[1]最高價!$A:$C,3,FALSE),"") -> 111 | E74: =IFERROR(VLOOKUP(B74,[1]最低價!$A:$C,3,FALSE),"") -> 93.5 | F74: 償還銀行借款10億，充實營運資金0.55億 | G74: =VLOOKUP(B74,'[2]01_ALLCB基本資料'!C:U,16,FALSE) -> 44587 | H74: 償還+充實
A75: 1535 | B75: 15351 | C75: 中宇一 | D75: =IFERROR(VLOOKUP(B75,[1]最高價!$A:$C,3,FALSE),"") -> 164 | E75: =IFERROR(VLOOKUP(B75,[1]最低價!$A:$C,3,FALSE),"") -> 104 | F75: 充實營運資金4.5億，轉投資中宇越南1.5億 | G75: =VLOOKUP(B75,'[2]01_ALLCB基本資料'!C:U,16,FALSE) -> 40959 | H75: 充實營運資金
A76: 1536 | B76: 15361 | C76: 和大一 | D76: =IFERROR(VLOOKUP(B76,[1]最高價!$A:$C,3,FALSE),"") -> 231 | E76: =IFERROR(VLOOKUP(B76,[1]最低價!$A:$C,3,FALSE),"") -> 97.1 | G76: =VLOOKUP(B76,'[2]01_ALLCB基本資料'!C:U,16,FALSE)
A77: 1536 | B77: 15362 | C77: 和大二 | D77: =IFERROR(VLOOKUP(B77,[1]最高價!$A:$C,3,FALSE),"") -> 141.5 | E77: =IFERROR(VLOOKUP(B77,[1]最低價!$A:$C,3,FALSE),"") -> 82.15 | G77: =VLOOKUP(B77,'[2]01_ALLCB基本資料'!C:U,16,FALSE) -> 38906
A78: 1536 | B78: 15363 | C78: 和大三 | D78: =IFERROR(VLOOKUP(B78,[1]最高價!$A:$C,3,FALSE),"") -> 765 | E78: =IFERROR(VLOOKUP(B78,[1]最低價!$A:$C,3,FALSE),"") -> 725 | G78: =VLOOKUP(B78,'[2]01_ALLCB基本資料'!C:U,16,FALSE) -> 40122
A79: 1536 | B79: 15364 | C79: 和大四 | D79: =IFERROR(VLOOKUP(B79,[1]最高價!$A:$C,3,FALSE),"") -> 130.3 | E79: =IFERROR(VLOOKUP(B79,[1]最低價!$A:$C,3,FALSE),"") -> 93.9 | F79: 償還銀行借款15億，發行CB4共15000張，詢圈100發行 | G79: =VLOOKUP(B79,'[2]01_ALLCB基本資料'!C:U,16,FALSE) -> 45516 | H79: 借新還舊
A80: 1537 | B80: 15371 | C80: 廣隆一 | D80: =IFERROR(VLOOKUP(B80,[1]最高價!$A:$C,3,FALSE),"") -> 225 | E80: =IFERROR(VLOOKUP(B80,[1]最低價!$A:$C,3,FALSE),"") -> 83 | G80: =VLOOKUP(B80,'[2]01_ALLCB基本資料'!C:U,16,FALSE) -> 39413
A81: 1541 | B81: 15411 | C81: 錩泰一 | D81: =IFERROR(VLOOKUP(B81,[1]最高價!$A:$C,3,FALSE),"") -> 129.45 | E81: =IFERROR(VLOOKUP(B81,[1]最低價!$A:$C,3,FALSE),"") -> 77 | G81: =VLOOKUP(B81,'[2]01_ALLCB基本資料'!C:U,16,FALSE)
A82: 1560 | B82: 15601 | C82: 中砂一 | D82: =IFERROR(VLOOKUP(B82,[1]最高價!$A:$C,3,FALSE),"") -> 141.85 | E82: =IFERROR(VLOOKUP(B82,[1]最低價!$A:$C,3,FALSE),"") -> 98.7 | F82: 償還銀行借款11.83億 | G82: =VLOOKUP(B82,'[2]01_ALLCB基本資料'!C:U,16,FALSE) -> 45467 | H82: 償還銀行借款
A83: 1566 | B83: 15661 | C83: 捷邦一 | D83: =IFERROR(VLOOKUP(B83,[1]最高價!$A:$C,3,FALSE),"") -> 124.85 | E83: =IFERROR(VLOOKUP(B83,[1]最低價!$A:$C,3,FALSE),"") -> 94 | G83: =VLOOKUP(B83,'[2]01_ALLCB基本資料'!C:U,16,FALSE) -> 41257
A84: 1569 | B84: 15691 | C84: 濱川一 | D84: =IFERROR(VLOOKUP(B84,[1]最高價!$A:$C,3,FALSE),"") -> 207 | E84: =IFERROR(VLOOKUP(B84,[1]最低價!$A:$C,3,FALSE),"") -> 92.25 | G84: =VLOOKUP(B84,'[2]01_ALLCB基本資料'!C:U,16,FALSE)
A85: 1569 | B85: 15692 | C85: 濱川二 | D85: =IFERROR(VLOOKUP(B85,[1]最高價!$A:$C,3,FALSE),"") -> 182 | E85: =IFERROR(VLOOKUP(B85,[1]最低價!$A:$C,3,FALSE),"") -> 107 | G85: =VLOOKUP(B85,'[2]01_ALLCB基本資料'!C:U,16,FALSE) -> 40196
A86: 1569 | B86: 15693 | C86: 濱川三 | D86: =IFERROR(VLOOKUP(B86,[1]最高價!$A:$C,3,FALSE),"") -> 162 | E86: =IFERROR(VLOOKUP(B86,[1]最低價!$A:$C,3,FALSE),"") -> 107 | G86: =VLOOKUP(B86,'[2]01_ALLCB基本資料'!C:U,16,FALSE) -> 40197
A87: 1569 | B87: 15694 | C87: 濱川四 | D87: =IFERROR(VLOOKUP(B87,[1]最高價!$A:$C,3,FALSE),"") -> 136.95 | E87: =IFERROR(VLOOKUP(B87,[1]最低價!$A:$C,3,FALSE),"") -> 101 | F87: 現金增資2億，5000張/40元，濱川四募得2億，償還銀行借款2億，轉投資2億 | G87: =VLOOKUP(B87,'[2]01_ALLCB基本資料'!C:U,16,FALSE) -> 41255 | H87: 償還銀行借款
A88: 1569 | B88: 15695 | C88: 濱川五 | D88: =IFERROR(VLOOKUP(B88,[1]最高價!$A:$C,3,FALSE),"") -> 187 | E88: =IFERROR(VLOOKUP(B88,[1]最低價!$A:$C,3,FALSE),"") -> 100.2 | F88: 現金增資1.75億，10000張/17.5元，濱川五募得2億，償還銀行借款3.75億 | G88: =VLOOKUP(B88,'[2]01_ALLCB基本資料'!C:U,16,FALSE) -> 42039 | H88: 償還銀行借款
A89: 1569 | B89: 15696 | C89: 濱川六 | D89: =IFERROR(VLOOKUP(B89,[1]最高價!$A:$C,3,FALSE),"") -> 149 | E89: =IFERROR(VLOOKUP(B89,[1]最低價!$A:$C,3,FALSE),"") -> 95 | F89: 償還銀行借款6億 | G89: =VLOOKUP(B89,'[2]01_ALLCB基本資料'!C:U,16,FALSE) -> 43523 | H89: 償還銀行借款
A90: 1582 | B90: 15821 | C90: 信錦一 | D90: =IFERROR(VLOOKUP(B90,[1]最高價!$A:$C,3,FALSE),"") -> 130.8 | E90: =IFERROR(VLOOKUP(B90,[1]最低價!$A:$C,3,FALSE),"") -> 97.6 | G90: =VLOOKUP(B90,'[2]01_ALLCB基本資料'!C:U,16,FALSE) -> 40593
A91: 1582 | B91: 15822 | C91: 信錦二 | D91: =IFERROR(VLOOKUP(B91,[1]最高價!$A:$C,3,FALSE),"") -> 147 | E91: =IFERROR(VLOOKUP(B91,[1]最低價!$A:$C,3,FALSE),"") -> 98.5 | F91: 償還銀行借款6.24億，轉投資子公司(昆山鴻嘉駿)1.82億 | G91: =VLOOKUP(B91,'[2]01_ALLCB基本資料'!C:U,16,FALSE) -> 42024 | H91: 償還銀行借款
A92: 1582 | B92: 15823 | C92: 信錦三 | D92: =IFERROR(VLOOKUP(B92,[1]最高價!$A:$C,3,FALSE),"") -> 203 | E92: =IFERROR(VLOOKUP(B92,[1]最低價!$A:$C,3,FALSE),"") -> 101 | F92: 償還銀行借款8.35億，轉投資子公司4.28億 | G92: =VLOOKUP(B92,'[2]01_ALLCB基本資料'!C:U,16,FALSE) -> 44448 | H92: 償還銀行借款
A93: 1583 | B93: 15831 | C93: 程泰一 | D93: =IFERROR(VLOOKUP(B93,[1]最高價!$A:$C,3,FALSE),"") -> 106.8 | E93: =IFERROR(VLOOKUP(B93,[1]最低價!$A:$C,3,FALSE),"") -> 95.05 | F93: 償還金融機構借款6.03億 | G93: =VLOOKUP(B93,'[2]01_ALLCB基本資料'!C:U,16,FALSE) -> 42074 | H93: 償還銀行借款
A94: 1584 | B94: 15841 | C94: 精剛一 | D94: =IFERROR(VLOOKUP(B94,[1]最高價!$A:$C,3,FALSE),"") -> 117.7 | E94: =IFERROR(VLOOKUP(B94,[1]最低價!$A:$C,3,FALSE),"") -> 93 | G94: =VLOOKUP(B94,'[2]01_ALLCB基本資料'!C:U,16,FALSE)
A95: 1584 | B95: 15842 | C95: 精剛二 | D95: =IFERROR(VLOOKUP(B95,[1]最高價!$A:$C,3,FALSE),"") -> 113 | E95: =IFERROR(VLOOKUP(B95,[1]最低價!$A:$C,3,FALSE),"") -> 100 | F95: 現金增資1.93億，精剛二募得2.87億，償還銀行借款4.67億，充實營運資金0.2億 | G95: =VLOOKUP(B95,'[2]01_ALLCB基本資料'!C:U,16,FALSE) -> 41023 | H95: 償還+充實
A96: 1586 | B96: 15861 | C96: 和勤一 | D96: =IFERROR(VLOOKUP(B96,[1]最高價!$A:$C,3,FALSE),"") -> 189 | E96: =IFERROR(VLOOKUP(B96,[1]最低價!$A:$C,3,FALSE),"") -> 100.2 | F96: 償還銀行借款3億 | G96: =VLOOKUP(B96,'[2]01_ALLCB基本資料'!C:U,16,FALSE) -> 42017 | H96: 償還銀行借款
A97: 1586 | B97: 15862 | C97: 和勤二 | D97: =IFERROR(VLOOKUP(B97,[1]最高價!$A:$C,3,FALSE),"") -> 127.5 | E97: =IFERROR(VLOOKUP(B97,[1]最低價!$A:$C,3,FALSE),"") -> 99.5 | F97: 償還銀行借款4億 | G97: =VLOOKUP(B97,'[2]01_ALLCB基本資料'!C:U,16,FALSE) -> 44074 | H97: 償還銀行借款
A98: 1586 | B98: 15863 | C98: 和勤三 | D98: =IFERROR(VLOOKUP(B98,[1]最高價!$A:$C,3,FALSE),"") -> 125.25 | E98: =IFERROR(VLOOKUP(B98,[1]最低價!$A:$C,3,FALSE),"") -> 98.55 | F98: 償還銀行借款4億 | G98: =VLOOKUP(B98,'[2]01_ALLCB基本資料'!C:U,16,FALSE) -> 44075 | H98: 償還銀行借款
A99: 1586 | B99: 15864 | C99: 和勤四 | D99: =IFERROR(VLOOKUP(B99,[1]最高價!$A:$C,3,FALSE),"") -> 124 | E99: =IFERROR(VLOOKUP(B99,[1]最低價!$A:$C,3,FALSE),"") -> 105 | F99: 償還國內第二次第三次有擔保轉換公司債3.85億，償還銀行借款1.14億，充實營運資金0.14億，與和勤五同時發行 | G99: =VLOOKUP(B99,'[2]01_ALLCB基本資料'!C:U,16,FALSE) -> 45168 | H99: 借新還舊
A100: 1586 | B100: 15865 | C100: 和勤五 | D100: =IFERROR(VLOOKUP(B100,[1]最高價!$A:$C,3,FALSE),"") -> 114.5 | E100: =IFERROR(VLOOKUP(B100,[1]最低價!$A:$C,3,FALSE),"") -> 93.55 | F100: 償還國內第二次第三次有擔保轉換公司債3.85億，償還銀行借款1.14億，充實營運資金0.14億，與和勤四同時發行 | G100: =VLOOKUP(B100,'[2]01_ALLCB基本資料'!C:U,16,FALSE) -> 45169 | H100: 借新還舊
...

Sheet 01_ALLCB基本資料
A1: 序號 | B1: 股票代號 | C1: CB代號 | D1: 名稱 | E1: 信用評等 | F1: 擔保 | G1: 發行規模 | H1: 轉換價格 | I1: 發行年期 | J1: 詢圈競拍 | K1: 發行券商 | L1: 產業分類 | M1: 產業地位 | N1: 股本大小 | O1: 發行價格 | P1: 到期還本價格 | Q1: 訂價溢價率 | R1: 掛牌日期 | S1: 到期日期 | T1: 掛牌最高 | U1: 掛牌最低
A2: 1 | B2: 1101 | C2: 11011 | D2: 台泥一永 | E2: 4 | F2: 無擔保 | G2: 80 | H2: 36.5 | I2: 5 | J2: 詢圈 | K2: 元大證券 | L2: 水泥工業 | M2: 台灣最大水泥廠 | N2: 775 | O2: 100 | P2: 100 | Q2: 1.0918 | R2: 45636 | S2: 47462 | T2: 108.1 | U2: 94.4
A3: 2 | B3: 1210 | C3: 12101 | D3: 大成一 | E3: 0 | F3: 0 | G3: 10 | H3: 33.59 | I3: 5 | J3: 詢圈 | L3: 食品工業 | M3: 兩岸最大白肉雞電宰加工廠及飼料大廠 | R3: 39336 | S3: 2012/09/11 | T3: 127 | U3: 72.5
A4: 3 | B4: 1216 | C4: 12161 | D4: 統一一 | E4: 0 | G4: 50 | H4: 48.6 | I4: 3 | J4: 詢圈 | L4: 食品工業 | M4: 台灣食品業龍頭廠之一 | R4: 39370 | S4: 2010/10/15 | T4: 106.75 | U4: 91.2
A5: 4 | B5: 1217 | C5: 12171 | D5: 愛之味一 | E5: 0 | G5: 11 | H5: 13.9 | I5: 3 | J5: 詢圈 | L5: 食品工業 | M5: 以飲料、傳統類罐頭為主的食品商 | R5: 40664 | S5: 2014/05/01 | T5: 123 | U5: 100
A6: 5 | B6: 1217 | C6: 12172 | D6: 愛之味二 | E6: 0 | G6: 3 | H6: 13.9 | I6: 5 | J6: 詢圈 | K6: 台新證券 | L6: 食品工業 | M6: 以飲料、傳統類罐頭為主的食品商 | O6: 100 | P6: 100 | R6: 40675 | S6: 42502 | T6: 112 | U6: 89
A7: 6 | B7: 1217 | C7: 12173 | D7: 愛之味三 | E7: 7 | F7: 無擔保 | G7: 10 | H7: 10.9 | I7: 5 | J7: 詢圈 | K7: 台新證券 | L7: 食品工業 | M7: 以飲料、傳統類罐頭為主的食品商 | N7: 49.5 | O7: 100 | P7: 100 | Q7: 1.0139 | R7: 41340 | S7: 43166 | T7: 105 | U7: 99.6
A8: 7 | B8: 1218 | C8: 12181 | D8: 泰山一 | E8: 新光銀行 | F8: 有擔保 | G8: 5 | H8: 15.1 | I8: 3 | J8: 詢圈 | K8: 群益證券 | L8: 食品工業 | M8: 台灣油脂、飲料大廠及轉投資全家便利超商 | N8: 50 | O8: 100 | P8: 100 | Q8: 1.0155 | R8: 41417 | S8: 42513 | T8: 109.9 | U8: 99
A9: 8 | B9: 1225 | C9: 12251 | D9: 福脂一 | E9: 0 | G9: 5 | H9: 14 | I9: 5 | J9: 詢圈 | L9: 食品工業 | M9: 台灣油脂、飼料大廠 | R9: 40158 | S9: 2014/12/11 | T9: 233 | U9: 101
A10: 9 | B10: 1258 | C10: 12581 | D10: 其祥一K | H10: 38.8 | J10: 詢圈 | K10: 台中銀證 | P10: 100 | R10: 42262 | S10: 43358 | T10: 124.25 | U10: 99.1
A11: 10 | B11: 1258 | C11: 12582 | D11: 其祥二K | H11: 30 | J11: 詢圈 | K11: 國票證券 | P11: 100 | R11: 43353 | S11: 45179 | T11: 101.3 | U11: 76.2
A12: 11 | B12: 1312 | C12: 13121 | D12: 國喬一 | I12: 3 | J12: 詢圈 | L12: 塑膠工業 | M12: 台灣第二大SM及ABS廠 | T12: 171 | U12: 90
A13: 12 | B13: 1316 | C13: 13161 | D13: 上曜一 | E13: 板信商銀 | F13: 有擔保 | G13: 3 | H13: 24.9 | I13: 3 | J13: 詢圈 | K13: 元大證券 | L13: 建材營造業 | M13: 上曜集團旗下豪宅品牌 | N13: 27.9 | Q13: 1.01 | R13: 40757 | S13: 2014/07/23 | T13: 122 | U13: 99.65
A14: 13 | B14: 1316 | C14: 13162 | D14: 上曜二 | E14: 板信商銀 | F14: 有擔保 | G14: 2 | H14: 12 | I14: 3 | J14: 詢圈 | K14: 元富證券 | L14: 建材營造業 | M14: 上曜集團旗下豪宅品牌 | N14: 27.9 | O14: 100 | P14: 100 | Q14: 1.0161 | R14: 41996 | S14: 43092 | T14: 177 | U14: 104
A15: 14 | B15: 1316 | C15: 13163 | D15: 上曜三 | E15: 元大銀行 | F15: 有擔保 | G15: 5 | H15: 20.1 | I15: 3 | J15: 詢圈 | K15: 元富證券 | L15: 建材營造業 | M15: 上曜集團旗下豪宅品牌 | N15: 27.9 | O15: 100 | P15: 100 | Q15: 1.1519 | R15: 43411 | S15: 44507 | T15: 117.95 | U15: 99.6
A16: 15 | B16: 1316 | C16: 13164 | D16: 上曜四 | E16: 日盛銀行 | F16: 有擔保 | G16: 4 | H16: 14.9 | I16: 5 | J16: 詢圈 | K16: 富邦證券 | L16: 建材營造業 | M16: 上曜集團旗下豪宅品牌 | N16: 27.9 | O16: 101 | P16: 100 | Q16: 1.2 | R16: 44225 | S16: 46051 | T16: 189 | U16: 101.5
A17: 16 | B17: 1316 | C17: 13165 | D17: 上曜五 | E17: 8 | F17: 無擔保 | G17: 4 | H17: 12.6 | I17: 3 | J17: 詢圈 | K17: 富邦證券 | L17: 建材營造業 | M17: 上曜集團旗下豪宅品牌 | N17: 27.9 | O17: 100 | P17: 100 | Q17: 1.02 | R17: 44228 | S17: 45323 | T17: 232 | U17: 99.6
A18: 17 | B18: 1316 | C18: 13166 | D18: 上曜六 | E18: 板信銀行 | F18: 有擔保 | G18: 4 | H18: 17.8 | I18: 3 | J18: 競拍 | K18: 元富證券 | O18: 100 | P18: 100 | Q18: 1.1995 | R18: 45653 | S18: 46748 | T18: 125.5 | U18: 102.8
A19: 18 | B19: 1319 | C19: 13191 | D19: 東陽一 | E19: 0 | G19: 10 | H19: 50.9 | I19: 5 | J19: 詢圈 | L19: 汽車工業 | M19: 全球第一大汽車AM塑膠件製造商 | R19: 40536 | S19: 2015/12/24 | T19: 115 | U19: 95.4
A20: 19 | B20: 1336 | C20: 13361 | D20: 台翰一 | E20: 台灣中小企 | F20: 有擔保 | G20: 3.5 | H20: 16.58 | I20: 3 | J20: 詢圈 | K20: 國泰證券 | L20: 電子零組件業 | M20: 宣德轉投資之消費電子產品外殼製造商 | N20: 7.88 | O20: 100.5 | P20: 103.03 | Q20: 1.0303 | R20: 41892 | S20: 42988 | T20: 116 | U20: 101.1
A21: 20 | B21: 1337 | C21: 13371 | D21: 再生一 | E21: 4 | F21: 無擔保 | G21: 6 | H21: 101.6 | I21: 3 | J21: 詢圈 | K21: 元大證券 | L21: 塑膠工業 | M21: 大陸第一大EVA發泡材商 | N21: 26.9 | Q21: 1.05 | R21: 41193 | S21: 2015/10/01 | T21: 120.5 | U21: 82.95
A22: 21 | B22: 1338 | C22: 13381 | D22: 廣華一K | E22: 5 | F22: 無擔保 | G22: 6 | H22: 68.8 | I22: 5 | J22: 詢圈 | K22: 國票證券 | L22: 汽車工業 | M22: 汽車OEM塑膠內飾件大廠，供應以大陸市場為主 | N22: 8.38 | O22: 100 | P22: 100 | Q22: 1.0208 | R22: 44215 | S22: 46041 | T22: 117 | U22: 97.1
A23: 22 | B23: 1338 | C23: 13382 | D23: 廣華二K | E23: 5 | F23: 無擔保 | G23: 6 | H23: 39.4 | I23: 5 | J23: 詢圈 | K23: 國票證券 | L23: 汽車工業 | M23: 汽車OEM塑膠內飾件大廠，供應以大陸市場為主 | N23: 8.38 | O23: 100 | P23: 100 | Q23: 1.051 | R23: 45261 | S23: 47088 | T23: 115.5 | U23: 93.05
A24: 23 | B24: 1341 | C24: 13411 | D24: 富林一K | E24: 6 | F24: 無擔保 | G24: 1.5 | H24: 75.8 | I24: 3 | J24: 競拍 | K24: 中信證券 | L24: 塑膠工業 | M24: 越南第一大PVC人造皮革生產商 | N24: 5.17 | O24: 115 | P24: 101.51 | Q24: 1.0218 | R24: 44329 | S24: 45425 | T24: 116.9 | U24: 100.8
A25: 24 | B25: 1342 | C25: 13421 | D25: 八貫一 | E25: 華南銀行 | F25: 有擔保 | G25: 2 | H25: 72 | I25: 3 | J25: 競拍 | K25: 元大證券 | L25: 其他業 | M25: 台灣機能性皮布料及薄膜製造商 | N25: 7.13 | O25: 112.93 | P25: 100 | Q25: 1.0381 | R25: 44714 | S25: 45810 | T25: 243 | U25: 106.5
A26: 25 | B26: 1409 | C26: 14093 | D26: 新纖三 | E26: 0 | G26: 22 | H26: 9.93 | I26: 5 | J26: 詢圈 | L26: 紡織纖維 | M26: 新光集團旗下，台灣知名化纖廠 | R26: 39189 | S26: 2012/04/17 | T26: 180 | U26: 77
A27: 26 | B27: 1432 | C27: 14321 | D27: 大魯閣一 | E27: 有擔保 | F27: 有擔保 | G27: 2.5 | H27: 20.1 | I27: 3 | J27: 詢圈 | K27: 元大證券 | L27: 運動休閒 | M27: 經營型娛樂購物中心事業 | N27: 9 | O27: 100 | P27: 103.8 | Q27: 1.0177 | R27: 42047 | S27: 43143 | T27: 119 | U27: 100.5
A28: 27 | B28: 1432 | C28: 14322 | D28: 大魯閣二 | E28: 8 | F28: 無擔保 | G28: 2.5 | H28: 20.1 | I28: 5 | J28: 詢圈 | K28: 元大證券 | L28: 運動休閒 | M28: 經營型娛樂購物中心事業 | N28: 9 | O28: 100 | P28: 100 | Q28: 1.01 | R28: 42048 | S28: 43874 | T28: 119.1 | U28: 92.3
A29: 28 | B29: 1436 | C29: 14361 | D29: 華友聯一 | E29: 第一銀行 | F29: 有擔保 | G29: 3 | H29: 40 | I29: 5 | J29: 競拍 | K29: 第一金證 | L29: 建材營造業 | M29: 以市地重劃為基礎且針對首購族市場的建商 | N29: 9.8 | O29: 107.73 | P29: 100 | Q29: 1.0521 | R29: 43847 | S29: 45674 | T29: 695 | U29: 106
A30: 29 | B30: 1436 | C30: 14362 | D30: 華友聯二 | E30: 第一銀行 | F30: 有擔保 | G30: 10 | H30: 42 | I30: 5 | J30: 詢圈 | K30: 第一金證 | L30: 建材營造業 | M30: 以市地重劃為基礎且針對首購族市場的建商 | N30: 9.8 | O30: 101 | P30: 100 | Q30: 1.0805 | R30: 44166 | S30: 45992 | T30: 600 | U30: 111.1
A31: 30 | B31: 1436 | C31: 14363 | D31: 華友聯三 | E31: 8 | F31: 無擔保 | G31: 6 | H31: 182.5 | I31: 3 | J31: 詢圈 | K31: 國泰證券 | L31: 建材營造業 | M31: 以市地重劃為基礎且針對首購族市場的建商 | N31: 11.4 | O31: 100 | P31: 104.5678 | Q31: 1.051 | R31: 45531 | S31: 46626 | T31: 124.25 | U31: 93.6
A32: 31 | B32: 1436 | C32: 14364 | D32: 華友聯四 | E32: 8 | F32: 無擔保 | G32: 20 | H32: 140.3 | I32: 3 | J32: 詢圈 | K32: 國泰證券 | L32: 建材營造業 | M32: 以市地重劃為基礎且針對首購族市場的建商 | N32: 11.4 | O32: 101 | P32: 104.5678 | Q32: 1.02 | R32: 45734 | S32: 46830 | T32: 104.95 | U32: 92.5
A33: 32 | B33: 1437 | C33: 14371 | D33: 勤益一 | E33: 0 | I33: 5 | J33: 詢圈 | L33: 其他業 | M33: 投資控股公司，從事地產、紡織貿易及投資事業 | T33: 266 | U33: 92
A34: 33 | B34: 1438 | C34: 14381 | D34: 三地開發一 | E34: 有擔保 | F34: 有擔保 | G34: 10 | H34: 57.5 | I34: 5 | J34: 競拍 | K34: 統一證券 | L34: 建材營造業 | M34: 開發以台南及高雄地區為主力的建商 | N34: 9.12 | O34: 117.63 | P34: 102.5251 | Q34: 1.0201 | R34: 45645 | S34: 47471 | T34: 134 | U34: 119
A35: 34 | B35: 1442 | C35: 14422 | D35: 名軒二 | E35: 台銀 | F35: 有擔保 | G35: 8 | H35: 26.5 | I35: 3 | J35: 詢圈 | K35: 凱基證券 | L35: 建材營造業 | M35: 麗寶集團旗下成員 | N35: 36.6 | Q35: 1.0271 | R35: 41122 | S35: 2015/07/22 | T35: 165 | U35: 105.55
A36: 35 | B36: 1442 | C36: 14423 | D36: 名軒三 | E36: 台灣銀行 | F36: 有擔保 | G36: 8 | H36: 17.9 | I36: 5 | J36: 詢圈 | K36: 凱基證券 | L36: 建材營造業 | M36: 麗寶集團旗下成員 | N36: 36.6 | O36: 100 | P36: 100 | Q36: 1.0142 | R36: 42339 | S36: 44166 | T36: 188 | U36: 105
A37: 36 | B37: 1457 | C37: 14571 | D37: 宜進一 | E37: 7 | F37: 無擔保 | G37: 3 | H37: 10 | I37: 3 | J37: 詢圈 | K37: 福邦證券 | L37: 紡織纖維 | M37: 台灣前五大加工絲廠之一 | N37: 30.2 | Q37: 1.0162 | R37: 40724 | S37: 2014/06/20 | T37: 109.8 | U37: 90
A38: 37 | B38: 1464 | C38: 14641 | D38: 得力一 | E38: 合庫銀行 | F38: 有擔保 | G38: 2 | H38: 24.6 | I38: 3 | J38: 詢圈 | K38: 合庫證券 | L38: 紡織纖維 | M38: 台灣老牌織染一貫化布廠 | N38: 40.8 | O38: 100 | P38: 0 | Q38: 1.04 | R38: 42144 | S38: 43240 | T38: 172 | U38: 107
A39: 38 | B39: 1464 | C39: 14642 | D39: 得力二 | E39: 6 | F39: 無擔保 | G39: 2.5 | H39: 24 | I39: 3 | J39: 詢圈 | K39: 合庫證券 | L39: 紡織纖維 | M39: 台灣老牌織染一貫化布廠 | N39: 40.8 | O39: 100 | P39: 0 | Q39: 1.017 | R39: 42145 | S39: 43241 | T39: 177 | U39: 103
A40: 39 | B40: 1466 | C40: 14661 | D40: 聚隆一 | E40: 合庫擔 | F40: 有擔保 | G40: 3 | H40: 32.8 | I40: 3 | J40: 詢圈 | K40: 元大證券 | L40: 紡織纖維 | M40: 台灣第二大的尼龍加工絲廠 | N40: 11.1 | Q40: 1.011 | R40: 40693 | S40: 2014/05/20 | T40: 127 | U40: 98
A41: 40 | B41: 1466 | C41: 14662 | D41: 聚隆二 | E41: 5 | F41: 無擔保 | G41: 3 | H41: 20.1 | I41: 5 | J41: 詢圈 | K41: 福邦證券 | L41: 紡織纖維 | M41: 台灣第二大的尼龍加工絲廠 | N41: 11.1 | O41: 100 | P41: 100 | Q41: 1.01 | R41: 41288 | S41: 43114 | T41: 147.5 | U41: 102.75
A42: 41 | B42: 1466 | C42: 14663 | D42: 聚隆三 | E42: 5 | F42: 無擔保 | G42: 4 | H42: 22.6 | I42: 5 | J42: 詢圈 | K42: 福邦證券 | L42: 紡織纖維 | M42: 台灣第二大的尼龍加工絲廠 | N42: 11.1 | O42: 100 | P42: 100 | Q42: 1.01 | R42: 41906 | S42: 43732 | T42: 109 | U42: 98
A43: 42 | B43: 1467 | C43: 14671 | D43: 南緯一 | E43: 0 | J43: 詢圈 | L43: 紡織纖維 | M43: 為品牌大廠代工及與Wal-mart合作的成衣廠 | T43: 142.2 | U43: 101.5
A44: 43 | B44: 1472 | C44: 14721 | D44: 三洋實業一 | E44: 合庫銀 | F44: 有擔保 | G44: 3 | H44: 29.99 | I44: 3 | J44: 詢圈 | K44: 合庫證券 | L44: 建材營造業 | M44: 承建公共工程、商辦、住宅等營造工程 | N44: 4.25 | O44: 101 | P44: 100 | Q44: 1.02 | R44: 43495 | S44: 44591 | T44: 124.5 | U44: 99.1
A45: 44 | B45: 1474 | C45: 14741 | D45: 弘裕一 | E45: 0 | J45: 詢圈 | L45: 紡織纖維 | M45: 台灣最大的工業用布廠 | T45: 125 | U45: 100
A46: 45 | B46: 1474 | C46: 14742 | D46: 弘裕二 | E46: 6 | F46: 無擔保 | G46: 3 | H46: 16 | I46: 3 | J46: 競拍 | K46: 兆豐證券 | L46: 紡織纖維 | M46: 台灣最大的工業用布廠 | N46: 13 | O46: 109.01 | P46: 101.5075 | Q46: 1.0224 | R46: 44587 | S46: 45683 | T46: 117 | U46: 96
A47: 46 | B47: 1474 | C47: 14743 | D47: 弘裕三 | E47: 6 | F47: 無擔保 | G47: 3 | H47: 14.5 | I47: 3 | J47: 競拍 | K47: 兆豐證券 | L47: 紡織纖維 | M47: 台灣最大的工業用布廠 | N47: 13 | O47: 101.5 | P47: 101.5075 | Q47: 1.0283 | R47: 45747 | S47: 46843 | T47: 99.95 | U47: 89.5
A48: 47 | B48: 1477 | C48: 14771 | D48: 聚陽一 | E48: 0 | I48: 5 | J48: 詢圈 | L48: 紡織纖維 | M48: 全球第五大、台灣第一大成衣代工廠 | T48: 386 | U48: 110
A49: 48 | B49: 1477 | C49: 14772 | D49: 聚陽二 | E49: 0 | I49: 5 | J49: 詢圈 | L49: 紡織纖維 | M49: 全球第五大、台灣第一大成衣代工廠 | T49: 292 | U49: 100
A50: 49 | B50: 1477 | C50: 14773 | D50: 聚陽三 | E50: 0 | G50: 6 | H50: 44.8 | I50: 5 | J50: 詢圈 | L50: 紡織纖維 | M50: 全球第五大、台灣第一大成衣代工廠 | R50: 39976 | S50: 2014/06/12 | T50: 495 | U50: 106.5
A51: 50 | B51: 1477 | C51: 14774 | D51: 聚陽四 | E51: 3 | F51: 無擔保 | G51: 7 | H51: 85.2 | I51: 5 | J51: 詢圈 | K51: 元富證券 | L51: 紡織纖維 | M51: 全球第五大、台灣第一大成衣代工廠 | N51: 24.2 | O51: 100 | P51: 100 | Q51: 1.01 | R51: 41145 | S51: 42971 | T51: 401 | U51: 106.2
A52: 51 | B52: 1504 | C52: 15043 | D52: 東元三 | E52: 4 | F52: 無擔保 | G52: 30 | H52: 22.5 | I52: 3 | J52: 詢圈 | K52: 富邦證券 | L52: 電機機械 | M52: 多角化經營的台灣老牌家電廠 | N52: 214 | Q52: 1.15 | R52: 41102 | S52: 2015/07/02 | T52: 167 | U52: 99.05
A53: 52 | B53: 1506 | C53: 15061 | D53: 正道一 | E53: 安泰銀行 | F53: 有擔保 | G53: 7 | H53: 24.18 | I53: 3 | J53: 詢圈 | K53: 統一證券 | L53: 電機機械 | M53: 台灣知名活塞與汽車鍛件製造商 | N53: 30 | O53: 100 | P53: 100 | Q53: 1.0147 | R53: 42027 | S53: 43123 | T53: 121 | U53: 96.95
A54: 53 | B54: 1513 | C54: 15131 | D54: 中興電一 | E54: 5 | F54: 無擔保 | G54: 15 | H54: 27.7 | I54: 5 | J54: 詢圈 | K54: 凱基證券 | L54: 電機機械 | M54: 台灣知名重電及機電工程廠商 | N54: 50.3 | O54: 100.35 | P54: 100 | Q54: 1.0983 | R54: 43846 | S54: 45673 | T54: 213 | U54: 101
A55: 54 | B55: 1513 | C55: 15132 | D55: 中興電二 | E55: 5 | F55: 無擔保 | G55: 15 | H55: 61.4 | I55: 5 | J55: 詢圈 | K55: 凱基證券 | L55: 電機機械 | M55: 台灣知名重電及機電工程廠商 | N55: 50.3 | O55: 100.4 | P55: 100 | Q55: 1.0407 | R55: 44182 | S55: 46008 | T55: 231 | U55: 106
A56: 55 | B56: 1514 | C56: 15141 | D56: 亞力一 | E56: 6 | F56: 無擔保 | G56: 10 | H56: 67 | I56: 5 | J56: 詢圈 | K56: 華南永昌 | L56: 電機機械 | M56: 生產配電盤、電力變壓器為主的電機公司 | N56: 25.3 | O56: 100.5 | P56: 100 | Q56: 1.0983 | R56: 45155 | S56: 46982 | T56: 276 | U56: 103.8
A57: 56 | B57: 1514 | C57: 15142 | D57: 亞力二 | E57: 6 | F57: 無擔保 | G57: 12 | H57: 113.2 | I57: 5 | J57: 詢圈 | K57: 元大證券 | L57: 電機機械 | M57: 生產配電盤、電力變壓器為主的電機公司 | N57: 26.2 | O57: 100.5 | P57: 100 | Q57: 1.13 | R57: 45670 | S57: 47496 | T57: 127 | U57: 99.45
A58: 57 | B58: 1515 | C58: 15151 | D58: 力山一 | E58: 0 | J58: 詢圈 | L58: 電機機械 | M58: 台灣知名健身器材代工廠 | T58: 131 | U58: 122
A59: 58 | B59: 1522 | C59: 15221 | D59: 堤維西一 | E59: 0 | J59: 詢圈 | L59: 汽車工業 | M59: 專攻AM市場之台灣第二大車燈製造商 | T59: 142 | U59: 92
A60: 59 | B60: 1524 | C60: 15241 | D60: 耿鼎一 | E60: 0 | J60: 詢圈 | L60: 汽車工業 | M60: 為汽車AM鈑金件製造商 | T60: 195 | U60: 103.2
A61: 60 | B61: 1524 | C61: 15242 | D61: 耿鼎二 | E61: 0 | G61: 4 | I61: 5 | J61: 詢圈 | L61: 汽車工業 | M61: 為汽車AM鈑金件製造商 | R61: 38374 | S61: 2010/01/22 | T61: 100 | U61: 100
A62: 61 | B62: 1524 | C62: 15243 | D62: 耿鼎三 | E62: 安泰銀行擔保 | F62: 有擔保 | G62: 3 | H62: 7.5 | I62: 3 | J62: 詢圈 | K62: 元大證券 | L62: 汽車工業 | M62: 為汽車AM鈑金件製造商 | N62: 16.5 | Q62: 1.0714 | R62: 40910 | S62: 2014/12/22 | T62: 127 | U62: 101
A63: 62 | B63: 1526 | C63: 15261 | D63: 日馳一 | E63: 6 | F63: 無擔保 | G63: 5 | H63: 38 | I63: 3 | J63: 競拍 | K63: 富邦證券 | L63: 電機機械 | M63: 全球知名的自行車內、外變速器製造商 | N63: 6 | O63: 103.81 | P63: 100 | Q63: 1.0683 | R63: 45188 | S63: 46284 | T63: 104.8 | U63: 90.1
A64: 63 | B64: 1528 | C64: 15281 | D64: 恩德一 | E64: 0 | J64: 詢圈 | L64: 電機機械 | M64: 台灣生產PCB鑽孔機、成型機與木工機械廠商 | T64: 132 | U64: 78.3
A65: 64 | B65: 1528 | C65: 15282 | D65: 恩德二 | E65: 0 | G65: 3 | H65: 14.7 | I65: 5 | J65: 詢圈 | L65: 電機機械 | M65: 台灣生產PCB鑽孔機、成型機與木工機械廠商 | R65: 40375 | S65: 2015/07/16 | T65: 149 | U65: 102
A66: 65 | B66: 1529 | C66: 15291 | D66: 樂士一 | E66: 0 | J66: 詢圈 | L66: 電機機械 | M66: 以重電事業及太陽能光電業務為主 | T66: 179 | U66: 54
A67: 66 | B67: 1530 | C67: 15301 | D67: 亞崴一 | E67: 0 | J67: 詢圈 | L67: 電機機械 | M67: 台灣知名CNC加工機及龍門機製造商 | T67: 115 | U67: 103
A68: 67 | B68: 1530 | C68: 15302 | D68: 亞崴二 | E68: 6 | F68: 無擔保 | G68: 4 | H68: 51 | I68: 5 | J68: 詢圈 | K68: 元大證券 | L68: 電機機械 | M68: 台灣知名CNC加工機及龍門機製造商 | N68: 9.66 | O68: 100 | P68: 100 | Q68: 1.119649 | R68: 42138 | S68: 43965 | T68: 105 | U68: 98
A69: 68 | B69: 1532 | C69: 15321 | D69: 勤美一 | E69: 0 | I69: 5 | J69: 詢圈 | L69: 電機機械 | M69: 台灣鑄鐵龍頭廠之一，並轉投資營建地產 | T69: 225 | U69: 123
A70: 69 | B70: 1532 | C70: 15322 | D70: 勤美二 | E70: 0 | I70: 5 | J70: 詢圈 | L70: 電機機械 | M70: 台灣鑄鐵龍頭廠之一，並轉投資營建地產 | T70: 211 | U70: 102.5
A71: 70 | B71: 1532 | C71: 15323 | D71: 勤美三 | E71: 0 | I71: 5 | J71: 詢圈 | L71: 電機機械 | M71: 台灣鑄鐵龍頭廠之一，並轉投資營建地產 | T71: 338 | U71: 102
A72: 71 | B72: 1532 | C72: 15324 | D72: 勤美四 | E72: 6 | F72: 無擔保 | G72: 15 | H72: 34.2 | I72: 3 | J72: 競拍 | K72: 台新證券 | L72: 電機機械 | M72: 台灣鑄鐵龍頭廠之一，並轉投資營建地產 | N72: 37.8 | O72: 110.04 | P72: 100 | Q72: 1.04 | R72: 44585 | S72: 45681 | T72: 184 | U72: 99.75
A73: 72 | B73: 1533 | C73: 15331 | D73: 車王電一 | E73: 0 | I73: 3 | J73: 詢圈 | L73: 汽車工業 | M73: 主攻AM車用電子零組件之大廠 | T73: 132 | U73: 103
A74: 73 | B74: 1533 | C74: 15332 | D74: 車王電二 | E74: 6 | F74: 無擔保 | G74: 10 | H74: 73.5 | I74: 3 | J74: 競拍 | K74: 凱基證券 | L74: 汽車工業 | M74: 主攻AM車用電子零組件之大廠 | N74: 9.85 | O74: 105.51 | P74: 100 | Q74: 1.05 | R74: 44587 | S74: 45683 | T74: 111 | U74: 93.5
A75: 74 | B75: 1535 | C75: 15351 | D75: 中宇一 | E75: 4 | F75: 無擔保 | G75: 6 | H75: 59.7 | I75: 3 | J75: 詢圈 | K75: 統一證券 | L75: 電機機械 | M75: 中鋼集團旗下，環保工程廠商 | N75: 12.4 | Q75: 1.012 | R75: 40959 | S75: 2015/02/10 | T75: 164 | U75: 104
A76: 75 | B76: 1536 | C76: 15361 | D76: 和大一 | E76: 0 | J76: 詢圈 | L76: 汽車工業 | M76: 台灣最大、全球前十大車廠之傳動零組件供應商 | T76: 231 | U76: 97.1
A77: 76 | B77: 1536 | C77: 15362 | D77: 和大二 | E77: 0 | G77: 13.8 | H77: 25.9 | I77: 5 | J77: 詢圈 | L77: 汽車工業 | M77: 台灣最大、全球前十大車廠之傳動零組件供應商 | R77: 38906 | S77: 2011/07/08 | T77: 141.5 | U77: 82.15
A78: 77 | B78: 1536 | C78: 15363 | D78: 和大三 | E78: 0 | G78: 2 | H78: 8.36 | I78: 5 | J78: 詢圈 | L78: 汽車工業 | M78: 台灣最大、全球前十大車廠之傳動零組件供應商 | R78: 40122 | S78: 2014/11/05 | T78: 765 | U78: 725
A79: 78 | B79: 1536 | C79: 15364 | D79: 和大四 | E79: 6 | F79: 無擔保 | G79: 15 | H79: 72.26 | I79: 3 | J79: 詢圈 | K79: 台中銀證 | L79: 汽車工業 | M79: 台灣最大、全球前十大車廠之傳動零組件供應商 | N79: 28 | O79: 100 | P79: 100 | Q79: 1.06 | R79: 45516 | S79: 46611 | T79: 130.3 | U79: 93.9
A80: 79 | B80: 1537 | C80: 15371 | D80: 廣隆一 | E80: 0 | G80: 5 | H80: 30.5 | I80: 5 | J80: 詢圈 | L80: 電機機械 | M80: 鉛酸蓄電池專業製造商 | R80: 39413 | S80: 2012/11/27 | T80: 225 | U80: 83
A81: 80 | B81: 1541 | C81: 15411 | D81: 錩泰一 | E81: 0 | J81: 詢圈 | L81: 電機機械 | M81: 主要代工生產圓鋸機、線鋸機等桌上型木工機廠商 | T81: 129.45 | U81: 77
A82: 81 | B82: 1560 | C82: 15601 | D82: 中砂一 | E82: 4 | F82: 無擔保 | G82: 10 | H82: 292.1 | I82: 5 | J82: 競拍 | K82: 凱基證券 | L82: 電機機械 | M82: 台灣從事砂輪及再生晶圓生產製造廠商 | N82: 14.5 | O82: 118.38 | P82: 100 | Q82: 1.02 | R82: 45467 | S82: 47293 | T82: 141.85 | U82: 98.7
A83: 82 | B83: 1566 | C83: 15661 | D83: 捷邦一 | H83: 32.93 | J83: 詢圈 | K83: 凱基證券 | P83: 100 | R83: 41257 | S83: 43083 | T83: 124.85 | U83: 94
A84: 83 | B84: 1569 | C84: 15691 | D84: 濱川一 | E84: 0 | J84: 詢圈 | L84: 電腦及週邊設備業 | M84: 全球NB鍵盤支架最大供應商 | T84: 207 | U84: 92.25
A85: 84 | B85: 1569 | C85: 15692 | D85: 濱川二 | E85: 0 | G85: 1.5 | H85: 42.2 | I85: 3 | J85: 詢圈 | L85: 電腦及週邊設備業 | M85: 全球NB鍵盤支架最大供應商 | R85: 40196 | S85: 2013/01/18 | T85: 182 | U85: 107
A86: 85 | B86: 1569 | C86: 15693 | D86: 濱川三 | E86: 0 | G86: 1.2 | H86: 43.6 | I86: 5 | J86: 詢圈 | L86: 電腦及週邊設備業 | M86: 全球NB鍵盤支架最大供應商 | R86: 40197 | S86: 2015/01/19 | T86: 162 | U86: 107
A87: 86 | B87: 1569 | C87: 15694 | D87: 濱川四 | E87: 台新銀 | F87: 有擔保 | G87: 2 | H87: 39 | I87: 3 | J87: 詢圈 | K87: 台新證券 | L87: 電腦及週邊設備業 | M87: 全球NB鍵盤支架最大供應商 | N87: 12.1 | Q87: 1.0104 | R87: 41255 | S87: 2015/12/02 | T87: 136.95 | U87: 101
A88: 87 | B88: 1569 | C88: 15695 | D88: 濱川五 | E88: 台新銀行 | F88: 有擔保 | G88: 2 | H88: 22.6 | I88: 3 | J88: 詢圈 | K88: 台新證券 | L88: 電腦及週邊設備業 | M88: 全球NB鍵盤支架最大供應商 | N88: 12.1 | O88: 100 | P88: 103.6434 | Q88: 1.01 | R88: 42039 | S88: 43135 | T88: 187 | U88: 100.2
A89: 88 | B89: 1569 | C89: 15696 | D89: 濱川六 | E89: 7 | F89: 無擔保 | G89: 2 | H89: 23 | I89: 4 | J89: 詢圈 | K89: 台新證券 | L89: 電腦及週邊設備業 | M89: 全球NB鍵盤支架最大供應商 | N89: 12.1 | O89: 100 | P89: 102.0151 | Q89: 1.07 | R89: 43523 | S89: 44984 | T89: 149 | U89: 95
A90: 89 | B90: 1582 | C90: 15821 | D90: 信錦一 | E90: 0 | G90: 6 | H90: 50.2 | I90: 3 | J90: 詢圈 | L90: 電子零組件業 | M90: 全球最大監視器軸承及底座廠商 | R90: 40593 | S90: 2014/02/19 | T90: 130.8 | U90: 97.6
A91: 90 | B91: 1582 | C91: 15822 | D91: 信錦二 | E91: 4 | F91: 無擔保 | G91: 8 | H91: 63.8 | I91: 3 | J91: 詢圈 | K91: 康和證券 | L91: 電子零組件業 | M91: 全球最大監視器軸承及底座廠商 | N91: 12.4 | O91: 100 | P91: 101.5075 | Q91: 1.013 | R91: 42024 | S91: 43120 | T91: 147 | U91: 98.5
A92: 91 | B92: 1582 | C92: 15823 | D92: 信錦三 | E92: 4 | F92: 無擔保 | G92: 12 | H92: 66.8 | I92: 3 | J92: 競拍 | K92: 富邦證券 | L92: 電子零組件業 | M92: 全球最大監視器軸承及底座廠商 | N92: 12.4 | O92: 111.87 | P92: 100 | Q92: 1.02 | R92: 44448 | S92: 45544 | T92: 203 | U92: 101
A93: 92 | B93: 1583 | C93: 15831 | D93: 程泰一 | E93: 6 | F93: 無擔保 | G93: 6 | H93: 102 | I93: 5 | J93: 詢圈 | K93: 富邦證券 | L93: 電機機械 | M93: 台灣規模最大的專業CNC車床製造商 | N93: 11 | O93: 100.5 | P93: 100 | Q93: 1.1308 | R93: 42074 | S93: 43901 | T93: 106.8 | U93: 95.05
A94: 93 | B94: 1584 | C94: 15841 | D94: 精剛一 | E94: 0 | J94: 詢圈 | L94: 其他業 | M94: 台灣鋼鐵集團旗下合金鋼廠 | T94: 117.7 | U94: 93
A95: 94 | B95: 1584 | C95: 15842 | D95: 精剛二 | E95: 聯保 | F95: 有擔保 | G95: 2.87 | H95: 23.6 | I95: 3 | J95: 詢圈 | K95: 富邦證券 | L95: 其他業 | M95: 台灣鋼鐵集團旗下合金鋼廠 | N95: 19.2 | Q95: 1.01 | R95: 41023 | S95: 2015/04/14 | T95: 113 | U95: 100
A96: 95 | B96: 1586 | C96: 15861 | D96: 和勤一 | E96: 安泰銀行 | F96: 有擔保 | G96: 3 | H96: 30.5 | I96: 3 | J96: 詢圈 | K96: 康和證券 | L96: 電機機械 | M96: 台灣汽車及硬碟零件雙核心精沖技術大廠 | N96: 8.63 | O96: 100 | P96: 100 | Q96: 1.027 | R96: 42017 | S96: 43113 | T96: 189 | U96: 100.2
A97: 96 | B97: 1586 | C97: 15862 | D97: 和勤二 | E97: 合庫銀 | F97: 有擔保 | G97: 2 | H97: 46 | I97: 3 | J97: 詢圈 | K97: 合庫證券 | L97: 電機機械 | M97: 台灣汽車及硬碟零件雙核心精沖技術大廠 | N97: 8.63 | O97: 100 | P97: 100 | Q97: 1.0768 | R97: 44074 | S97: 45169 | T97: 127.5 | U97: 99.5
A98: 97 | B98: 1586 | C98: 15863 | D98: 和勤三 | E98: 7 | F98: 無擔保 | G98: 2 | H98: 45 | I98: 3 | J98: 詢圈 | K98: 合庫證券 | L98: 電機機械 | M98: 台灣汽車及硬碟零件雙核心精沖技術大廠 | N98: 8.63 | O98: 100 | P98: 100.7519 | Q98: 1.0207 | R98: 44075 | S98: 45170 | T98: 125.25 | U98: 98.55
A99: 98 | B99: 1586 | C99: 15864 | D99: 和勤四 | E99: 合庫銀行 | F99: 有擔保 | G99: 2 | H99: 33.39 | I99: 3 | J99: 競拍 | K99: 合庫證券 | L99: 電機機械 | M99: 台灣汽車及硬碟零件雙核心精沖技術大廠 | N99: 8.63 | O99: 107.2 | P99: 100 | Q99: 1.05 | R99: 45168 | S99: 46264 | T99: 124 | U99: 105
A100: 99 | B100: 1586 | C100: 15865 | D100: 和勤五 | E100: 7 | F100: 無擔保 | G100: 3 | H100: 32.74 | I100: 3 | J100: 詢圈 | K100: 合庫證券 | L100: 電機機械 | M100: 台灣汽車及硬碟零件雙核心精沖技術大廠 | N100: 8.63 | O100: 100 | P100: 101.5075 | Q100: 1.051 | R100: 45169 | S100: 46265 | T100: 114.5 | U100: 93.55
...

Sheet 02_ALLCB發行時程
A1: 序號 | B1: 股票代號 | C1: CB代號 | D1: 名稱 | E1: 掛牌日期 | F1: 到期日期 | G1: 董事會公告 | H1: 送件日期 | I1: 生效日期 | J1: 詢圈競拍日期 | K1: 代收價款公告 | L1: 掛牌日期 | M1: CBAS拆解日
A2: 1 | B2: 1101 | C2: 11011 | D2: 台泥一永 | E2: 45636 | F2: 47462 | G2: 45548 | H2: 2024/09/30 | I2: 2024/10/21 | J2: 11/26-11/28 | K2: 45621 | L2: 45636 | M2: 45643
A3: 2 | B3: 1210 | C3: 12101 | D3: 大成一 | E3: 39336 | F3: 2012/09/11
A4: 3 | B4: 1216 | C4: 12161 | D4: 統一一 | E4: 39370 | F4: 2010/10/15
A5: 4 | B5: 1217 | C5: 12171 | D5: 愛之味一 | E5: 40664 | F5: 2014/05/01
A6: 5 | B6: 1217 | C6: 12172 | D6: 愛之味二 | E6: 40675 | F6: 42502
A7: 6 | B7: 1217 | C7: 12173 | D7: 愛之味三 | E7: 41340 | F7: 43166 | H7: 41211 | I7: 41227 | J7: 2/21-2/23 | L7: 41340
A8: 7 | B8: 1218 | C8: 12181 | D8: 泰山一 | E8: 41417 | F8: 42513 | H8: 41374 | I8: 41403 | J8: 5/13-5/14 | L8: 41417
A9: 8 | B9: 1225 | C9: 12251 | D9: 福脂一 | E9: 40158 | F9: 2014/12/11
A10: 9 | B10: 1258 | C10: 12581 | D10: 其祥一KY | E10: 42262 | F10: 43358
A11: 10 | B11: 1258 | C11: 12582 | D11: 其祥二KY | E11: 43353 | F11: 45179
A12: 11 | B12: 1312 | C12: 13121 | D12: 國喬一
A13: 12 | B13: 1316 | C13: 13161 | D13: 上曜一 | E13: 40757 | F13: 2014/07/23 | L13: 40757
A14: 13 | B14: 1316 | C14: 13162 | D14: 上曜二 | E14: 41996 | F14: 43092 | H14: 41912 | I14: 41941 | J14: 12/10-12/11 | L14: 41996
A15: 14 | B15: 1316 | C15: 13163 | D15: 上曜三 | E15: 43411 | F15: 44507 | H15: 2018/09/26 | I15: 2018/10/15 | J15: 10/25-10/26 | L15: 43411
A16: 15 | B16: 1316 | C16: 13164 | D16: 上曜四 | E16: 44225 | F16: 46051 | G16: 44172 | H16: 2020/12/14 | I16: 2020/12/30 | J16: 1/18-1/19 | K16: 44211 | L16: 44225
A17: 16 | B17: 1316 | C17: 13165 | D17: 上曜五 | E17: 44228 | F17: 45323 | G17: 44172 | H17: 2020/12/14 | I17: 2020/12/30 | J17: 1/18-1/19 | K17: 44211 | L17: 44228
A18: 17 | B18: 1316 | C18: 13166 | D18: 上曜六 | E18: 45653 | F18: 46748 | J18: 12/12-12/16 | L18: 45653 | M18: 45663
A19: 18 | B19: 1319 | C19: 13191 | D19: 東陽一 | E19: 40536 | F19: 2015/12/24
A20: 19 | B20: 1336 | C20: 13361 | D20: 台翰一 | E20: 41892 | F20: 42988 | H20: 41835 | I20: 41851 | J20: 8/27-8/28 | L20: 41892
A21: 20 | B21: 1337 | C21: 13371 | D21: 再生一 | E21: 41193 | F21: 2015/10/01 | L21: 41193
A22: 21 | B22: 1338 | C22: 13381 | D22: 廣華一KY | E22: 44215 | F22: 46041 | G22: 44000 | H22: 2020/07/06 | I22: 2020/07/22 | J22: 1/5-1/6 | K22: 44202 | L22: 44215
A23: 22 | B23: 1338 | C23: 13382 | D23: 廣華二KY | E23: 45261 | F23: 47088 | G23: 45166 | H23: 2023/10/17 | I23: 2023/11/02 | J23: 11/16-11/17 | K23: 45253 | L23: 45261 | M23: 45268
A24: 23 | B24: 1341 | C24: 13411 | D24: 富林一KY | E24: 44329 | F24: 45425 | G24: 44266 | H24: 2021/03/30 | I24: 2021/04/19 | J24: 4/27-4/29 | K24: 44307 | L24: 44329
A25: 24 | B25: 1342 | C25: 13421 | D25: 八貫一 | E25: 44714 | F25: 45810 | G25: 44616 | H25: 2022/04/13 | I25: 2022/04/29 | J25: 5/18-5/20 | K25: 44697 | L25: 44714 | M25: 44722
A26: 25 | B26: 1409 | C26: 14093 | D26: 新纖三 | E26: 39189 | F26: 2012/04/17
A27: 26 | B27: 1432 | C27: 14321 | D27: 大魯閣一 | E27: 42047 | F27: 43143 | H27: 41999 | I27: 42030 | J27: 1/30-2/2 | L27: 42047
A28: 27 | B28: 1432 | C28: 14322 | D28: 大魯閣二 | E28: 42048 | F28: 43874 | H28: 41999 | I28: 42030 | J28: 1/30-2/2 | L28: 42048
A29: 28 | B29: 1436 | C29: 14361 | D29: 華友聯一 | E29: 43847 | F29: 45674 | G29: 43777 | H29: 2019/12/10 | I29: 2019/12/26 | J29: 1/2-1/6 | K29: 43826 | L29: 43847
A30: 29 | B30: 1436 | C30: 14362 | D30: 華友聯二 | E30: 44166 | F30: 45992 | G30: 43910 | H30: 44081 | I30: 44097 | J30: 11/18-11/19 | K30: 44158 | L30: 44166
A31: 30 | B31: 1436 | C31: 14363 | D31: 華友聯三 | E31: 45531 | F31: 46626 | G31: 45422 | H31: 2024/07/01 | I31: 2024/07/17 | J31: 8/12-8/14 | K31: 45444 | L31: 45531 | M31: 45538
A32: 31 | B32: 1436 | C32: 14364 | D32: 華友聯四 | E32: 45734 | F32: 46830 | G32: 45597 | H32: 2024/12/13 | I32: 2024/12/31 | J32: 3/4-3/6 | K32: 45715 | L32: 45734 | M32: 45376
A33: 32 | B33: 1437 | C33: 14371 | D33: 勤益一
A34: 33 | B34: 1438 | C34: 14381 | D34: 三地開發一 | E34: 45645 | F34: 47471 | G34: 45488 | H34: 2024/10/21 | I34: 2024/11/06 | J34: 12/4-12/6 | K34: 45625 | L34: 45645 | M34: 45652
A35: 34 | B35: 1442 | C35: 14422 | D35: 名軒二 | E35: 41122 | F35: 2015/07/22 | H35: 41089 | I35: 41107 | J35: 7/20-7/23 | L35: 41122
A36: 35 | B36: 1442 | C36: 14423 | D36: 名軒三 | E36: 42339 | F36: 44166 | H36: 42307 | I36: 42325 | J36: 11/19-11/20 | L36: 42339
A37: 36 | B37: 1457 | C37: 14571 | D37: 宜進一 | E37: 40724 | F37: 2014/06/20 | L37: 40724
A38: 37 | B38: 1464 | C38: 14641 | D38: 得力一 | E38: 42144 | F38: 43240 | H38: 42102 | I38: 42118 | J38: 5/5-5/7 | L38: 42144
A39: 38 | B39: 1464 | C39: 14642 | D39: 得力二 | E39: 42145 | F39: 43241 | H39: 42102 | I39: 42118 | J39: 5/5-5/7 | L39: 42145
A40: 39 | B40: 1466 | C40: 14661 | D40: 聚隆一 | E40: 40693 | F40: 2014/05/20 | L40: 40693
A41: 40 | B41: 1466 | C41: 14662 | D41: 聚隆二 | E41: 41288 | F41: 43114 | H41: 41250 | I41: 41267 | J41: 1/2-1/3 | L41: 41288
A42: 41 | B42: 1466 | C42: 14663 | D42: 聚隆三 | E42: 41906 | F42: 43732 | H42: 41869 | I42: 41885 | J42: - | L42: 41906
A43: 42 | B43: 1467 | C43: 14671 | D43: 南緯一
A44: 43 | B44: 1472 | C44: 14721 | D44: 三洋實業一 | E44: 43495 | F44: 44591 | H44: 2018/12/14 | I44: 2019/01/14 | J44: 1/15-1/16 | K44: 43482 | L44: 43495
A45: 44 | B45: 1474 | C45: 14741 | D45: 弘裕一
A46: 45 | B46: 1474 | C46: 14742 | D46: 弘裕二 | E46: 44587 | F46: 45683 | G46: 44512 | H46: 2021/12/15 | I46: 2022/01/03 | J46: 1/11-1/13 | K46: 44566 | L46: 44587 | M46: 44603
A47: 46 | B47: 1474 | C47: 14743 | D47: 弘裕三 | E47: 45747 | F47: 46843 | G47: 45608 | H47: 2024/12/27 | I47: 2025/01/15 | J47: 3/14-3/18 | K47: 45727 | L47: 45747 | M47: 45756
A48: 47 | B48: 1477 | C48: 14771 | D48: 聚陽一
A49: 48 | B49: 1477 | C49: 14772 | D49: 聚陽二
A50: 49 | B50: 1477 | C50: 14773 | D50: 聚陽三 | E50: 39976 | F50: 2014/06/12
A51: 50 | B51: 1477 | C51: 14774 | D51: 聚陽四 | E51: 41145 | F51: 42971 | L51: 41145
A52: 51 | B52: 1504 | C52: 15043 | D52: 東元三 | E52: 41102 | F52: 2015/07/02 | L52: 41102
A53: 52 | B53: 1506 | C53: 15061 | D53: 正道一 | E53: 42027 | F53: 43123 | H53: 41975 | I53: 42002 | J53: 1/8-1/9 | L53: 42027
A54: 53 | B54: 1513 | C54: 15131 | D54: 中興電一 | E54: 43846 | F54: 45673 | G54: 43689 | H54: 2019/11/04 | I54: 2019/12/20 | J54: 1/3-1/6 | L54: 43846
A55: 54 | B55: 1513 | C55: 15132 | D55: 中興電二 | E55: 44182 | F55: 46008 | G55: 44120 | H55: 2020/11/10 | I55: 2020/11/26 | J55: 12/4-12/7 | L55: 44182
A56: 55 | B56: 1514 | C56: 15141 | D56: 亞力一 | E56: 45155 | F56: 46982 | G56: 45057 | H56: 2023/07/10 | I56: 2023/07/26 | J56: 8/2-8/4 | K56: 45134 | L56: 45155 | M56: 45162
A57: 56 | B57: 1514 | C57: 15142 | D57: 亞力二 | E57: 45670 | F57: 47496 | G57: 45517 | H57: 2024/10/04 | I57: 2024/10/23 | J57: 12/27-12/31 | K57: 45590 | L57: 45670 | M57: 45677
A58: 57 | B58: 1515 | C58: 15151 | D58: 力山一
A59: 58 | B59: 1522 | C59: 15221 | D59: 堤維西一
A60: 59 | B60: 1524 | C60: 15241 | D60: 耿鼎一
A61: 60 | B61: 1524 | C61: 15242 | D61: 耿鼎二 | E61: 38374 | F61: 2010/01/22
A62: 61 | B62: 1524 | C62: 15243 | D62: 耿鼎三 | E62: 40910 | F62: 2014/12/22 | H62: 40842 | I62: 40870 | J62: 12/1/12/5 | L62: 40910
A63: 62 | B63: 1526 | C63: 15261 | D63: 日馳一 | E63: 45188 | F63: 46284 | H63: 2023/07/10 | I63: 2023/07/26 | J63: 9/4-9/6 | K63: 45161 | L63: 45188 | M63: 45195
A64: 63 | B64: 1528 | C64: 15281 | D64: 恩德一
A65: 64 | B65: 1528 | C65: 15282 | D65: 恩德二 | E65: 40375 | F65: 2015/07/16
A66: 65 | B66: 1529 | C66: 15291 | D66: 樂士一
A67: 66 | B67: 1530 | C67: 15301 | D67: 亞崴一
A68: 67 | B68: 1530 | C68: 15302 | D68: 亞崴二 | E68: 42138 | F68: 43965 | H68: 41947 | I68: 41963 | J68: 5/4-/5/5 | L68: 42138
A69: 68 | B69: 1532 | C69: 15321 | D69: 勤美一
A70: 69 | B70: 1532 | C70: 15322 | D70: 勤美二
A71: 70 | B71: 1532 | C71: 15323 | D71: 勤美三
A72: 71 | B72: 1532 | C72: 15324 | D72: 勤美四 | E72: 44585 | F72: 45681 | G72: 44511 | H72: 44539 | I72: 44557 | J72: 1/7-1/11 | K72: 44565 | L72: 44585 | M72: 44601
A73: 72 | B73: 1533 | C73: 15331 | D73: 車王電一
A74: 73 | B74: 1533 | C74: 15332 | D74: 車王電二 | E74: 44587 | F74: 45683 | G74: 44327 | H74: 2021/07/26 | I74: 2021/08/11 | J74: 1/11-1/13 | K74: 44567 | L74: 44587 | M74: 44603
A75: 74 | B75: 1535 | C75: 15351 | D75: 中宇一 | E75: 40959 | F75: 2015/02/10 | H75: 40900 | I75: 40918 | J75: 2012/2/2-2012/2/4 | L75: 40959
A76: 75 | B76: 1536 | C76: 15361 | D76: 和大一
A77: 76 | B77: 1536 | C77: 15362 | D77: 和大二 | E77: 38906 | F77: 2011/07/08
A78: 77 | B78: 1536 | C78: 15363 | D78: 和大三 | E78: 40122 | F78: 2014/11/05
A79: 78 | B79: 1536 | C79: 15364 | D79: 和大四 | E79: 45516 | F79: 46611 | G79: 45365 | H79: 2024/07/08 | I79: 2024/07/24 | J79: 7/30-7/31 | K79: 45502 | L79: 45516 | M79: 45523
A80: 79 | B80: 1537 | C80: 15371 | D80: 廣隆一 | E80: 39413 | F80: 2012/11/27
A81: 80 | B81: 1541 | C81: 15411 | D81: 錩泰一
A82: 81 | B82: 1560 | C82: 15601 | D82: 中砂一 | E82: 45467 | F82: 47293 | G82: 45406 | H82: 2024/05/15 | I82: 2024/05/31 | J82: 6/6-6/11 | K82: 45443 | L82: 45467 | M82: 45474
A83: 82 | B83: 1566 | C83: 15661 | D83: 捷邦一 | E83: 41257 | F83: 43083
A84: 83 | B84: 1569 | C84: 15691 | D84: 濱川一
A85: 84 | B85: 1569 | C85: 15692 | D85: 濱川二 | E85: 40196 | F85: 2013/01/18
A86: 85 | B86: 1569 | C86: 15693 | D86: 濱川三 | E86: 40197 | F86: 2015/01/19
A87: 86 | B87: 1569 | C87: 15694 | D87: 濱川四 | E87: 41255 | F87: 2015/12/02 | H87: 41191 | I87: 41220 | J87: 11/28-11/30 | L87: 41255
A88: 87 | B88: 1569 | C88: 15695 | D88: 濱川五 | E88: 42039 | F88: 43135 | H88: 42000 | I88: 42019 | J88: 1/21-1/23 | L88: 42039
A89: 88 | B89: 1569 | C89: 15696 | D89: 濱川六 | E89: 43523 | F89: 44984 | H89: 2018/11/12 | I89: 2018/11/28 | J89: 2/13-2/15 | L89: 43523
A90: 89 | B90: 1582 | C90: 15821 | D90: 信錦一 | E90: 40593 | F90: 2014/02/19
A91: 90 | B91: 1582 | C91: 15822 | D91: 信錦二 | E91: 42024 | F91: 43120 | H91: 41981 | I91: 41997 | J91: 1/7-1/8 | L91: 42024
A92: 91 | B92: 1582 | C92: 15823 | D92: 信錦三 | E92: 44448 | F92: 45544 | G92: 44321 | H92: 2021/05/25 | I92: 2021/06/10 | J92: 8/25-8/27 | L92: 44448
A93: 92 | B93: 1583 | C93: 15831 | D93: 程泰一 | E93: 42074 | F93: 43901 | H93: 41953 | J93: 2/25-2/26 | L93: 42074
A94: 93 | B94: 1584 | C94: 15841 | D94: 精剛一
A95: 94 | B95: 1584 | C95: 15842 | D95: 精剛二 | E95: 41023 | F95: 2015/04/14 | H95: 40840 | I95: 40856 | J95: 2012/4/10-4/12 | L95: 41023
A96: 95 | B96: 1586 | C96: 15861 | D96: 和勤一 | E96: 42017 | F96: 43113 | H96: 41974 | I96: 41990 | J96: 12/26-12/27 | L96: 42017
A97: 96 | B97: 1586 | C97: 15862 | D97: 和勤二 | E97: 44074 | F97: 45169 | G97: 44005 | J97: 8/18-8/19 | L97: 44074
A98: 97 | B98: 1586 | C98: 15863 | D98: 和勤三 | E98: 44075 | F98: 45170 | G98: 44005 | H98: 2020/07/17 | I98: 2020/08/14 | J98: 8/18-8/19 | L98: 44075
A99: 98 | B99: 1586 | C99: 15864 | D99: 和勤四 | E99: 45168 | F99: 46264 | G99: 45054 | H99: 2023/05/29 | I99: 2023/06/14 | J99: 8/15-8/17 | K99: 45149 | L99: 45168 | M99: 45175
A100: 99 | B100: 1586 | C100: 15865 | D100: 和勤五 | E100: 45169 | F100: 46265 | G100: 45054 | H100: 2023/05/29 | I100: 2023/06/14 | J100: 8/18-8/21 | K100: 45149 | L100: 45169 | M100: 45176
...

Sheet 03_ALLCB賣回條件
A1: 序號 | B1: 股票代號 | C1: CB代號 | D1: 名稱 | E1: 賣回日期1 | F1: 賣回日期2 | G1: 投資人提前賣回 | H1: 賣回條件
A2: 1 | B2: 1101 | C2: 11011 | D2: 台泥一永 | E2: 46731 | F2: 47462 | G2: 發行滿三年 | H2: YTP(3)=(0%)
A3: 2 | B3: 1210 | C3: 12101 | D3: 大成一
A4: 3 | B4: 1216 | C4: 12161 | D4: 統一一
A5: 4 | B5: 1217 | C5: 12171 | D5: 愛之味一
A6: 5 | B6: 1217 | C6: 12172 | D6: 愛之味二 | E6: 41406 | F6: 41771 | G6: 發行滿二年、滿三年
A7: 6 | B7: 1217 | C7: 12173 | D7: 愛之味三 | E7: 42070 | F7: 42436 | G7: 到期滿二/年、/三年 | H7: YTP(2,3)=(1.75%)
A8: 7 | B8: 1218 | C8: 12181 | D8: 泰山一 | E8: 42147 | F8: 42513 | G8: 發行滿二年 | H8: YTP(2)=(1%)
A9: 8 | B9: 1225 | C9: 12251 | D9: 福脂一
A10: 9 | B10: 1258 | C10: 12581 | D10: 其祥一KY | E10: 42993 | F10: 43358 | G10: 發行滿二年 | H10: YTP(2)=(1%)
A11: 10 | B11: 1258 | C11: 12582 | D11: 其祥二KY | E11: 44449 | F11: 45179 | G11: 發行滿三年 | H11: YTP(3)=(0.5%)
A12: 11 | B12: 1312 | C12: 13121 | D12: 國喬一
A13: 12 | B13: 1316 | C13: 13161 | D13: 上曜一
A14: 13 | B14: 1316 | C14: 13162 | D14: 上曜二 | E14: 42727 | F14: 43092 | G14: 發行滿二年 | H14: YTP(2)=(1%)
A15: 14 | B15: 1316 | C15: 13163 | D15: 上曜三 | E15: 44142 | F15: 44507 | G15: 發行滿二年 | H15: YTP(2)=(0.5%)
A16: 15 | B16: 1316 | C16: 13164 | D16: 上曜四 | E16: 45320 | F16: 46051 | G16: 發行滿三年 | H16: YTP(3)=(0.25%)
A17: 16 | B17: 1316 | C17: 13165 | D17: 上曜五 | E17: 44958 | F17: 45323 | G17: 發行滿二年 | H17: YTP(2)=(2%)
A18: 17 | B18: 1316 | C18: 13166 | D18: 上曜六 | E18: 46383 | F18: 46748 | G18: 發行滿二年 | H18: YTP(2)=(0.25%)
A19: 18 | B19: 1319 | C19: 13191 | D19: 東陽一
A20: 19 | B20: 1336 | C20: 13361 | D20: 台翰一 | E20: 42623 | F20: 42988 | G20: 發行滿二年 | H20: YTP(2)=(1%)
A21: 20 | B21: 1337 | C21: 13371 | D21: 再生一
A22: 21 | B22: 1338 | C22: 13381 | D22: 廣華一KY | E22: 45310 | F22: 46041 | G22: 發行滿三年 | H22: YTP(3)=(0.5%)
A23: 22 | B23: 1338 | C23: 13382 | D23: 廣華二KY | E23: 46357 | F23: 47088 | G23: 發行滿三年 | H23: YTP(3)=(2%)
A24: 23 | B24: 1341 | C24: 13411 | D24: 富林一KY | E24: 45059 | F24: 45425 | G24: 發行滿二年 | H24: YTM(3)=(0.5%)
A25: 24 | B25: 1342 | C25: 13421 | D25: 八貫一 | E25: 45810 | G25: 無 | H25: YTM(3)=(0%)
A26: 25 | B26: 1409 | C26: 14093 | D26: 新纖三
A27: 26 | B27: 1432 | C27: 14321 | D27: 大魯閣一 | E27: 42778 | F27: 43143 | G27: 發行滿二年 | H27: YTP(2,3)=(1,1.25%)
A28: 27 | B28: 1432 | C28: 14322 | D28: 大魯閣二 | E28: 43144 | F28: 43509 | G28: 發行滿三、四年 | H28: YTP(3,4)=(1.25,1.5%)
A29: 28 | B29: 1436 | C29: 14361 | D29: 華友聯一 | E29: 44943 | F29: 45674 | G29: 發行滿三年 | H29: YTP(3)=(0.5%)
A30: 29 | B30: 1436 | C30: 14362 | D30: 華友聯二 | E30: 45261 | F30: 45992 | G30: 發行滿三年 | H30: YTP(3)=(0.25%)
A31: 30 | B31: 1436 | C31: 14363 | D31: 華友聯三 | E31: 46261 | F31: 46626 | G31: 發行滿二年 | H31: YTP(2)=(1.5%)
A32: 31 | B32: 1436 | C32: 14364 | D32: 華友聯四 | E32: 46464 | F32: 46830 | G32: 發行滿二年 | H32: YTP(2)=(1.5%)
A33: 32 | B33: 1437 | C33: 14371 | D33: 勤益一
A34: 33 | B34: 1438 | C34: 14381 | D34: 三地開發一 | E34: 46740 | F34: 47471 | G34: 發行滿三年 | H34: YTP(3)=(0.5%)
A35: 34 | B35: 1442 | C35: 14422 | D35: 名軒二 | H35: YTP(2)=(1%)，無重設
A36: 35 | B36: 1442 | C36: 14423 | D36: 名軒三 | E36: 43070 | F36: 43435 | G36: 發行滿二、三年 | H36: YTP(2,3)=(1.25%)
A37: 36 | B37: 1457 | C37: 14571 | D37: 宜進一
A38: 37 | B38: 1464 | C38: 14641 | D38: 得力一 | E38: 43240 | G38: 0 | H38: YTP(3)=(0%)
A39: 38 | B39: 1464 | C39: 14642 | D39: 得力二 | E39: 42876 | F39: 43241 | G39: 0 | H39: YTP(2)=(1%)
A40: 39 | B40: 1466 | C40: 14661 | D40: 聚隆一
A41: 40 | B41: 1466 | C41: 14662 | D41: 聚隆二 | E41: 42018 | F41: 42383 | G41: 發行滿二年、發行滿三年 | H41: YTP(2,3)=(1.25%)
A42: 41 | B42: 1466 | C42: 14663 | D42: 聚隆三 | E42: 43002 | F42: 43732 | G42: 發行滿三年 | H42: YTP(3)=(1.25%)
A43: 42 | B43: 1467 | C43: 14671 | D43: 南緯一
A44: 43 | B44: 1472 | C44: 14721 | D44: 三洋實業一 | E44: 44591 | G44: 無 | H44: YTP(3)=(0%)
A45: 44 | B45: 1474 | C45: 14741 | D45: 弘裕一
A46: 45 | B46: 1474 | C46: 14742 | D46: 弘裕二 | E46: 45683 | G46: 無 | H46: YTM(3)=(0%)
A47: 46 | B47: 1474 | C47: 14743 | D47: 弘裕三 | E47: 46843 | G47: 無 | H47: YTM(3)=(0%)
A48: 47 | B48: 1477 | C48: 14771 | D48: 聚陽一
A49: 48 | B49: 1477 | C49: 14772 | D49: 聚陽二
A50: 49 | B50: 1477 | C50: 14773 | D50: 聚陽三
A51: 50 | B51: 1477 | C51: 14774 | D51: 聚陽四 | E51: 42240 | F51: 42606 | G51: 發行滿三年、發行滿四年
A52: 51 | B52: 1504 | C52: 15043 | D52: 東元三
A53: 52 | B53: 1506 | C53: 15061 | D53: 正道一 | E53: 43123 | G53: 無 | H53: YTP(3)=(0%)
A54: 53 | B54: 1513 | C54: 15131 | D54: 中興電一 | E54: 44942 | F54: 45307 | G54: 發行滿三、四年 | H54: YTP(3,4)=(0.25%)
A55: 54 | B55: 1513 | C55: 15132 | D55: 中興電二 | E55: 45277 | F55: 45643 | G55: 發行滿三、四年 | H55: YTP(3,4)=(0.25%)
A56: 55 | B56: 1514 | C56: 15141 | D56: 亞力一 | E56: 46251 | F56: 46982 | G56: 發行滿三年 | H56: YTP(3)=(0.25%)
A57: 56 | B57: 1514 | C57: 15142 | D57: 亞力二 | E57: 46765 | F57: 47496 | G57: 發行滿三年 | H57: YTP(3)=(0.25%)
A58: 57 | B58: 1515 | C58: 15151 | D58: 力山一
A59: 58 | B59: 1522 | C59: 15221 | D59: 堤維西一
A60: 59 | B60: 1524 | C60: 15241 | D60: 耿鼎一
A61: 60 | B61: 1524 | C61: 15242 | D61: 耿鼎二
A62: 61 | B62: 1524 | C62: 15243 | D62: 耿鼎三 | H62: YTP(2)=(1%)，無重設
A63: 62 | B63: 1526 | C63: 15261 | D63: 日馳一 | E63: 46284 | G63: 無 | H63: YTM(3)=(0%)
A64: 63 | B64: 1528 | C64: 15281 | D64: 恩德一
A65: 64 | B65: 1528 | C65: 15282 | D65: 恩德二
A66: 65 | B66: 1529 | C66: 15291 | D66: 樂士一
A67: 66 | B67: 1530 | C67: 15301 | D67: 亞崴一
A68: 67 | B68: 1530 | C68: 15302 | D68: 亞崴二 | E68: 42869 | F68: 43965 | G68: 發行滿二年 | H68: YTP(2)=(1%)
A69: 68 | B69: 1532 | C69: 15321 | D69: 勤美一
A70: 69 | B70: 1532 | C70: 15322 | D70: 勤美二
A71: 70 | B71: 1532 | C71: 15323 | D71: 勤美三
A72: 71 | B72: 1532 | C72: 15324 | D72: 勤美四 | E72: 45315 | F72: 45681 | G72: 發行滿二年 | H72: YTP(2)=(0.25%)
A73: 72 | B73: 1533 | C73: 15331 | D73: 車王電一
A74: 73 | B74: 1533 | C74: 15332 | D74: 車王電二 | E74: 45683 | G74: 無 | H74: YTM(3)=(0%)
A75: 74 | B75: 1535 | C75: 15351 | D75: 中宇一 | H75: YTP(2)=(0.25%)，無重設
A76: 75 | B76: 1536 | C76: 15361 | D76: 和大一
A77: 76 | B77: 1536 | C77: 15362 | D77: 和大二
A78: 77 | B78: 1536 | C78: 15363 | D78: 和大三
A79: 78 | B79: 1536 | C79: 15364 | D79: 和大四 | E79: 46246 | F79: 46611 | G79: 發行滿二年 | H79: YTP(2)=(0%)
A80: 79 | B80: 1537 | C80: 15371 | D80: 廣隆一
A81: 80 | B81: 1541 | C81: 15411 | D81: 錩泰一
A82: 81 | B82: 1560 | C82: 15601 | D82: 中砂一 | E82: 46562 | F82: 47293 | G82: 發行滿三年 | H82: YTP(3)=(0%)
A83: 82 | B83: 1566 | C83: 15661 | D83: 捷邦一 | E83: 42352 | F83: 43083 | G83: 發行滿三年 | H83: YTP(3)=(0-0.5%)
A84: 83 | B84: 1569 | C84: 15691 | D84: 濱川一
A85: 84 | B85: 1569 | C85: 15692 | D85: 濱川二
A86: 85 | B86: 1569 | C86: 15693 | D86: 濱川三
A87: 86 | B87: 1569 | C87: 15694 | D87: 濱川四 | H87: YTP(2,3)=(1.2%)
A88: 87 | B88: 1569 | C88: 15695 | D88: 濱川五 | E88: 42770 | F88: 43135 | G88: 發行滿二年 | H88: YTP(2,3)=(1.2%)
A89: 88 | B89: 1569 | C89: 15696 | D89: 濱川六 | E89: 44254 | F89: 44984 | G89: 發行滿二年 | H89: YTP(2,4)=(0.5%)
A90: 89 | B90: 1582 | C90: 15821 | D90: 信錦一
A91: 90 | B91: 1582 | C91: 15822 | D91: 信錦二 | E91: 43120 | G91: 無 | H91: YTP(3)=(0.5%)
A92: 91 | B92: 1582 | C92: 15823 | D92: 信錦三 | E92: 45544 | G92: 無 | H92: YTM(3)=(0%)
A93: 92 | B93: 1583 | C93: 15831 | D93: 程泰一 | E93: 43170 | F93: 43901 | G93: 發行滿三年 | H93: YTP(3)=(0.5%)
A94: 93 | B94: 1584 | C94: 15841 | D94: 精剛一
A95: 94 | B95: 1584 | C95: 15842 | D95: 精剛二 | H95: YTP(2)=(1.5%)，無重設
A96: 95 | B96: 1586 | C96: 15861 | D96: 和勤一 | E96: 42748 | F96: 43113 | G96: 發行滿二年 | H96: YTP(2)=(1%)
A97: 96 | B97: 1586 | C97: 15862 | D97: 和勤二 | E97: 45169 | G97: 無 | H97: YTM(3)=(0%)
A98: 97 | B98: 1586 | C98: 15863 | D98: 和勤三 | E98: 45170 | G98: 無 | H98: YTM(3)=(0.25%)
A99: 98 | B99: 1586 | C99: 15864 | D99: 和勤四 | E99: 46264 | G99: 無 | H99: YTM(3)=(0%)
A100: 99 | B100: 1586 | C100: 15865 | D100: 和勤五 | E100: 46265 | G100: 無 | H100: YTM(3)=(0.5%)
...

Sheet 04_所有CB競拍資料庫
A1: 序號 | B1: 開標日期 | C1: 股票代號 | D1: CB代號 | E1: 名稱 | F1: 股本 | G1: 發行規模 | H1: 年期 | I1: 擔保 | J1: 信用評等 | K1: 競拍張數 | L1: 底標價 | M1: 截標日 | N1: 截標收盤 | O1: 轉換價 | P1: 訂價溢價率 | Q1: 理論價 | R1: 最低得標 | S1: 最低溢價 | T1: 平均得標 | U1: 平均溢價 | V1: 發行券商 | W1: 產業分類 | X1: 合格件數 | Y1: 投標張數 | Z1: 投標倍數 | AA1: 投標均張 | AB1: 投標開始日 | AC1: 最高投(得)標數量(張) | AD1: 撥券日 | AE1: 得標總金額 | AF1: 得標手續費率(%) | AG1: 最高得標價格(元) | AH1: 承銷價格(元)
A2: 1 | B2: 43546 | C2: 4943 | D2: 49431 | E2: 康控一KY | F2: 15.7 | G2: 15 | H2: 3 | I2: 無擔保 | J2: 9 | K2: 13500 | L2: 100 | M2: 43544 | N2: 124.5 | O2: 121.1 | P2: 1.02 | Q2: 102.81 | R2: 100.5 | S2: -0.0224 | T2: 102.07 | U2: -0.0072 | V2: 中信證券 | W2: 電子零組件業 | X2: 829 | Y2: 19751 | Z2: 1.46 | AA2: 23.83 | AB2: 43542 | AC2: 1350 | AD2: 43557 | AE2: 1377907550 | AF2: 1 | AG2: 159 | AH2: 102.07
A3: 2 | B3: 43710 | C3: 4736 | D3: 47363 | E3: 泰博三 | F3: 9.2 | G3: 15 | H3: 5 | I3: 有擔保 | J3: 4 | K3: 12752 | L3: 100 | M3: 43684 | N3: 126 | O3: 140 | P3: 1.057 | Q3: 90 | R3: 107.17 | S3: 0.1908 | T3: 108.46 | U3: 0.2051 | V3: 凱基證券 | W3: 生技醫療業 | X3: 1559 | Y3: 54356 | Z3: 4.26 | AA3: 34.87 | AB3: 43682 | AC3: 1275 | AD3: 43698 | AE3: 1394223850 | AF3: 0.5 | AG3: 140.1 | AH3: 109.33
A4: 3 | B4: 43773 | C4: 8028 | D4: 80281 | E4: 昇陽一 | F4: 13.2 | G4: 10 | H4: 3 | I4: 無擔保 | J4: 6 | K4: 8732 | L4: 102 | M4: 43769 | N4: 76.8 | O4: 76.1 | P4: 1.02 | Q4: 100.92 | R4: 108.45 | S4: 0.0746 | T4: 109.92 | U4: 0.0892 | V4: 富邦證券 | W4: 半導體業 | X4: 1063 | Y4: 31398 | Z4: 3.6 | AA4: 29.54
A5: 4 | B5: 43801 | C5: 2729 | D5: 27291 | E5: 瓦城一 | F5: 2.3 | G5: 8 | H5: 3 | I5: 無擔保 | J5: 5 | K5: 6880 | L5: 102 | M5: 43797 | N5: 286 | O5: 300 | P5: 1.072 | Q5: 95.33 | R5: 102.81 | S5: 0.0784 | T5: 107.3 | U5: 0.1255 | V5: 富邦證券 | W5: 觀光餐旅 | X5: 674 | Y5: 11341 | Z5: 1.65 | AA5: 16.83
A6: 5 | B6: 43810 | C6: 6477 | D6: 64771 | E6: 安集一 | F6: 11.4 | G6: 3 | H6: 5 | I6: 無擔保 | J6: 6 | K6: 2550 | L6: 100 | M6: 43808 | N6: 22.65 | O6: 23 | P6: 1.02 | Q6: 98.48 | R6: 100.51 | S6: 0.0206 | T6: 101.59 | U6: 0.0316 | V6: 福邦證券 | W6: 光電業 | X6: 187 | Y6: 4116 | Z6: 1.61 | AA6: 22.01 | AB6: 43804 | AC6: 255 | AD6: 43819 | AE6: 259066700 | AF6: 0.5 | AG6: 109.22 | AH6: 101.59
A7: 6 | B7: 43836 | C7: 3617 | D7: 36171 | E7: 碩天一 | F7: 8.1 | G7: 10 | H7: 3 | I7: 無擔保 | J7: 5 | K7: 10200 | L7: 101.5 | M7: 43832 | N7: 113 | O7: 122 | P7: 1.096 | Q7: 92.62 | R7: 104.1 | S7: 0.1239 | T7: 105.23 | U7: 0.1361 | V7: 宏遠證券 | W7: 其他電子業 | X7: 882 | Y7: 24587 | Z7: 2.41 | AA7: 27.88 | AB7: 43829 | AC7: 1020 | AD7: 43845 | AE7: 1073334860 | AF7: 0.5 | AG7: 141 | AH7: 105.23
A8: 7 | B8: 43838 | C8: 1436 | D8: 14361 | E8: 華友聯一 | F8: 9.6 | G8: 3 | H8: 5 | I8: 有擔保 | J8: 8 | K8: 2550 | L8: 100 | M8: 43836 | N8: 40.95 | O8: 40 | P8: 1.052 | Q8: 102.38 | R8: 106.66 | S8: 0.0419 | T8: 107.73 | U8: 0.0523 | V8: 第一金證 | W8: 建材營造業 | X8: 372 | Y8: 7637 | Z8: 2.99 | AA8: 20.53 | AB8: 43832 | AC8: 255 | AD8: 43847 | AE8: 274721790 | AF8: 0.5 | AG8: 120 | AH8: 107.73
A9: 8 | B9: 43839 | C9: 3594 | D9: 35943 | E9: 磐儀三 | F9: 7.2 | G9: 3 | H9: 3 | I9: 無擔保 | J9: 7 | K9: 2550 | L9: 100 | M9: 43837 | N9: 25.45 | O9: 22.8 | P9: 1.02 | Q9: 111.62 | R9: 101.65 | S9: -0.0893 | T9: 104.86 | U9: -0.0606 | V9: 福邦證券 | W9: 電腦及週邊設備業 | X9: 241 | Y9: 4769 | Z9: 1.87 | AA9: 19.79 | AB9: 43833 | AC9: 255 | AD9: 43850 | AE9: 267389720 | AF9: 0.5 | AG9: 115.3 | AH9: 104.86
A10: 9 | B10: 43867 | C10: 4967 | D10: 49671 | E10: 十銓一 | F10: 7.5 | G10: 5 | H10: 3 | I10: 有擔保 | J10: 6 | K10: 4250 | L10: 102 | M10: 43865 | N10: 36.55 | O10: 33.9 | P10: 1.069 | Q10: 107.82 | R10: 110.7 | S10: 0.0267 | T10: 112.21 | U10: 0.0407 | V10: 群益證券 | W10: 半導體業 | X10: 444 | Y10: 11307 | Z10: 2.66 | AA10: 25.47 | AB10: 43861 | AC10: 425 | AD10: 43878 | AE10: 476883600 | AF10: 0.5 | AG10: 119.6 | AH10: 112.21
A11: 10 | B11: 43879 | C11: 2466 | D11: 24663 | E11: 冠希電三 | F11: 15.6 | G11: 3 | H11: 3 | I11: 有擔保 | J11: 8 | K11: 2660 | L11: 102 | M11: 43875 | N11: 34.9 | O11: 38 | P11: 1.08 | Q11: 91.84 | R11: 103.11 | S11: 0.1227 | T11: 104.5 | U11: 0.1378 | V11: 中信證券 | W11: 光電業 | X11: 481 | Y11: 5011 | Z11: 1.88 | AA11: 10.42 | AB11: 43873 | AC11: 266 | AD11: 43888 | AE11: 277980900 | AF11: 0.5 | AG11: 110 | AH11: 104.5
A12: 11 | B12: 43880 | C12: 4175 | D12: 41752 | E12: 杏一二 | F12: 3.2 | G12: 3 | H12: 5 | I12: 無擔保 | J12: 6 | K12: 2550 | L12: 102 | M12: 43878 | N12: 72.9 | O12: 77.3 | P12: 1.05 | Q12: 94.31 | R12: 102.65 | S12: 0.0885 | T12: 103.62 | U12: 0.0987 | V12: 國泰證券 | W12: 生技醫療業 | X12: 190 | Y12: 4108 | Z12: 1.61 | AA12: 21.62 | AB12: 43874 | AC12: 255 | AD12: 43892 | AE12: 264225240 | AF12: 0.5 | AG12: 110 | AH12: 103.62
A13: 12 | B13: 43887 | C13: 2228 | D13: 22282 | E13: 劍麟二 | F13: 7.6 | G13: 3 | H13: 3 | I13: 無擔保 | J13: 5 | K13: 2550 | L13: 100 | M13: 43885 | N13: 95.2 | O13: 106.23 | P13: 1.05 | Q13: 89.62 | R13: 104.5 | S13: 0.1661 | T13: 105.98 | U13: 0.1826 | V13: 元大證券 | W13: 汽車工業 | X13: 416 | Y13: 11327 | Z13: 4.44 | AA13: 27.23 | AB13: 43881 | AC13: 255 | AD13: 43899 | AE13: 270260630 | AF13: 0.5 | AG13: 110 | AH13: 105.98
A14: 13 | B14: 43941 | C14: 6150 | D14: 61504 | E14: 撼訊四 | F14: 4.5 | G14: 4 | H14: 3 | I14: 無擔保 | J14: 8 | K14: 3550 | L14: 100 | M14: 43937 | N14: 42.8 | O14: 34.5 | P14: 1.02 | Q14: 124.06 | R14: 102.22 | S14: -0.176 | T14: 106.83 | U14: -0.1389 | V14: 宏遠證券 | W14: 電腦及週邊設備業 | X14: 221 | Y14: 4439 | Z14: 1.25 | AA14: 20.09 | AB14: 43935 | AC14: 355 | AD14: 43950 | AE14: 379239070 | AF14: 0.5 | AG14: 117.33 | AH14: 106.83
A15: 14 | B15: 43962 | C15: 4919 | D15: 49191 | E15: 新唐一 | F15: 39.1 | G15: 20 | H15: 7 | I15: 無擔保 | J15: 4 | K15: 5361 | L15: 100 | M15: 43958 | N15: 39.15 | O15: 39.9 | P15: 1.083 | Q15: 98.12 | R15: 100 | S15: 0.0192 | T15: 100.91 | U15: 0.0284 | V15: 中信證券 | W15: 半導體業 | X15: 473 | Y15: 5361 | Z15: 1 | AA15: 11.33 | AB15: 43956 | AC15: 1800 | AD15: 43971 | AE15: 540953740 | AF15: 0.5 | AG15: 110 | AH15: 100
A16: 15 | B16: 43979 | C16: 6189 | D16: 61893 | E16: 豐藝三 | F16: 18.3 | G16: 10 | H16: 3 | I16: 無擔保 | J16: 4 | K16: 3740 | L16: 101 | M16: 43977 | N16: 34.4 | O16: 34.5 | P16: 1.021 | Q16: 99.71 | R16: 101 | S16: 0.0129 | T16: 103.94 | U16: 0.0424 | V16: 群益證券 | W16: 電子通路業 | X16: 192 | Y16: 3740 | Z16: 1 | AA16: 19.48 | AB16: 43973 | AC16: 850 | AD16: 43990 | AE16: 388726950 | AF16: 0.5 | AG16: 498 | AH16: 101
A17: 16 | B17: 44043 | C17: 9958 | D17: 99584 | E17: 世紀鋼四 | F17: 23.1 | G17: 15 | H17: 3 | I17: 無擔保 | J17: 5 | K17: 10544 | L17: 100 | M17: 44041 | N17: 92.8 | O17: 90.88 | P17: 1.02 | Q17: 102.11 | R17: 100 | S17: -0.0207 | T17: 101.13 | U17: -0.0096 | V17: 群益證券 | W17: 鋼鐵工業 | X17: 426 | Y17: 10544 | Z17: 1 | AA17: 24.75 | AB17: 44039 | AC17: 1275 | AD17: 44054 | AE17: 1066290440 | AF17: 0.5 | AG17: 110 | AH17: 100
... A37: 36 | B37: 44322 | C37: 6641 | D37: 66411 | E37: 基士德KY一 | F37: 3.4 | G37: 3 | H37: 3 | I37: 無擔保 | J37: 5 | K37: 2550 | L37: 100 | M37: 44320 | N37: 71.6 | O37: 76 | P37: 1.05 | Q37: 94.21 | R37: 101.5 | S37: 0.0774 | T37: 104.64 | U37: 0.1107 | V37: 永豐金證 | W37: 綠能環保 | X37: 189 | Y37: 3666 | Z37: 1.44 | AA37: 19.4 | AB37: 44315 | AC37: 255 | AD37: 44333 | AE37: 266842900 | AF37: 0.5 | AG37: 138 | AH37: 104.64
A38: 37 | B38: 44349 | C38: 6015 | D38: 60151 | E38: 宏遠一 | F38: 33.1 | G38: 7 | H38: 5 | I38: 無擔保 | J38: BBB | K38: 7000 | L38: 100 | M38: 44347 | N38: 25.15 | O38: 19.18 | P38: 1.02 | Q38: 131.13 | R38: 114.7 | S38: -0.1253 | T38: 117.8 | U38: -0.1016 | V38: 凱基證券 | W38: 證券業 | X38: 747 | Y38: 21079 | Z38: 3.01 | AA38: 28.22 | AB38: 44343 | AC38: 700 | AD38: 44358 | AE38: 824581730 | AF38: 0.5 | AG38: 151.3 | AH38: 117.8
A39: 38 | B39: 44357 | C39: 6179 | D39: 61792 | E39: 亞通二 | F39: 7.4 | G39: 2 | H39: 3 | I39: 有擔保 | J39: 6 | K39: 1700 | L39: 101 | M39: 44357 | N39: 32.75 | O39: 32.9 | P39: 1.02 | Q39: 99.54 | R39: 114.33 | S39: 0.1485 | T39: 115.29 | U39: 0.1582 | V39: 兆豐證券 | W39: 其他業 | X39: 613 | Y39: 11047 | Z39: 6.5 | AA39: 18.02 | AB39: 44351 | AC39: 170 | AD39: 44369 | AE39: 195992260 | AF39: 0.5 | AG39: 125 | AH39: 115.29
A40: 39 | B40: 44378 | C40: 2482 | D40: 24822 | E40: 連宇二 | F40: 6.2 | G40: 2 | H40: 3 | I40: 有擔保 | J40: 7 | K40: 1700 | L40: 100 | M40: 44378 | N40: 12.5 | O40: 12.65 | P40: 1.025 | Q40: 98.81 | R40: 112.8 | S40: 0.1415 | T40: 114.15 | U40: 0.1552 | V40: 國票證券 | W40: 其他電子業 | X40: 311 | Y40: 6224 | Z40: 3.66 | AA40: 20.01 | AB40: 44372 | AC40: 170 | AD40: 44389 | AE40: 194053150 | AF40: 0.5 | AG40: 117.71 | AH40: 114.15
A41: 40 | B41: 44385 | C41: 6541 | D41: 65481 | E41: 長科一 | F41: 31.2 | G41: 15 | H41: 5 | I41: 有擔保 | J41: 7 | K41: 12750 | L41: 102 | M41: 44383 | N41: 83.1 | O41: 75 | P41: 1.042 | Q41: 110.8 | R41: 118.28 | S41: 0.0675 | T41: 120.56 | U41: 0.0881 | V41: 凱基證券 | W41: 生技醫療業 | X41: 1154 | Y41: 41071 | Z41: 3.22 | AA41: 35.59 | AB41: 44379 | AC41: 1275 | AD41: 44396 | AE41: 1537201910 | AF41: 0.5 | AG41: 128 | AH41: 120.56
A42: 41 | B42: 44386 | C42: 8109 | D42: 81091 | E42: 博大一 | F42: 7.8 | G42: 3 | H42: 3 | I42: 無擔保 | J42: 5 | K42: 2550 | L42: 100 | M42: 44384 | N42: 72.7 | O42: 74 | P42: 1.021 | Q42: 98.24 | R42: 109.8 | S42: 0.1176 | T42: 111.42 | U42: 0.1341 | V42: 凱基證券 | W42: 電子零組件業 | X42: 559 | Y42: 12744 | Z42: 5 | AA42: 22.8 | AB42: 44382 | AC42: 255 | AD42: 44397 | AE42: 284123890 | AF42: 0.5 | AG42: 116.23 | AH42: 111.42
A43: 42 | B43: 44400 | C43: 2338 | D43: 23383 | E43: 光罩三 | F43: 25.3 | G43: 20 | H43: 5 | I43: 無擔保 | J43: 7 | K43: 17200 | L43: 102 | M43: 44398 | N43: 99 | O43: 88.8 | P43: 1.024 | Q43: 111.49 | R43: 112.56 | S43: 0.0096 | T43: 115.23 | U43: 0.0336 | V43: 凱基證券 | W43: 半導體業 | X43: 1154 | Y43: 33705 | Z43: 1.96 | AA43: 29.21 | AB43: 44396 | AC43: 1720 | AD43: 44411 | AE43: 1981888020 | AF43: 0.5 | AG43: 128 | AH43: 115.23
A44: 43 | B44: 44400 | C44: 3028 | D44: 30284 | E44: 增你強四 | F44: 21.4 | G44: 7 | H44: 3 | I44: 無擔保 | J44: 6 | K44: 5100 | L44: 101 | M44: 44398 | N44: 27.65 | O44: 29 | P44: 1.034 | Q44: 95.34 | R44: 107.33 | S44: 0.1257 | T44: 109.18 | U44: 0.1451 | V44: 群益證券 | W44: 電子通路業 | X44: 562 | Y44: 15559 | Z44: 3.05 | AA44: 27.69 | AB44: 44396 | AC44: 510 | AD44: 44411 | AE44: 556814850 | AF44: 0.5 | AG44: 115.2 | AH44: 109.18
A45: 44 | B45: 44403 | C45: 6477 | D45: 64773 | E45: 安集三 | F45: 11.4 | G45: 5 | H45: 5 | I45: 無擔保 | J45: 6 | K45: 4250 | L45: 100 | M45: 44399 | N45: 45.8 | O45: 45.3 | P45: 1.022 | Q45: 101.1 | R45: 103.88 | S45: 0.0275 | T45: 106.99 | U45: 0.0582 | V45: 福邦證券 | W45: 光電業 | X45: 321 | Y45: 7088 | Z45: 1.67 | AA45: 22.08 | AB45: 44397 | AC45: 425 | AD45: 44412 | AE45: 454703100 | AF45: 0.5 | AG45: 116.5 | AH45: 106.99
A46: 45 | B46: 44403 | C46: 6150 | D46: 61505 | E46: 撼訊五 | F46: 4.5 | G46: 7 | H46: 3 | I46: 無擔保 | J46: 8 | K46: 5950 | L46: 100 | M46: 44399 | N46: 139 | O46: 138.3 | P46: 1.021 | Q46: 100.51 | R46: 100.23 | S46: -0.0027 | T46: 104.29 | U46: 0.0376 | V46: 宏遠證券 | W46: 電腦及週邊設備業 | X46: 333 | Y46: 7459 | Z46: 1.25 | AA46: 22.4 | AB46: 44397 | AC46: 595 | AD46: 44412 | AE46: 620518730 | AF46: 0.5 | AG46: 120 | AH46: 104.29
A47: 46 | B47: 44412 | C47: 6209 | D47: 62092 | E47: 今國光二 | F47: 16.3 | G47: 3.5 | H47: 3 | I47: 有擔保 | J47: 6 | K47: 2975 | L47: 100 | M47: 44410 | N47: 33.6 | O47: 35 | P47: 1.036 | Q47: 96 | R47: 113.3 | S47: 0.1802 | T47: 115.17 | U47: 0.1997 | V47: 國票證券 | W47: 光電業 | X47: 696 | Y47: 12874 | Z47: 4.33 | AA47: 18.5 | AB47: 44406 | AC47: 297 | AD47: 44421 | AE47: 342640330 | AF47: 0.5 | AG47: 123.5 | AH47: 115.17
A48: 47 | B48: 44418 | C48: 3533 | D48: 35331 | E48: 嘉澤一 | F48: 10.3 | G48: 10 | H48: 3 | I48: 無擔保 | J48: 4 | K48: 8800 | L48: 102 | M48: 44414 | N48: 570 | O48: 563.2 | P48: 1.02 | Q48: 101.21 | R48: 114.46 | S48: 0.1309 | T48: 115.45 | U48: 0.1407 | V48: 元大證券 | W48: 電子零組件業 | X48: 1352 | Y48: 37818 | Z48: 4.3 | AA48: 27.97 | AB48: 44412 | AC48: 880 | AD48: 44427 | AE48: 1015932860 | AF48: 0.6 | AG48: 163.5 | AH48: 115.45
A49: 48 | B49: 44432 | C49: 3339 | D49: 33394 | E49: 泰谷四 | F49: 4.3 | G49: 3 | H49: 3 | I49: 有擔保 | J49: 8 | K49: 2550 | L49: 102 | M49: 44428 | N49: 18.8 | O49: 19.8 | P49: 1.02 | Q49: 94.95 | R49: 109.3 | S49: 0.1511 | T49: 110.98 | U49: 0.1688 | V49: 富邦證券 | W49: 光電業 | X49: 315 | Y49: 7618 | Z49: 2.99 | AA49: 24.18 | AB49: 44426 | AC49: 255 | AD49: 44441 | AE49: 282999350 | AF49: 0.5 | AG49: 116.5 | AH49: 110.98
A50: 49 | B50: 44439 | C50: 6203 | D50: 62031 | E50: 海韻一 | F50: 8 | G50: 6 | H50: 3 | I50: 無擔保 | J50: 5 | K50: 5116 | L50: 103.5 | M50: 44435 | N50: 97.2 | O50: 95.8 | P50: 1.02 | Q50: 101.46 | R50: 111.1 | S50: 0.095 | T50: 112.84 | U50: 0.1121 | V50: 富邦證券 | W50: 電子零組件業 | X50: 550 | Y50: 13263 | Z50: 2.59 | AA50: 24.11 | AB50: 44433 | AC50: 511 | AD50: 44448 | AE50: 577269840 | AF50: 0.5 | AG50: 119 | AH50: 112.84
... A172: 171 | B172: 45268 | C172: 8488 | D172: 84881 | E172: 吉源一KY | F172: 6.8 | G172: 3 | H172: 3 | I172: 有擔保 | J172: 7 | K172: 2550 | L172: 101 | M172: 45266 | N172: 18.6 | O172: 18.5 | P172: 1.025 | Q172: 100.54 | R172: 102.71 | S172: 0.0216 | T172: 104.67 | U172: 0.0411 | V172: 玉山證券 | W172: 其他業 | X172: 191 | Y172: 5497 | Z172: 2.16 | AA172: 28.78 | AB172: 45264 | AC172: 255 | AD172: 45279 | AE172: 266913480 | AF172: 0.5 | AG172: 112.83 | AH172: 104.67
A173: 172 | B173: 45286 | C173: 6015 | D173: 60152 | E173: 宏遠證二 | F173: 35.1 | G173: 6 | H173: 5 | I173: 無擔保 | J173: BBB | K173: 6000 | L173: 100 | M173: 45282 | N173: 10.85 | O173: 10.92 | P173: 1.021 | Q173: 99.36 | R173: 100.05 | S173: 0.007 | T173: 101.36 | U173: 0.0201 | V173: 凱基證券 | W173: 證券業 | X173: 200 | Y173: 11413 | Z173: 1.9 | AA173: 57.07 | AB173: 45280 | AC173: 600 | AD173: 45296 | AE173: 608160270 | AF173: 0.5 | AG173: 107.1 | AH173: 101.36
A174: 173 | B174: 45287 | C174: 3548 | D174: 35482 | E174: 兆利二 | F174: 6.6 | G174: 8 | H174: 3 | I174: 無擔保 | J174: 5 | K174: 7200 | L174: 101 | M174: 45285 | N174: 195.5 | O174: 199 | P174: 1.031 | Q174: 98.24 | R174: 112.12 | S174: 0.1413 | T174: 113.2 | U174: 0.1523 | V174: 永豐金證 | W174: 電子零組件業 | X174: 1246 | Y174: 42464 | Z174: 5.9 | AA174: 34.08 | AB174: 45281 | AC174: 720 | AD174: 45299 | AE174: 815044010 | AF174: 0.5 | AG174: 118.91 | AH174: 113.2
A175: 174 | B175: 45300 | C175: 6715 | D175: 67152 | E175: 嘉基二 | F175: 6.3 | G175: 3 | H175: 3 | I175: 無擔保 | J175: 5 | K175: 2550 | L175: 100 | M175: 45296 | N175: 157.5 | O175: 168 | P175: 1.021 | Q175: 93.75 | R175: 113.87 | S175: 0.2146 | T175: 114.74 | U175: 0.2239 | V175: 中信證券 | W175: 電子零組件業 | X175: 848 | Y175: 22565 | Z175: 8.85 | AA175: 26.61 | AB175: 45294 | AC175: 255 | AD175: 45309 | AE175: 292598840 | AF175: 0.5 | AG175: 117.38 | AH175: 114.74
A176: 175 | B176: 45301 | C176: 8210 | D176: 82101 | E176: 勤誠一 | F176: 12.1 | G176: 10 | H176: 3 | I176: 無擔保 | J176: 4 | K176: 8974 | L176: 102 | M176: 45299 | N176: 242.5 | O176: 271 | P176: 1.021 | Q176: 89.48 | R176: 108.1 | S176: 0.208 | T176: 109.69 | U176: 0.2258 | V176: 元大證券 | W176: 電腦及週邊設備業 | X176: 862 | Y176: 32252 | Z176: 3.59 | AA176: 37.42 | AB176: 45295 | AC176: 897 | AD176: 45310 | AE176: 984373650 | AF176: 0.5 | AG176: 158 | AH176: 109.69
A177: 176 | B177: 45302 | C177: 3479 | D177: 34793 | E177: 安勤三 | F177: 7.2 | G177: 6.5 | H177: 3 | I177: 無擔保 | J177: 5 | K177: 5700 | L177: 100 | M177: 45300 | N177: 112 | O177: 121.5 | P177: 1.023 | Q177: 92.18 | R177: 108.5 | S177: 0.177 | T177: 109.53 | U177: 0.1882 | V177: 凱基證券 | W177: 電腦及週邊設備業 | X177: 616 | Y177: 25637 | Z177: 4.5 | AA177: 41.62 | AB177: 45296 | AC177: 570 | AD177: 45313 | AE177: 624292740 | AF177: 0.5 | AG177: 116.87 | AH177: 109.53
A178: 177 | B178: 45308 | C178: 4967 | D178: 49673 | E178: 十銓三 | F178: 7.2 | G178: 12 | H178: 3 | I178: 有擔保 | J178: 6 | K178: 10800 | L178: 102 | M178: 45306 | N178: 85.2 | O178: 81 | P178: 1.021 | Q178: 105.19 | R178: 114.16 | S178: 0.0853 | T178: 116.16 | U178: 0.1043 | V178: 永豐金證 | W178: 半導體業 | X178: 885 | Y178: 31244 | Z178: 2.89 | AA178: 35.3 | AB178: 45302 | AC178: 1080 | AD178: 45317 | AE178: 1254497820 | AF178: 0.5 | AG178: 121.19 | AH178: 116.16
A179: 178 | B179: 45308 | C179: 2476 | D179: 24762 | E179: 鉅祥二 | F179: 19.1 | G179: 10 | H179: 3 | I179: 無擔保 | J179: 4 | K179: 8500 | L179: 102 | M179: 45306 | N179: 73.6 | O179: 72.2 | P179: 1.02 | Q179: 101.94 | R179: 112.51 | S179: 0.1037 | T179: 113.8 | U179: 0.1164 | V179: 中信證券 | W179: 電子零組件業 | X179: 792 | Y179: 29362 | Z179: 3.45 | AA179: 37.07 | AB179: 45302 | AC179: 850 | AD179: 45317 | AE179: 967266980 | AF179: 0.5 | AG179: 121.1 | AH179: 113.8
A180: 179 | B180: 45343 | C180: 5263 | D180: 52635 | E180: 智崴五 | F180: 6.5 | G180: 8 | H180: 3 | I180: 有擔保 | J180: 7 | K180: 6800 | L180: 100 | M180: 45341 | N180: 115.5 | O180: 112 | P180: 1.023 | Q180: 103.13 | R180: 112.94 | S180: 0.0952 | T180: 114.83 | U180: 0.1135 | V180: 台新證券 | W180: 文化創意業 | X180: 692 | Y180: 28230 | Z180: 4.15 | AA180: 40.79 | AB180: 45337 | AC180: 680 | AD180: 45355 | AE180: 780836290 | AF180: 0.5 | AG180: 117 | AH180: 114.83
A181: 180 | B181: 45343 | C181: 5321 | D181: 53211 | E181: 美而快一 | F181: 5 | G181: 2 | H181: 3 | I181: 無擔保 | J181: 7 | K181: 1700 | L181: 100 | M181: 45341 | N181: 88.3 | O181: 92 | P181: 1.035 | Q181: 95.98 | R181: 104 | S181: 0.0836 | T181: 105.95 | U181: 0.1039 | V181: 台新證券 | W181: 數位雲端 | X181: 212 | Y181: 5336 | Z181: 3.14 | AA181: 25.17 | AB181: 45337 | AC181: 170 | AD181: 45355 | AE181: 180116430 | AF181: 0.5 | AG181: 116.3 | AH181: 105.95
A182: 181 | B182: 45348 | C182: 6150 | D182: 61506 | E182: 撼訊六 | F182: 4.8 | G182: 4 | H182: 3 | I182: 無擔保 | J182: 8 | K182: 3400 | L182: 100 | M182: 45344 | N182: 91.6 | O182: 90.2 | P182: 1.02 | Q182: 101.55 | R182: 104 | S182: 0.0241 | T182: 105.95 | U182: 0.0433 | V182: 宏遠證券 | W182: 電腦及週邊設備業 | X182: 321 | Y182: 9991 | Z182: 2.94 | AA182: 31.12 | AB182: 45342 | AC182: 340 | AD182: 45358 | AE182: 362909500 | AF182: 0.5 | AG182: 111.88 | AH182: 106.74
A183: 182 | B183: 45348 | C183: 3272 | D183: 32723 | E183: 東碩三 | F183: 6.1 | G183: 3 | H183: 5 | I183: 無擔保 | J183: 6 | K183: 2550 | L183: 100 | M183: 45344 | N183: 34.05 | O183: 34.2 | P183: 1.02 | Q183: 99.56 | R183: 104 | S183: 0.0446 | T183: 105.95 | U183: 0.0642 | V183: 凱基證券 | W183: 電腦及週邊設備業 | X183: 363 | Y183: 11968 | Z183: 4.69 | AA183: 32.97 | AB183: 45342 | AC183: 255 | AD183: 45358 | AE183: 277763680 | AF183: 0.5 | AG183: 114.5 | AH183: 108.93
A184: 183 | B184: 45351 | C184: 8092 | D184: 80924 | E184: 建暐四 | F184: 5.2 | G184: 1.7 | H184: 3 | I184: 有擔保 | J184: 9 | K184: 1530 | L184: 100 | M184: 45348 | N184: 21 | O184: 14.5 | P184: 1.021 | Q184: 144.83 | R184: 137 | S184: -0.054 | T184: 139.45 | U184: -0.0371 | V184: 國票證券 | W184: 其他電子業 | X184: 297 | Y184: 8859 | Z184: 5.79 | AA184: 29.83 | AB184: 45344 | AC184: 153 | AD184: 45362 | AE184: 213351730 | AF184: 0.5 | AG184: 150 | AH184: 139.45
A185: 184 | B185: 45425 | C185: 3483 | D185: 34834 | E185: 力致四 | F185: 8.6 | G185: 2 | H185: 3 | I185: 無擔保 | J185: 6 | K185: 1700 | L185: 101 | M185: 45421 | N185: 162 | O185: 168 | P185: 1.049 | Q185: 96.43 | R185: 117.11 | S185: 0.2145 | T185: 118.57 | U185: 0.2296 | V185: 永豐金證 | W185: 電腦及週邊設備業 | X185: 847 | Y185: 18767 | Z185: 11.04 | AA185: 22.16 | AB185: 45419 | AC185: 170 | AD185: 45434 | AE185: 201571750 | AF185: 0.5 | AG185: 175 | AH185: 118.57
... A231: 230 | B231: 45593 | C231: 4549 | D231: 45491 | E231: 恒達一 | F231: 5.5 | G231: 5 | H231: 3 | I231: 無擔保 | J231: 5 | K231: 4250 | L231: 100 | M231: 45589 | N231: 165.5 | O231: 162.7 | P231: 1.061 | Q231: 101.72 | R231: 114.51 | S231: 0.1257 | T231: 117.27 | U231: 0.1529 | V231: 凱基證券 | W231: 電機機械 | X231: 602 | Y231: 19888 | Z231: 4.68 | AA231: 33.04 | AB231: 45587 | AC231: 425 | AD231: 45603 | AE231: 498382070 | AF231: 0.5 | AG231: 187 | AH231: 117.27
A232: 231 | B232: 45594 | C232: 9958 | D232: 99588 | E232: 世紀鋼八 | F232: 25.7 | G232: 20 | H232: 3 | I232: 無擔保 | J232: 5 | K232: 17950 | L232: 102 | M232: 45590 | N232: 214.5 | O232: 238 | P232: 1.033 | Q232: 90.13 | R232: 102.75 | S232: 0.1401 | T232: 104.82 | U232: 0.163 | V232: 凱基證券 | W232: 鋼鐵工業 | X232: 435 | Y232: 24007 | Z232: 1.34 | AA232: 55.19
A233: 232 | B233: 45596 | C233: 8171 | D233: 81714 | E233: 天宇四 | F233: 7.8 | G233: 2.5 | H233: 3 | I233: 有擔保 | J233: 6 | K233: 2125 | L233: 100 | M233: 45594 | N233: 34.5 | O233: 33.8 | P233: 1.02 | Q233: 102.07 | R233: 110.27 | S233: 0.0803 | T233: 112.44 | U233: 0.1016 | V233: 台中銀證 | W233: 綠能環保 | X233: 222 | Y233: 5411 | Z233: 2.55 | AA233: 24.37 | AB233: 45590 | AC233: 212 | AD233: 45608 | AE233: 238930120 | AF233: 0.5 | AG233: 117.38 | AH233: 112.44
A234: 233 | B234: 45602 | C234: 8374 | D234: 83742 | E234: 羅昇二 | F234: 11.2 | G234: 5 | H234: 3 | I234: 無擔保 | J234: 6 | K234: 4250 | L234: 100 | M234: 45600 | N234: 125.5 | O234: 133.1 | P234: 1.02 | Q234: 94.29 | R234: 104.2 | S234: 0.1051 | T234: 107.06 | U234: 0.1354 | V234: 台新證券 | W234: 電機機械 | X234: 288 | Y234: 9131 | Z234: 2.15 | AA234: 31.7 | AB234: 45596 | AC234: 425 | AD234: 45611 | AE234: 455006980 | AF234: 0.5 | AG234: 116 | AH234: 107.06
A235: 234 | B235: 45602 | C235: 9802 | D235: 98026 | E235: 鈺齊六-KY | F235: 20.1 | G235: 10 | H235: 3 | I235: 無擔保 | J235: 4 | K235: 8500 | L235: 100 | M235: 45600 | N235: 113 | O235: 111 | P235: 1.02 | Q235: 101.8 | R235: 107 | S235: 0.0511 | T235: 108.6 | U235: 0.0668 | V235: 國票證券 | W235: 運動休閒 | X235: 602 | Y235: 21716 | Z235: 2.55 | AA235: 36.07 | AB235: 45596 | AC235: 850 | AD235: 45611 | AE235: 923101060 | AF235: 0.5 | AG235: 117 | AH235: 108.6
A236: 235 | B236: 45604 | C236: 6664 | D236: 66642 | E236: 群翊二 | F236: 6 | G236: 12.5 | H236: 3 | I236: 無擔保 | J236: 6 | K236: 11250 | L236: 100 | M236: 45602 | N236: 285 | O236: 306 | P236: 1.047 | Q236: 93.14 | R236: 105.4 | S236: 0.1317 | T236: 106.98 | U236: 0.1486 | V236: 福邦證券 | W236: 電子零組件業 | X236: 725 | Y236: 27655 | Z236: 2.46 | AA236: 38.14 | AB236: 45600 | AC236: 1125 | AD236: 45615 | AE236: 1203580260 | AF236: 0.5 | AG236: 200 | AH236: 106.98
A237: 236 | B237: 45608 | C237: 3702 | D237: 37023 | E237: 大聯大三 | F237: 167.9 | G237: 20 | H237: 3 | I237: 無擔保 | J237: 4 | K237: 18000 | L237: 100 | M237: 45604 | N237: 76.6 | O237: 78 | P237: 1.022 | Q237: 98.21 | R237: 102.51 | S237: 0.0438 | T237: 104.3 | U237: 0.0621 | V237: 元大證券 | W237: 電子通路業 | X237: 518 | Y237: 44848 | Z237: 2.49 | AA237: 86.58 | AB237: 45602 | AC237: 1800 | AD237: 45617 | AE237: 1877477270 | AF237: 0.5 | AG237: 120 | AH237: 104.3
A238: 237 | B238: 45611 | C238: 3303 | D238: 33035 | E238: 岱稜五 | F238: 9.4 | G238: 5 | H238: 5 | I238: 無擔保 | J238: 6 | K238: 4410 | L238: 100 | M238: 45609 | N238: 60.3 | O238: 62 | P238: 1.028 | Q238: 97.26 | R238: 103 | S238: 0.059 | T238: 105.28 | U238: 0.0825 | V238: 福邦證券 | W238: 其他電子業 | X238: 264 | Y238: 9838 | Z238: 2.23 | AA238: 37.27 | AB238: 45607 | AC238: 441 | AD238: 45622 | AE238: 464283590 | AF238: 0.5 | AG238: 117.5 | AH238: 105.28
A239: 238 | B239: 45614 | C239: 3346 | D239: 33466 | E239: 麗清六 | F239: 12.1 | G239: 3 | H239: 3 | I239: 無擔保 | J239: 7 | K239: 2656 | L239: 100 | M239: 45610 | N239: 36.1 | O239: 38 | P239: 1.022 | Q239: 95 | R239: 100 | S239: 0.0526 | T239: 101.12 | U239: 0.0644 | V239: 永豐證券 | W239: 汽車工業 | X239: 35 | Y239: 1524 | Z239: 0.57 | AA239: 43.54 | AB239: 45608 | AC239: 265 | AD239: 45623 | AE239: 115179630 | AF239: 0.5 | AG239: 120 | AH239: 100
A240: 239 | B240: 45616 | C240: 3313 | D240: 33133 | E240: 斐成三 | F240: 16.9 | G240: 4 | H240: 3 | I240: 有擔保 | J240: 7 | K240: 3480 | L240: 100 | M240: 45614 | N240: 15.2 | O240: 16.5 | P240: 1.03 | Q240: 92.12 | R240: 100 | S240: 0.0855 | T240: 103.94 | U240: 0.1283 | V240: 合庫證券 | W240: 其他業 | X240: 85 | Y240: 3753 | Z240: 1.08 | AA240: 44.15 | AB240: 45610 | AC240: 348 | AD240: 45625 | AE240: 337296910 | AF240: 1 | AG240: 120 | AH240: 100
A241: 240 | B241: 45622 | C241: 6870 | D241: 68702 | E241: 騰雲二 | F241: 2.3 | G241: 3.5 | H241: 5 | I241: 無擔保 | J241: 6 | K241: 3150 | L241: 101 | M241: 45618 | N241: 267 | O241: 236.6 | P241: 1.02 | Q241: 112.85 | R241: 108.64 | S241: -0.0373 | T241: 112.33 | U241: -0.0046 | V241: 元大證券 | W241: 數位雲端 | X241: 277 | Y241: 12249 | Z241: 3.89 | AA241: 44.22 | AB241: 45616 | AC241: 315 | AD241: 45631 | AE241: 353846790 | AF241: 0.5 | AG241: 130 | AH241: 112.33
A242: 241 | B242: 45624 | C242: 8489 | D242: 84891 | E242: 三貝德一 | F242: 3.7 | G242: 3 | H242: 3 | I242: 有擔保 | J242: 6 | K242: 2700 | L242: 100 | M242: 45622 | N242: 29.1 | O242: 28.8 | P242: 1.02 | Q242: 101.04 | R242: 110.38 | S242: 0.0924 | T242: 111 | U242: 0.0986 | V242: 台中銀證 | W242: 其他業 | X242: 160 | Y242: 6461 | Z242: 2.39 | AA242: 40.38 | AB242: 45618 | AC242: 270 | AD242: 45635 | AE242: 299692100 | AF242: 0.5 | AG242: 113.58 | AH242: 111
A243: 242 | B243: 45632 | C243: 5608 | D243: 56087 | E243: 四維航七 | F243: 38.9 | G243: 6 | H243: 3 | I243: 有擔保 | J243: 7 | K243: 5100 | L243: 100 | M243: 45630 | N243: 17.6 | O243: 19.3 | P243: 1.032 | Q243: 91.19 | R243: 100.87 | S243: 0.1061 | T243: 102.44 | U243: 0.1233 | V243: 永豐證券 | W243: 航運業 | X243: 165 | Y243: 7280 | Z243: 1.43 | AA243: 44.12 | AB243: 45628 | AC243: 510 | AD243: 45643 | AE243: 522419970 | AF243: 0.5 | AG243: 110 | AH243: 102.44
A244: 243 | B244: 45635 | C244: 5245 | D244: 52452 | E244: 智晶二 | F244: 4.5 | G244: 3 | H244: 3 | I244: 無擔保 | J244: 6 | K244: 2550 | L244: 100 | M244: 45631 | N244: 36.4 | O244: 35 | P244: 1.02 | Q244: 104 | R244: 100 | S244: -0.0385 | T244: 101.1 | U244: -0.0279 | V244: 台新證券 | W244: 光電業 | X244: 100 | Y244: 3666 | Z244: 1.44 | AA244: 36.66 | AB244: 45629 | AC244: 255 | AD244: 45644 | AE244: 257797350 | AF244: 0.5 | AG244: 106.8 | AH244: 101.1
... A305: 304 | B305: 45855 | C305: 4442 | D305: 44421 | E305: 竣邦一KY | F305: 3.12 | G305: 1.5 | H305: 3 | I305: 無擔保 | J305: 6 | K305: 1275 | L305: 100 | M305: 45853 | N305: 46.05 | O305: 49 | P305: 1.03 | Q305: 93.98 | R305: 100 | S305: 0.0641 | T305: 100.37 | U305: 0.068 | V305: 台新證券 | W305: 紡織纖維 | X305: 64 | Y305: 1445 | Z305: 1.13 | AA305: 22.58 | AB305: 45849 | AC305: 127 | AD305: 45866 | AE305: 127965450 | AF305: 0.5 | AG305: 103.1 | AH305: 100.37

Sheet 05_CB競拍篩選條件區間
A1: 轉換價格 | B1: 股本大小 | C1: 規模大小 | D1: 信評 | E1: 產業分類 | F1: 發行年期 | G1: 發行券商 | H1: 承銷方式 | I1: 擔保 | J1: 資金用途
A2: 1_轉換價格_小於20元 | B2: 1_股本大小_小於3億 | C2: 1_發行規模_小於2億 | D2: 2 | E2: 資訊服務 | F2: 3 | G2: 統一證券 | H2: 詢圈 | I2: 有擔保 | J2: 償還銀行借款
A3: 2_轉換價格_介於20~50元 | B3: 2_股本大小_3~6億 | C3: 2_發行規模_2~5億 | D3: 3 | E3: 化工 | F3: 5 | G3: 第一金證 | H3: 競拍 | I3: 無擔保 | J3: 充實營運資金
A4: 3_轉換價格_介於50~100元 | B4: 3_股本大小_6~10億 | C4: 3_發行規模_5~10億 | D4: 4 | E4: 航運 | F4: 7 | G4: 國票證券 | J4: 併購/轉投資
A5: 4_轉換價格_介於100~150元 | B5: 4_股本大小_10~15億 | C5: 4_發行規模_10~15億 | D5: 5 | E5: 其他電子 | G5: 富邦證券 | J5: 購買機器設備
A6: 5_轉換價格_介於150~200元 | B6: 5_股本大小_15~20億 | C6: 5_發行規模_15~20億 | D6: 6 | E6: 油電燃氣 | G6: 永豐金證 | J6: 擴廠/建廠
A7: 6_轉換價格_大於200元 | B7: 6_股本大小_大於20億 | C7: 6_發行規模_大於20億 | D7: 7 | E7: 農業科技 | G7: 凱基證券 | J7: 購買不動產
D8: 8 | E8: 文化創意 | G8: 中信證券 | J8: 研發
D9: 9 | E9: 建材營造 | G9: 台新證券 | J9: 借新還舊
D10: BBB | E10: 生技醫療 | G10: 兆豐證券
E11: 電子零組件 | G11: 福邦證券
E12: 電腦及週邊設備 | G12: 群益證券
E13: 電機機械 | G13: 台中銀證
E14: 半導體 | G14: 元大證券
E15: 光電 | G15: 元富證券
E16: 運動休閒 | G16: 國泰證券
E17: 其他 | G17: 華南永昌
E18: 綠能環保 | G18: 合庫證券
E19: 電器電纜 | G19: 宏遠證券
E20: 通信網路 | G20: 康和證券
E21: 電子通路 | G21: 永豐證券
E22: 貿易百貨 | G22: 玉山證券
E23: 鋼鐵
E24: 觀光餐旅
E25: 金融保險
E26: 汽車
E27: 居家生活
E28: 數位雲端
E29: 造紙
E30: 塑膠
E31: 紡織纖維
E32: 食品
E33: 水泥

Sheet 06_發行案件
A1: 股票代號 | B1: 詢圈/競拍 | C1: 標的代號 | D1: 發行標的 | E1: TCRI/擔保 | F1: 發行量 | G1: 發行券商 | H1: 送件日 | I1: 生效日 | J1: 詢圈/投標期間 | K1: 溢價率 | L1: 轉換價 | M1: 掛牌日 | N1: 可拆解選擇權日 | O1: 承銷價格 | P1: 年期 | Q1: 賣回條件 | R1: 股本 | S1: 股價 | T1: 60天波動率 | U1: 備註
A2: =LEFT(C2,4) -> 3135 | B2: 詢圈 | C2: 31351 | D2: 凌航一 | E2: TCRI6 | F2: 10 | G2: 統一證券 | H2: 2025/10/31 | I2: 2025/11/18 | J2: 11/21-11/24 | K2: 1.0501 | L2: 52.19 | M2: 45995 | N2: 無報價2025/12/11 | O2: 100 | P2: 3Y | Q2: YTP(2)=(1%) | R2: 7.7493405 | S2: 67.3 | T2: 80.93
A3: =LEFT(C3,4) -> 2732 | B3: 詢圈 | C3: 27324 | D3: 六角四 | E3: TCRI5 | F3: 6 | G3: 華南永昌證 | H3: 2025/10/31 | I3: 2025/11/18 | J3: 11/24-11/26 | K3: 1.051 | L3: 74.3 | M3: 45999 | N3: 額度有限2025/12/15 | O3: 100 | P3: 5Y | Q3: YTP(2)=(0.5%) | R3: 4.651857 | S3: 74.9 | T3: 25.16
A4: =LEFT(C4,4) -> 6890 | B4: 競拍 | C4: 68902 | D4: 來億二KY | E4: TCRI5 | F4: 5 | G4: 富邦證券 | H4: 2025/10/23 | I4: 2025/11/11 | J4: 11/25-11/27 | K4: 1.02 | L4: 245.2 | M4: 46001 | N4: 無報價2025/12/17 | O4: 119.83 | P4: 3Y | Q4: YTM(3)=(0%) | R4: 24.94 | S4: 280.5 | T4: 53
A5: =LEFT(C5,4) -> 6442 | B5: 競拍 | C5: 64423 | D5: 光聖三 | E5: TCRI5 | F5: 15 | G5: 台新證券 | H5: 2025/10/21 | I5: 2025/11/07 | J5: 11/26-11/28 | K5: 1.02 | L5: 1065.9 | M5: 46002 | N5: 46009 | O5: 124.86 | P5: 3Y | Q5: YTP(2)=(0%) | R5: 7.7343078 | S5: 1190 | T5: 70.77
A6: =LEFT(C6,4) -> 5309 | B6: 詢圈 | C6: 53096 | D6: 系統電六 | E6: TCRI6 | F6: 7 | G6: 富邦證券 | H6: 2025/10/27 | I6: 2025/11/12 | J6: 11/28-12/2 | K6: 1.051 | L6: 63.5 | M6: 46003 | N6: 無報價2025/12/19 | O6: 100.5 | P6: 5Y | Q6: YTP(3)=(1%) | R6: 20.442378 | S6: 61.8 | T6: 56.65
A7: =LEFT(C7,4) -> 5309 | B7: 競拍 | C7: 53097 | D7: 系統電七 | E7: TCRI6 | F7: 5 | G7: 富邦證券 | H7: 2025/10/27 | I7: 2025/11/12 | J7: 11/28-12/2 | K7: 1.028 | L7: 55 | M7: 46006 | N7: 無報價2025/12/22 | O7: 116.91 | P7: 3Y | Q7: YTP(2)=(0.5%) | R7: 20.442378 | S7: 60.8 | T7: 56.65
A8: =LEFT(C8,4) -> 8042 | B8: 詢圈 | C8: 80426 | D8: 金山電六 | E8: TCRI7 | F8: 3.5 | G8: 永豐金證券 | H8: 2025/10/08 | I8: 2025/10/28 | J8: 12/3-12/4 | K8: 1.0526 | L8: 60 | M8: 46007 | N8: 無報價2025/12/23 | O8: 100 | P8: 3Y | Q8: YTP(2)=(0%) | R8: 12.946255 | S8: 57.3 | T8: 76.42
A9: =LEFT(C9,4) -> 4739 | B9: 競拍 | C9: 47394 | D9: 康普四 | E9: 第一銀行 | F9: 6 | G9: 福邦證券 | H9: 2025/11/03 | I9: 2025/11/19 | J9: 12/2-12/4 | K9: 1.086 | L9: 71 | M9: 46008 | N9: 46015 | O9: 110.46 | P9: 5Y | Q9: YTP(3)=(0%) | R9: 11.864927 | S9: 69.2 | T9: 38.92
A10: =LEFT(C10,4) -> 6796 | B10: 詢圈 | C10: 67962 | D10: 晉弘二 | E10: TCRI7 | F10: 2 | G10: 富邦證券 | H10: 2025/10/17 | I10: 2025/11/05 | J10: 12/8-12/10 | K10: 105.01-110% | L10: - | M10: 未定 | N10: 無報價 | O10: 100.5 | P10: 3Y | Q10: YTP(2)=(0-0.5%) | R10: 3.823397 | S10: 94.2 | T10: 31.96
A11: =LEFT(C11,4) -> 6904 | B11: 競拍 | C11: 69041 | D11: 伯鑫一 | E11: TCRI6 | F11: 2 | G11: 國泰證券 | H11: 2025/10/22 | I11: 2025/11/10 | J11: 12/10-12/12 | K11: 1.04 | L11: 130 | M11: 46017 | N11: 無報價2026/1/5 | O11: 102 | P11: 3Y | Q11: YTM(3)=(0%) | R11: 1.85 | S11: 118 | T11: 12.76
A12: =LEFT(C12,4) -> 3543 | B12: 競拍 | C12: 35431 | D12: 州巧一 | E12: 中國信託 | F12: 4 | G12: 福邦證券 | H12: 2025/10/27 | I12: 45988 | J12: 12/10-12/12 | K12: 1.048 | L12: 46.3 | M12: 46017 | N12: 46027 | O12: 100 | P12: 3Y | Q12: YTM(3)=(0%) | R12: 8.926315 | S12: 46.2 | T12: 67.83
A13: =LEFT(C13,4) -> 6670 | B13: 競拍 | C13: 66702 | D13: 復盛應用二 | E13: TCRI3 | F13: 15 | G13: 台新證券 | H13: 2025/06/18 | I13: 2025/07/04 | J13: 12/10-12/12 | K13: 1.0568 | L13: 270 | M13: 46017 | N13: 46027 | O13: 103 | P13: 3Y | Q13: YTM(3)=(0%) | R13: 13.938697 | S13: 257 | T13: 22.97 | U13: 延長三個月
A14: =LEFT(C14,4) -> 4113 | B14: 競拍 | C14: 41136 | D14: 聯上六 | E14: TCRI7 | F14: 3 | G14: 合庫證券 | H14: 2025/07/23 | I14: 45910 | J14: 未定 | K14: 102-110% | L14: - | M14: 未定 | N14: 未定 | O14: 100 | P14: 5Y | Q14: YTP(3)=(0.75%) | R14: 23.113814 | S14: 22.4 | T14: 31.76 | U14: 延長三個月
A15: =LEFT(C15,4) -> 2236 | B15: 詢圈 | C15: 22363 | D15: 百達三KY | E15: TCRI7 | F15: 4.5 | G15: 台新證券 | H15: 2025/08/07 | I15: 2025/08/25 | J15: 未定 | K15: 105.01-110% | L15: - | M15: 未定 | N15: 未定 | O15: 100 | P15: 5Y | Q15: YTP(3)=(0.5%) | R15: 5.9555656 | S15: 104.5 | T15: 43.12
A16: =LEFT(C16,4) -> 8299 | B16: 詢圈 | C16: 82993 | D16: 群聯三 | E16: TCRI3 | F16: 60 | G16: 凱基證券 | H16: 2025/08/08 | I16: 45910 | J16: 未定 | K16: 110-120% | L16: - | M16: 未定 | N16: 未定 | O16: 100-101 | P16: 5Y | Q16: YTP(3)=(0.6%) | R16: 20.662783 | S16: 1080 | T16: 77.95 | U16: 延長至115/3/9
A17: =LEFT(C17,4) -> 3715 | B17: 詢圈 | C17: 37151 | D17: 定穎一 | E17: TCRI5 | F17: 5 | G17: 凱基證券 | H17: 2025/11/03 | I17: 2025/11/19 | J17: 未定 | K17: 105.1-110% | L17: - | M17: 未定 | N17: 未定 | O17: 100.5-101 | P17: 3Y | Q17: YTM(3)=(0%) | R17: 27.767458 | S17: 112 | T17: 71.34
A18: =LEFT(C18,4) -> 3715 | B18: 競拍 | C18: 37152 | D18: 定穎二 | E18: TCRI5 | F18: 10 | G18: 凱基證券 | H18: 2025/11/03 | I18: 2025/11/19 | J18: 未定 | K18: 102-103% | L18: - | M18: 未定 | N18: 未定 | O18: 102 | P18: 3Y | Q18: YTM(3)=(0%) | R18: 27.767458 | S18: 112 | T18: 71.34
A19: =LEFT(C19,4) -> 6510 | B19: 競拍 | C19: 65101 | D19: 精測一 | E19: TCRI4 | F19: 20 | G19: 元大證券 | H19: 2025/11/07 | I19: 2025/11/25 | J19: 未定 | K19: 103-105% | L19: - | M19: 未定 | N19: 未定 | O19: 100-103 | P19: 3Y | Q19: YTM(3)=(0%) | R19: 3.2789022 | S19: 1900 | T19: 69.77
A20: =LEFT(C20,4) -> 2745 | B20: 競拍 | C20: 27451 | D20: 五福一 | E20: TCRI4 | F20: 3 | G20: 台新證券 | H20: 2025/11/18 | I20: 2025/12/04 | J20: 未定 | K20: 102-110% | L20: - | M20: 未定 | N20: 未定 | O20: 100 | P20: 3Y | Q20: YTP(2)=(0.5%) | R20: 3.3808526 | S20: 110 | T20: 27.49
A21: =LEFT(C21,4) -> 8431 | B21: 詢圈 | C21: 84312 | D21: 匯鑽科二 | E21: TCRI7 | F21: 3 | G21: 華南永昌證 | H21: 2025/11/27 | I21: 2025/12/15 | J21: 未定 | K21: 102-111% | L21: - | M21: 未定 | N21: 未定 | O21: 100 | P21: 3Y | Q21: YTP(2)=(0-0.5%) | R21: 4.4391482 | S21: 50.6 | T21: 39.63
A22: =LEFT(C22,4) -> 2467 | B22: 詢圈 | C22: 24672 | D22: 志聖二 | E22: TCRI5 | F22: 7 | G22: 富邦證券 | H22: 2025/11/28 | I22: 2025/12/16 | J22: 未定 | K22: 105.01-110% | L22: - | M22: 未定 | N22: 未定 | O22: 100-105 | P22: 3Y | Q22: YTP(2)=(0-0.5%) | R22: 15.675535 | S22: 206 | T22: 43.19
A23: =LEFT(C23,4) -> 2467 | B23: 競拍 | C23: 24673 | D23: 志聖三 | E23: TCRI5 | F23: 10 | G23: 富邦證券 | H23: 2025/11/28 | I23: 2025/12/16 | J23: 未定 | K23: 102-115% | L23: - | M23: 未定 | N23: 未定 | O23: 100 | P23: 3Y | Q23: YTP(2)=(0-0.5%) | R23: 15.675535 | S23: 206 | T23: 43.19
A24: =LEFT(C24,4) -> 3260 | B24: 詢圈 | C24: 32608 | D24: 威剛八 | E24: TCRI5 | F24: 20 | G24: 群益金鼎證 | H24: 2025/12/01 | I24: 2025/12/17 | J24: 未定 | K24: 101.5-110% | L24: - | M24: 未定 | N24: 未定 | O24: 100 | P24: 3Y | Q24: YTP(2)=(0-0.5%) | R24: 32.578565 | S24: 177 | T24: 59.31
A25: =LEFT(C25,4) -> 3717 | B25: 競拍 | C25: 37171 | D25: 聯嘉投控一 | E25: 安泰銀行 | F25: 7 | G25: 國泰證券 | H25: 2025/12/02 | I25: 2025/12/18 | J25: 未定 | K25: 102-105% | L25: - | M25: 未定 | N25: 未定 | O25: 100 | P25: 3Y | Q25: YTP(2)=(0.25%) | R25: 20.784544 | S25: 17.25 | T25: 27.77
A26: =LEFT(C26,4) -> 6199 | B26: 競拍 | C26: 61993 | D26: 天品三 | E26: 上海商銀 | F26: 2.5 | G26: 群益金鼎證 | H26: 2025/12/02 | I26: 2025/12/18 | J26: 未定 | K26: 102-110% | L26: - | M26: 未定 | N26: 未定 | O26: 100 | P26: 3Y | Q26: YTP(2)=(0-1%) | R26: 6.1760018 | S26: 95.9 | T26: 51.65
A27: =LEFT(C27,4) -> 6199 | B27: 詢圈 | C27: 61994 | D27: 天品四 | E27: TCRI7 | F27: 3.5 | G27: 群益金鼎證 | H27: 2025/12/02 | I27: 2025/12/18 | J27: 未定 | K27: 105.1-110% | L27: - | M27: 未定 | N27: 未定 | O27: 100-100.8 | P27: 3Y | Q27: YTP(2)=(0-1%) | R27: 6.1760018 | S27: 95.9 | T27: 51.65
A28: =LEFT(C28,4) -> 3290 | B28: 詢圈 | C28: 32904 | D28: 東浦四 | E28: TCRI6 | F28: 7 | G28: 台新證券 | H28: 2025/12/04 | I28: 2025/12/22 | J28: 未定 | K28: 101-110% | L28: - | M28: 未定 | N28: 未定 | O28: 100-100.5 | P28: 3Y | Q28: YTP(2)=(0.5%) | R28: 9.0215034 | S28: 42.25 | T28: 37.83
A29: =LEFT(C29,4) -> 3290 | B29: 競拍 | C29: 32905 | D29: 東浦五 | E29: TCRI6 | F29: 3 | G29: 台新證券 | H29: 2025/12/04 | I29: 2025/12/22 | J29: 未定 | K29: 101-110% | L29: - | M29: 未定 | N29: 未定 | O29: 100 | P29: 3Y | Q29: YTP(2)=(0.5%) | R29: 9.0215034 | S29: 42.25 | T29: 37.83
A30: =LEFT(C30,4) -> 4967 | B30: 競拍 | C30: 49674 | D30: 十銓四 | E30: 台中銀行 | F30: 20 | G30: 永豐金證券 | H30: 2025/12/04 | I30: 2025/12/22 | J30: 未定 | K30: 102-110% | L30: - | M30: 未定 | N30: 未定 | O30: 100 | P30: 3Y | Q30: YTM(3)=(0%) | R30: 8.4963288 | S30: 132.5 | T30: 69.04
A31: =LEFT(C31,4) -> 2301 | B31: 競拍 | C31: 23011 | D31: 光寶一 | E31: TCRI3 | F31: 40 | G31: 元大證券 | H31: 2025/12/05 | I31: 2025/12/23 | J31: 未定 | K31: 105-112% | L31: - | M31: 未定 | N31: 未定 | O31: 101 | P31: 5Y | Q31: YTP(3)=(0-0.25%) | R31: 231.67758 | S31: 160 | T31: 52.68
A32: =LEFT(C32,4) -> 2301 | B32: 詢圈 | C32: 23012 | D32: 光寶二 | E32: TCRI3 | F32: 80 | G32: 元大證券 | H32: 2025/12/05 | I32: 2025/12/23 | J32: 未定 | K32: 110-120% | L32: - | M32: 未定 | N32: 未定 | O32: 100 | P32: 5Y | Q32: YTP(3)=(0-0.25%) | R32: 231.67758 | S32: 160 | T32: 52.68
A33: =LEFT(C33,4) -> 3702 | B33: 詢圈 | C33: 370201 | D33: 大聯大E1 | E33: TCRI4 | F33: 30 | G33: 凱基證券 | H33: 2025/12/05 | I33: 2025/12/16 | J33: 未定 | K33: 102-130% | L33: - | M33: 未定 | N33: 未定 | O33: 100-101 | P33: 3Y | Q33: YTM(3)=(0%) | R33: 167.90568 | S33: 65.8 | T33: 27.37 | U33: 轉交換文曄
A34: =LEFT(C34,4) -> 8021 | B34: 競拍 | C34: 80212 | D34: 尖點二 | E34: TCRI4 | F34: 7 | G34: 福邦證券 | H34: 2025/12/05 | I34: 2025/12/23 | J34: 未定 | K34: 102-110% | L34: - | M34: 未定 | N34: 未定 | O34: 100 | P34: 5Y | Q34: YTP(3)=(0%) | R34: 14.204247 | S34: 135 | T34: 81.24
A35: =LEFT(C35,4) -> 6101 | B35: 競拍 | C35: 61011 | D35: 寬魚國際一 | E35: 有擔保 | F35: 1.5 | G35: 富邦證券 | H35: 2025/12/08 | I35: 2026/01/07 | J35: 未定 | K35: 102-105% | L35: - | M35: 未定 | N35: 未定 | O35: 100.5 | P35: 3Y | Q35: YTP(2)=(0%) | R35: 11.461837 | S35: 37.2 | T35: 10.27
A36: =LEFT(C36,4) -> 6101 | B36: 詢圈 | C36: 61012 | D36: 寬魚國際二 | E36: - | F36: 2.5 | G36: 富邦證券 | H36: 2025/12/08 | I36: 2026/01/07 | J36: 未定 | K36: 105.01-110% | L36: - | M36: 未定 | N36: 未定 | O36: 100 | P36: 3Y | Q36: YTP(2)=(0-0.5%) | R36: 11.461837 | S36: 37.2 | T36: 10.27
A37: =LEFT(C37,4) -> 8210 | B37: 詢圈 | C37: 82102 | D37: 勤誠二 | E37: TCRI4 | F37: 8 | G37: 元大證券 | H37: 2025/12/09 | I37: 2025/12/26 | J37: 未定 | K37: 105.1-108% | L37: - | M37: 未定 | N37: 未定 | O37: 100-102 | P37: 3Y | Q37: YTM(3)=(0%) | R37: 12.531915 | S37: 891 | T37: 53.58
A38: =LEFT(C38,4) -> 8210 | B38: 競拍 | C38: 82103 | D38: 勤誠三 | E38: TCRI4 | F38: 7 | G38: 元大證券 | H38: 2025/12/09 | I38: 2025/12/26 | J38: 未定 | K38: 102-108% | L38: - | M38: 未定 | N38: 未定 | O38: 102 | P38: 3Y | Q38: YTM(3)=(0%) | R38: 12.531915 | S38: 891 | T38: 53.58

Sheet 07_董事會決議
A1: 股鰾代號 | B1: 詢圈/競價 | C1: CB代碼 | D1: 發行標的 | E1: TCRI/擔保 | F1: 發行量 | G1: 主辦券商 | H1: 到期日 | I1: 董事會通過 | J1: 股本(億) | K1: 備註
A2: =LEFT(C2,4) -> 6807 | B2: 詢圈 | C2: 68071 | D2: 峰源一KY | E2: TCRI5 | F2: 6.5 | G2: 永豐金證券 | H2: 5Y | I2: 45729 | J2: 5.4
A3: =LEFT(C3,4) -> 6692 | B3: 詢圈 | C3: 66921 | D3: 進能服一 | E3: TCRI6 | F3: 2 | G3: 元大證券 | H3: 5Y | I3: 45785 | J3: 5.877639 | K3: 100-102%
A4: =LEFT(C4,4) -> 8431 | B4: 詢圈 | C4: 84312 | D4: 匯鑽科二 | E4: TCRI7 | F4: 5 | G4: 未定 | H4: 3Y | I4: 45786 | J4: 4.4391482
A5: =LEFT(C5,4) -> 2109 | B5: 詢圈 | C5: 21092 | D5: 華豐二 | E5: TCRI6 | F5: 10 | G5: 富邦證券 | H5: 3Y | I5: 45789 | J5: 27.934913
A6: =LEFT(C6,4) -> 4760 | B6: 詢圈 | C6: 47602 | D6: 勤凱二 | E6: TCRI6 | F6: 4 | G6: 未定 | H6: 3Y | I6: 45874 | J6: 3.2218283 | K6: 1.05
A7: =LEFT(C7,4) -> 6576 | B7: 競拍 | C7: 65761 | D7: 逸達一 | E7: 有擔保 | F7: 4 | G7: 未定 | H7: 3Y | I7: 45917 | J7: 15.741376
A8: =LEFT(C8,4) -> 6862 | B8: 詢圈 | C8: 68621 | D8: 三集瑞一KY | E8: TCRI6 | F8: 10 | G8: 華南永昌證 | H8: 3Y | I8: 45925 | J8: 5 | K8: 100-101%
A9: =LEFT(C9,4) -> 3701 | B9: 競拍 | C9: 37013 | D9: 大眾控三 | E9: TCRI6 | F9: 6 | G9: 富邦證券 | H9: 3Y | I9: 45933 | J9: 23.652661
A10: =LEFT(C10,4) -> 2329 | B10: 詢圈 | C10: 23291 | D10: 華泰一 | E10: TCRI5 | F10: 25 | G10: 未定 | H10: 3Y | I10: 45959 | J10: 65.900433 | K10: 100-102%
A11: =LEFT(C11,4) -> 2455 | B11: 詢圈 | C11: 24552 | D11: 全新二 | E11: TCRI5 | F11: 5 | G11: 未定 | H11: 3Y | I11: 45960 | J11: 18.490592 | K11: 100-110%
A12: =LEFT(C12,4) -> 2455 | B12: 競拍 | C12: 24553 | D12: 全新三 | E12: TCRI5 | F12: 25 | G12: 未定 | H12: 3Y | I12: 45960 | J12: 18.490592 | K12: 1.02
A13: =LEFT(C13,4) -> 2233 | B13: 詢圈 | C13: 22331 | D13: 宇隆一 | E13: TCRI4 | F13: 13 | G13: 未定 | H13: 3Y | I13: 45966 | J13: 6.0288089 | K13: 100-102%
A14: =LEFT(C14,4) -> 6547 | B14: 競拍 | C14: 65472 | D14: 高端二 | E14: 有擔保 | F14: 7.5 | G14: 未定 | H14: 3Y | I14: 45967 | J14: 32.874905 | K14: 1.005
A15: =LEFT(C15,4) -> 6672 | B15: 詢圈 | C15: 66721 | D15: 騰輝一KY | E15: TCRI6 | F15: 5 | G15: 永豐金證券 | H15: 5Y | I15: 45968 | J15: 7.1434745 | K15: 100-101%
A16: =LEFT(C16,4) -> 6672 | B16: 競拍 | C16: 66722 | D16: 騰輝二KY | E16: TCRI6 | F16: 5 | G16: 永豐金證券 | H16: 5Y | I16: 45968 | J16: 7.1434745
A17: =LEFT(C17,4) -> 3587 | B17: 競拍 | C17: 35872 | D17: 閎康二 | E17: TCRI4 | F17: 7 | G17: 元大證券 | H17: 5Y | I17: 45968 | J17: 6.7038234
A18: =LEFT(C18,4) -> 6913 | B18: 競拍 | C18: 69131 | D18: 鴻呈一 | E18: TCRI6 | F18: 4.5 | G18: 未定 | H18: 3Y | I18: 45971 | J18: 4.3848863
A19: =LEFT(C19,4) -> 5534 | B19: 詢圈 | C19: 55344 | D19: 長虹四 | E19: TCRI5 | F19: 15 | G19: 群益金鼎證 | H19: 5Y | I19: 45972 | J19: 29.032596 | K19: 100-101%
A20: =LEFT(C20,4) -> 6603 | B20: 詢圈 | C20: 66034 | D20: 富強鑫四 | E20: TCRI6 | F20: 4 | G20: 統一證券 | H20: 3Y | I20: 45972 | J20: 16.722059
A21: =LEFT(C21,4) -> 8476 | B21: 詢圈 | C21: 84762 | D21: 台境二 | E21: TCRI7 | F21: 2.5 | G21: 未定 | H21: 3Y | I21: 45973 | J21: 8.3113179 | K21: 100-101%
A22: =LEFT(C22,4) -> 2762 | B22: 詢圈 | C22: 27621 | D22: 世界健身一KY | E22: TCRI5 | F22: 5 | G22: 未定 | H22: 3Y | I22: 45973 | J22: 11.25 | K22: 100-101%
A23: =LEFT(C23,4) -> 8467 | B23: 競拍 | C23: 84674 | D23: 波力四KY | E23: 上海商銀 | F23: 2.1 | G23: 富邦證券 | H23: 3Y | I23: 45974 | J23: 5.0373575 | K23: 1.005
A24: =LEFT(C24,4) -> 8467 | B24: 詢圈 | C24: 84675 | D24: 波力五KY | E24: TCRI6 | F24: 3.9 | G24: 富邦證券 | H24: 3Y | I24: 45974 | J24: 5.0373575 | K24: 1.005
A25: =LEFT(C25,4) -> 3149 | B25: 競拍 | C25: 31494 | D25: 正達四 | E25: 有擔保 | F25: 6.5 | G25: 未定 | H25: 3Y | I25: 45983 | J25: 22.62336
A26: =LEFT(C26,4) -> 3011 | B26: 競拍 | C26: 30112 | D26: 今皓二 | E26: 有擔保 | F26: 4.5 | G26: 群益金鼎證 | H26: 3Y | I26: 45987 | J26: 11.271925
A27: =LEFT(C27,4) -> 4714 | B27: 競拍 | C27: 47148 | D27: 永捷八 | E27: 第一銀行 | F27: 3 | G27: 元富證券 | H27: 3Y | I27: 45996 | J27: 17.808819
A28: =LEFT(C28,4) -> 1727 | B28: 詢圈 | C28: 17272 | D28: 中華化二 | E28: TCRI6 | F28: 6 | G28: 富邦證券 | H28: 3Y | I28: 46001 | J28: 12.801956

Sheet 08_最新動態每週基本資料
A1: 代號 | B1: 名稱 | C1: 英文名稱 | D1: 票面利率 | E1: 轉換價格(元) | F1: 轉換價格生效日期 | G1: 轉換標的代碼 | H1: 轉換標的名稱 | I1: 轉換日期起 | J1: 轉換日期迄 | K1: 發行日期 | L1: 掛牌日期 | M1: 到期日 | N1: 到期價格 | O1: 到期殖利率 | P1: 申請發行總額(百萬) | Q1: 實際發行總額(百萬) | R1: 發行價格(元) | S1: 最新餘額(百萬) | T1: 還本年限 | U1: 發行時轉換價格(元) | V1: 承銷機構 | W1: 過戶機構 | X1: 提前償還日 | Y1: 提前償還日1 | Z1: 提前償還價格1 | AA1: 提前償還殖利率1 | AB1: 提前償還日2 | AC1: 提前償還價格2 | AD1: 提前償還殖利率2 | AE1: 提前償還日3 | AF1: 提前償還價格3 | AG1: 提前償還殖利率3 | AH1: 提前償還日4 | AI1: 提前償還價格4 | AJ1: 提前償還殖利率4 | AK1: 最近提前償還日 | AL1: 最近提前償還價格 | AM1: 最近提前償還殖利率 | AN1: 債券擔保情形 | AO1: 重設平均天數3 | AP1: 重設轉換價格公式 | AQ1: 停止受理轉換登記日期起 | AR1: 停止受理轉換登記日期訖 | AS1: 強制贖回日
A2: 13164 | B2: 上曜四 | C2: SUN YAD CONSTRUCTION CO.,LTD 4th Secured Convertible Bond | D2: 0 | E2: 14.7 | F2: 45708 | G2: 1316 | H2: 上曜 | I2: 44316 | J2: 46051 | K2: 44225 | L2: 44225 | M2: 46051 | N2: 100 | O2: 0 | P2: 400 | Q2: 400 | R2: 101 | S2: 134 | T2: 5 | U2: 14.9 | V2: 960T富邦綜合證券 | W2: 元大證券股份有限公司 | X2: 發行滿三年 | Y2: 45320 | Z2: 100.75 | AA2: 0.25 | AB2: 46051 | AC2: 100 | AD2: 0 | AK2: 46051 | AL2: 100 | AM2: 0 | AN2: 有，台北富邦商業銀行股份有限公司 | AQ2: 45939 | AR2: 45968
A3: 13166 | B3: 上曜六 | C3: SUN YAD CONSTRUCTION CO.,LTD 6th Secured Convertible Bond | D3: 0 | E3: 17.4 | F3: 45708 | G3: 1316 | H3: 上曜 | I3: 45744 | J3: 46748 | K3: 45653 | L3: 45653 | M3: 46748 | N3: 100 | O3: 0 | P3: 400 | Q3: 400 | R3: 100 | S3: 400 | T3: 3 | U3: 17.8 | V3: 592T元富證券 | W3: 元大證券股份有限公司 | X3: 發行滿二年 | Y3: 46383 | Z3: 100.5 | AA3: 0.25 | AB3: 46748 | AC3: 100 | AD3: 0 | AK3: 46383 | AL3: 100.5 | AM3: 0.25 | AN3: 有，板信商業銀行股份有限公司 | AQ3: 45939 | AR3: 45968
A4: 13382 | B4: 廣華二KY | C4: Hiroca Holdings Ltd. 2nd Unsecured Convertible Bond | D4: 0 | E4: 37.6 | F4: 45853 | G4: 1338 | H4: 廣華-KY | I4: 45353 | J4: 47088 | K4: 45261 | L4: 45261 | M4: 47088 | N4: 100 | O4: 0 | P4: 600 | Q4: 600 | R4: 100 | S4: 600 | T4: 5 | U4: 39.4 | V4: 779T國票綜合證券 | W4: 兆豐證券股份有限公司股務代理部 | X4: 發行滿三年 | Y4: 46357 | Z4: 106.1208 | AA4: 2 | AB4: 47088 | AC4: 100 | AD4: 0 | AK4: 46357 | AL4: 106.1208 | AM4: 2 | AN4: 無 | AQ4: 45828 | AR4: 45853
A5: 14363 | B5: 華友聯三 | C5: HUA YU LIEN Development Co., Ltd. 3rd Domestic Unsecured Convertible Bonds | D5: 0 | E5: 128.7 | F5: 45865 | G5: 1436 | H5: 華友聯 | I5: 45624 | J5: 46626 | K5: 45531 | L5: 45531 | M5: 46626 | N5: 104.5678 | O5: 1.5 | P5: 600 | Q5: 600 | R5: 100 | S5: 600 | T5: 3 | U5: 182.5 | V5: 888T國泰綜合證券 | W5: 群益金鼎證券股份有限公司股務代理部 | X5: 發行滿二年 | Y5: 46261 | Z5: 103.0225 | AA5: 1.5 | AB5: 46626 | AC5: 104.5678 | AD5: 1.5 | AK5: 46261 | AL5: 103.0225 | AM5: 1.5 | AN5: 無 | AQ5: 45840 | AR5: 45865
A6: 14364 | B6: 華友聯四 | C6: HUA YU LIEN Development Co., Ltd. 4th Unsecured Convertible Bonds | D6: 0 | E6: 99 | F6: 45865 | G6: 1436 | H6: 華友聯 | I6: 45827 | J6: 46830 | K6: 45734 | L6: 45734 | M6: 46830 | N6: 104.5678 | O6: 1.5 | P6: 2000 | Q6: 2000 | R6: 101 | S6: 2000 | T6: 3 | U6: 140.3 | V6: 888T國泰綜合證券 | W6: 群益金鼎證券股份有限公司股務代理部 | X6: 發行滿二年 | Y6: 46464 | Z6: 103.0225 | AA6: 1.5 | AB6: 46830 | AC6: 104.5678 | AD6: 1.5 | AK6: 46464 | AL6: 103.0225 | AM6: 1.5 | AN6: 無 | AQ6: 45840 | AR6: 45865
A7: 14381 | B7: 三地開發一 | C7: San Di Properties Co., Ltd. 1st domestic Secured convertible bonds | D7: 0 | E7: 55.88 | F7: 45652 | G7: 1438 | H7: 三地開發 | I7: 45736 | J7: 47471 | K7: 45645 | L7: 45645 | M7: 47471 | N7: 102.5251 | O7: 0.5 | P7: 970 | Q7: 970 | R7: 117.63 | S7: 970 | T7: 5 | U7: 57.5 | V7: 585T統一綜合證券 | W7: 中國信託股份有限公司 | X7: 發行滿三年 | Y7: 46740 | Z7: 101.5075 | AA7: 0.5 | AB7: 47471 | AC7: 102.5251 | AD7: 0.5 | AK7: 46740 | AL7: 101.5075 | AM7: 0.5 | AN7: 有，台中商業銀行股份有限公司 | AQ7: 45772 | AR7: 45831
A8: 14664 | B8: 聚隆四 | C8: Acelon Chemicals & Fiber Corp. 4th Domestic Secured Convertible Bonds | D8: 0 | E8: 18.8 | F8: 45828 | G8: 1466 | H8: 聚隆 | I8: 45921 | J8: 46924 | K8: 45828 | L8: 45828 | M8: 46924 | N8: 100 | O8: 0 | P8: 400 | Q8: 400 | R8: 103.11 | S8: 400 | T8: 3 | U8: 18.8 | V8: 779T國票綜合證券 | W8: 凱基證券股份有限公司 | X8: 無 | Y8: 46924 | Z8: 100 | AA8: 0 | AK8: 46924 | AL8: 100 | AM8: 0 | AN8: 有，台中商業銀行股份有限公司
A9: 14722 | B9: 三洋實業二 | C9: Triocean Industrial Corporation Co., LTD. 2nd Domestic Secured Convertible Bond | D9: 0 | E9: 98.6 | F9: 45853 | G9: 1472 | H9: 三洋實業 | I9: 45899 | J9: 46902 | K9: 45806 | L9: 45806 | M9: 46902 | N9: 100 | O9: 0 | P9: 300 | Q9: 300 | R9: 110.71 | S9: 300 | T9: 3 | U9: 102 | V9: 815T台新綜合證券 | W9: 凱基證券股份有限公司股務代理部 | X9: 發行滿二年 | Y9: 46536 | Z9: 101.0025 | AA9: 0.5 | AB9: 46902 | AC9: 100 | AD9: 0 | AK9: 46536 | AL9: 101.0025 | AM9: 0.5 | AN9: 有，台中商業銀行股份有限公司
A10: 14723 | B10: 三洋實業三 | C10: Triocean Industrial Corporation Co., LTD. 3rd Domestic Unsecured Convertible Bond | D10: 0 | E10: 101.5 | F10: 45853 | G10: 1472 | H10: 三洋實業 | I10: 45918 | J10: 46921 | K10: 45825 | L10: 45825 | M10: 46921 | N10: 100 | O10: 0 | P10: 400 | Q10: 400 | R10: 100 | S10: 400 | T10: 3 | U10: 105 | V10: 815T台新綜合證券 | W10: 凱基證券股份有限公司股務代理部 | X10: 發行滿二年 | Y10: 46555 | Z10: 102.01 | AA10: 1 | AB10: 46921 | AC10: 100 | AD10: 0 | AK10: 46555 | AL10: 102.01 | AM10: 1 | AN10: 無
A11: 14743 | B11: 弘裕三 | C11: Honmyue Enterprise Co., Ltd. 3rd Domestic Unsecured Convertible Bond | D11: 0 | E11: 14 | F11: 45894 | G11: 1474 | H11: 弘裕 | I11: 45839 | J11: 46843 | K11: 45747 | L11: 45747 | M11: 46843 | N11: 101.5075 | O11: 0.5 | P11: 300 | Q11: 300 | R11: 101.5 | S11: 300 | T11: 3 | U11: 14.5 | V11: 700T兆豐證券 | W11: 富邦綜合證券股務代理部 | X11: 無 | Y11: 46843 | Z11: 101.5075 | AA11: 0.5 | AK11: 46843 | AL11: 101.5075 | AM11: 0.5 | AN11: 無 | AQ11: 45869 | AR11: 45894
A12: 15142 | B12: 亞力二 | C12: ALLIS ELECTRIC CO.,Ltd 2nd Domestic Unsecured Convertible Bond | D12: 0 | E12: 109.2 | F12: 45915 | G12: 1514 | H12: 亞力 | I12: 45761 | J12: 47496 | K12: 45670 | L12: 45670 | M12: 47496 | N12: 100 | O12: 0 | P12: 1200 | Q12: 1200 | R12: 100.5 | S12: 1200 | T12: 5 | U12: 113.2 | V12: 980T元大證券 | W12: 元大證券股份有限公司股務代理部 | X12: 發行滿三年 | Y12: 46765 | Z12: 100.7519 | AA12: 0.25 | AB12: 47496 | AC12: 100 | AD12: 0 | AK12: 46765 | AL12: 100.7519 | AM12: 0.25 | AN12: 無 | AQ12: 45890 | AR12: 45915
A13: 12561 | B13: 鮮活果汁一KY | C13: Sunjuice Holdings Co., Limited 1st Unsecured Convertible Bonds | D13: 0 | E13: 189.1 | F13: 45964 | G13: 1256 | H13: 鮮活果汁-KY | I13: 46031 | J13: 47034 | K13: 45938 | L13: 45938 | M13: 47034 | N13: 100 | O13: 0 | P13: 200 | Q13: 200 | R13: 101.5 | S13: 200 | T13: 3 | U13: 190 | V13: 700T兆豐證券 | W13: 兆豐證券股份有限公司股務代理本部 | X13: 發行滿二年 | Y13: 46668 | Z13: 100.5006 | AA13: 0.25 | AB13: 47034 | AC13: 100 | AD13: 0 | AK13: 46668 | AL13: 100.5006 | AM13: 0.25 | AN13: 無
A14: 15261 | B14: 日馳一 | C14: SUN RACE STURMEY-ARCHER INC. 1st Domestic Unsecured Convertible Bond | D14: 0 | E14: 37.29 | F14: 45265 | G14: 1526 | H14: 日馳 | I14: 45280 | J14: 46284 | K14: 45188 | L14: 45188 | M14: 46284 | N14: 100 | O14: 0 | P14: 500 | Q14: 500 | R14: 103.81 | S14: 500 | T14: 3 | U14: 38 | V14: 960T富邦綜合證券 | W14: 富邦綜合證券股份有限公司股務代理部 | X14: 無 | Y14: 46284 | Z14: 100 | AA14: 0 | AK14: 46284 | AL14: 100 | AM14: 0 | AN14: 無 | AQ14: 45768 | AR14: 45827
A15: 15364 | B15: 和大四 | C15: HOTA Industrial Mfg. Co., Ltd. 4th Domestic Unsecured Convertible Bond | D15: 0 | E15: 71.47 | F15: 45763 | G15: 1536 | H15: 和大 | I15: 45609 | J15: 46611 | K15: 45516 | L15: 45516 | M15: 46611 | N15: 100 | O15: 0 | P15: 1500 | Q15: 1500 | R15: 100 | S15: 1500 | T15: 3 | U15: 72.26 | V15: 611T台中銀證券 | W15: 元富證券股份有限公司股務代理部 | X15: 發行滿二年 | Y15: 46246 | Z15: 100 | AA15: 0 | AB15: 46611 | AC15: 100 | AD15: 0 | AK15: 46246 | AL15: 100 | AM15: 0 | AN15: 無 | AQ15: 45736 | AR15: 45818
A16: 15601 | B16: 中砂一 | C16: Kinik Companay 1st Unsecured Convertible Bond | D16: 0 | E16: 284.6 | F16: 45865 | G16: 1560 | H16: 中砂 | I16: 45560 | J16: 47293 | K16: 45467 | L16: 45467 | M16: 47293 | N16: 100 | O16: 0 | P16: 1000 | Q16: 1000 | R16: 118.38 | S16: 999.5 | T16: 5 | U16: 292.1 | V16: 920T凱基證券 | W16: 凱基證券股份有限公司股務代理部 | X16: 發行滿三年 | Y16: 46562 | Z16: 100 | AA16: 0 | AB16: 47293 | AC16: 100 | AD16: 0 | AK16: 46562 | AL16: 100 | AM16: 0 | AN16: 無 | AQ16: 45840 | AR16: 45865
A17: 15864 | B17: 和勤四 | C17: CHINA FINEBLANKING TECHNOLOGY CO., LTD. 4th Domestic Secured Convertible Bond | D17: 0 | E17: 30.74 | F17: 45948 | G17: 1586 | H17: 和勤 | I17: 45261 | J17: 46264 | K17: 45168 | L17: 45168 | M17: 46264 | N17: 100 | O17: 0 | P17: 200 | Q17: 200 | R17: 107.2 | S17: 200 | T17: 3 | U17: 33.39 | V17: 102T合作金庫證券 | W17: 群益金鼎證券股份有限公司 | X17: 無 | Y17: 46264 | Z17: 100 | AA17: 0 | AK17: 46264 | AL17: 100 | AM17: 0 | AN17: 有，合作金庫商業銀行股份有限公司 | AQ17: 45918 | AR17: 45948
A18: 15865 | B18: 和勤五 | C18: CHINA FINEBLANKING TECHNOLOGY CO., LTD. 5th Domestic Unsecured Convertible Bond | D18: 0 | E18: 30.14 | F18: 45948 | G18: 1586 | H18: 和勤 | I18: 45261 | J18: 46265 | K18: 45169 | L18: 45169 | M18: 46265 | N18: 101.5075 | O18: 0.5 | P18: 300 | Q18: 300 | R18: 100 | S18: 290.2 | T18: 3 | U18: 32.74 | V18: 102T合作金庫證券 | W18: 群益金鼎證券股份有限公司 | X18: 無 | Y18: 46265 | Z18: 101.5075 | AA18: 0.5 | AK18: 46265 | AL18: 101.5075 | AM18: 0.5 | AN18: 無 | AQ18: 45918 | AR18: 45948
A19: 15894 | B19: 永冠四KY | C19: Yeong Guan Energy Technology Group Co., Ltd 4th Unsecured Convertible Bond | D19: 0 | E19: 60.7 | F19: 45974 | G19: 1589 | H19: 永冠-KY | I19: 45067 | J19: 46803 | K19: 44977 | L19: 44977 | M19: 46803 | N19: 100 | O19: 0 | P19: 1500 | Q19: 1500 | R19: 104.23 | S19: 1031.6 | T19: 5 | U19: 62.3 | V19: 9A0T永豐金證券 | W19: 群益金鼎證券股份有限公司股務代理部 | X19: 發行滿三年 | Y19: 46073 | Z19: 101.51 | AA19: 0.5 | AB19: 46803 | AC19: 100 | AD19: 0 | AK19: 46073 | AL19: 101.51 | AM19: 0.5 | AN19: 無 | AQ19: 45931 | AR19: 45960
A20: 15952 | B20: 川寶二 | C20: CHIME BALL TECHNOLOGY CO.,LTD 2nd Domestic Unsecured Convertible Bond | D20: 0 | E20: 37.7 | F20: 45856 | G20: 1595 | H20: 川寶 | I20: 45629 | J20: 47363 | K20: 45537 | L20: 45537 | M20: 47363 | N20: 100 | O20: 0 | P20: 300 | Q20: 300 | R20: 109.82 | S20: 91 | T20: 5 | U20: 38.3 | V20: 648T福邦證券 | W20: 福邦證券股份有限公司 | X20: 發行滿三年 | Y20: 46632 | Z20: 101.51 | AA20: 0.5 | AB20: 47363 | AC20: 100 | AD20: 0 | AK20: 46632 | AL20: 101.51 | AM20: 0.5 | AN20: 無 | AQ20: 45831 | AR20: 45856
A21: 15984 | B21: 岱宇四 | C21: Dyaco International Inc 4th Domestic unsecured Convertible Bond | D21: 0 | E21: 32.7 | F21: 45816 | G21: 1598 | H21: 岱宇 | I21: 45812 | J21: 46815 | K21: 45719 | L21: 45719 | M21: 46815 | N21: 100 | O21: 0 | P21: 200 | Q21: 200 | R21: 100 | S21: 200 | T21: 3 | U21: 33.6 | V21: 585T統一綜合證券 | W21: 富邦金證券股務代理部 | X21: 發行滿二年 | Y21: 46449 | Z21: 102.01 | AA21: 1 | AB21: 46815 | AC21: 100 | AD21: 0 | AK21: 46449 | AL21: 102.01 | AM21: 1 | AN21: 無 | AQ21: 45790 | AR21: 45816
A22: 16095 | B22: 大亞五 | C22: Ta Ya Electric Wire & Cable Co., Ltd. 5th Domestic Unsecured Convertible Bond | D22: 0 | E22: 51.3 | F22: 45858 | G22: 1609 | H22: 大亞 | I22: 45657 | J22: 47391 | K22: 45565 | L22: 45565 | M22: 47391 | N22: 100 | O22: 0 | P22: 2000 | Q22: 2000 | R22: 107.46 | S22: 2000 | T22: 5 | U22: 53.1 | V22: 920T凱基證券 | W22: 凱基證券股份有限公司 | X22: 發行滿三年 | Y22: 46660 | Z22: 100.75 | AA22: 0.25 | AB22: 47391 | AC22: 100 | AD22: 0 | AK22: 46660 | AL22: 100.75 | AM22: 0.25 | AN22: 無 | AQ22: 45833 | AR22: 45858
A23: 17813 | B23: 合世三 | C23: HEALTH&LIFE CO., LTD 3rd Domestic Secured Convertible Bond | D23: 0 | E23: 18 | F23: 45559 | G23: 1781 | H23: 合世 | I23: 45651 | J23: 46654 | K23: 45559 | L23: 45559 | M23: 46654 | N23: 100 | O23: 0 | P23: 200 | Q23: 200 | R23: 112.91 | S23: 200 | T23: 3 | U23: 18 | V23: 930T華南永昌綜合證券 | W23: 富邦證券 | X23: 無 | Y23: 46654 | Z23: 100 | AA23: 0 | AK23: 46654 | AL23: 100 | AM23: 0 | AN23: 有，華南商業銀行股份有限公司 | AQ23: 45765 | AR23: 45824
A24: 17863 | B24: 科妍三 | C24: SciVision Biotech Inc. 3rd Unsecured Convertible Bond | D24: 0 | E24: 116.5 | F24: 45870 | G24: 1786 | H24: 科妍 | I24: 45963 | J24: 46966 | K24: 45870 | L24: 45870 | M24: 46966 | N24: 100 | O24: 0 | P24: 400 | Q24: 400 | R24: 100 | S24: 400 | T24: 3 | U24: 116.5 | V24: 585T統一綜合證券 | W24: 宏遠證券股務代理部 | X24: 發行滿二年 | Y24: 46600 | Z24: 102.01 | AA24: 1 | AB24: 46966 | AC24: 100 | AD24: 0 | AK24: 46600 | AL24: 102.01 | AM24: 1 | AN24: 無
A25: 18156 | B25: 富喬六 | C25: Fulltech Fiber Glass Corp. 6th Domestic Unsecured Convertible Bond | D25: 0 | E25: 13.82 | F25: 45611 | G25: 1815 | H25: 富喬 | I25: 44364 | J25: 46097 | K25: 44271 | L25: 44271 | M25: 46097 | N25: 100 | O25: 0 | P25: 400 | Q25: 400 | R25: 100 | S25: 8.5 | T25: 5 | U25: 15.6 | V25: 104T臺銀綜合證券 | W25: 富喬工業股份有限公司 股務室 | X25: 發行滿三、四年 | Y25: 45367 | Z25: 103.0301 | AA25: 1 | AB25: 45732 | AC25: 105.0945 | AD25: 1.25 | AE25: 46097 | AF25: 100 | AG25: 0 | AK25: 46097 | AL25: 100 | AM25: 0 | AN25: 無 | AQ25: 45971 | AR25: 45994
A26: 19094 | B26: 榮成四 | C26: Longchen Paper & Packaging Co., Ltd. 2nd Domestic Unsecured Convertible Bond | D26: 0 | E26: 23.9 | F26: 45117 | G26: 1909 | H26: 榮成 | I26: 44641 | J26: 46376 | K26: 44550 | L26: 44550 | M26: 46376 | N26: 100 | O26: 0 | P26: 700 | Q26: 700 | R26: 108.58 | S26: 16 | T26: 5 | U26: 26.2 | V26: 815T台新綜合證券 | W26: 元大證券股份有限公司 | X26: 發行滿三年 | Y26: 45646 | Z26: 100.7519 | AA26: 0.25 | AB26: 46376 | AC26: 100 | AD26: 0 | AK26: 46376 | AL26: 100 | AM26: 0 | AN26: 無 | AQ26: 45746 | AR26: 45805
A27: 20343 | B27: 允強三 | C27: YC INOX&#039;s 3rd Domestic Unsecured Convertible Corporate Bonds | D27: 0 | E27: 20.1 | F27: 45859 | G27: 2034 | H27: 允強 | I27: 44271 | J27: 46006 | K27: 44180 | L27: 44180 | M27: 46006 | N27: 100 | O27: 0 | P27: 1000 | Q27: 1000 | R27: 100 | S27: 152.4 | T27: 5 | U27: 26.5 | V27: 9A0T永豐金證券 | W27: 永豐金證券股份有限公司股務代理部 | X27: 發行滿三年 | Y27: 45275 | Z27: 100 | AA27: 0 | AB27: 46006 | AC27: 100 | AD27: 0 | AK27: 46006 | AL27: 100 | AM27: 0 | AN27: 無 | AQ27: 45834 | AR27: 45859
A28: 20344 | B28: 允強四 | C28: YC INOX CO .,LTD 4th Domestic Unsecured Convertible Bonds | D28: 0 | E28: 24 | F28: 45859 | G28: 2034 | H28: 允強 | I28: 45660 | J28: 47393 | K28: 45567 | L28: 45567 | M28: 47393 | N28: 100 | O28: 0 | P28: 2000 | Q28: 2000 | R28: 100.5 | S28: 2000 | T28: 5 | U28: 25.6 | V28: 9A0T永豐金證券 | W28: 永豐金證券股份有限公司股務代理部 | X28: 發行滿三年 | Y28: 46662 | Z28: 100 | AA28: 0 | AB28: 47393 | AC28: 100 | AD28: 0 | AK28: 46662 | AL28: 100 | AM28: 0 | AN28: 無 | AQ28: 45834 | AR28: 45859
A29: 20632 | B29: 世鎧二 | C29: Sheh Kai Precision Co., Ltd. 2nd Unsecured Convertible Bond | D29: 0 | E29: 47.9 | F29: 45756 | G29: 2063 | H29: 世鎧 | I29: 45333 | J29: 46336 | K29: 45240 | L29: 45240 | M29: 46336 | N29: 100 | O29: 0 | P29: 600 | Q29: 600 | R29: 107.32 | S29: 14.5 | T29: 3 | U29: 55 | V29: 960T富邦綜合證券 | W29: 永豐金證券股份有限公司股務代理部 | X29: 發行滿二年 | Y29: 45971 | Z29: 100 | AA29: 0 | AB29: 46336 | AC29: 100 | AD29: 0 | AK29: 46336 | AL29: 100 | AM29: 0 | AN29: 無 | AQ29: 45729 | AR29: 45811 | AS29: 46035
A30: 20662 | B30: 世德二 | C30: SUMEEKO CO., LTD. 2nd Domestic Unsecured Convertible Bond | D30: 0 | E30: 88.1 | F30: 45970 | G30: 2066 | H30: 世德 | I30: 45231 | J30: 46234 | K30: 45138 | L30: 45138 | M30: 46234 | N30: 100 | O30: 0 | P30: 400 | Q30: 400 | R30: 109.91 | S30: 237.8 | T30: 3 | U30: 101 | V30: 585T統一綜合證券 | W30: 台新綜合證券股務代理部 | X30: 無 | Y30: 46234 | Z30: 100 | AA30: 0 | AK30: 46234 | AL30: 100 | AM30: 0 | AN30: 無 | AQ30: 45944 | AR30: 45970
A31: 21043 | B31: 國際中橡三 | C31: International CSRC Investment Holdings Co. 3rd Domestic Unsecured Convertible Bond | D31: 0 | E31: 21.2 | F31: 45212 | G31: 2104 | H31: 國際中橡 | I31: 45305 | J31: 47039 | K31: 45212 | L31: 45212 | M31: 47039 | N31: 100 | O31: 0 | P31: 3500 | Q31: 3500 | R31: 100.2 | S31: 3500 | T31: 5 | U31: 21.2 | V31: 980T元大證券 | W31: 中國信託商業銀行股份有限公司代理部 | X31: 發行滿三年 | Y31: 46308 | Z31: 100.9 | AA31: 0.3 | AB31: 47039 | AC31: 100 | AD31: 0 | AK31: 46308 | AL31: 100.9 | AM31: 0.3 | AN31: 無 | AQ31: 45746 | AR31: 45805
A32: 22013 | B32: 裕隆三 | C32: YULON MOTOR CO.,LTD 3rd Domestic Unsecured Convertible Bond | D32: 0 | E32: 75 | F32: 45898 | G32: 2201 | H32: 裕隆 | I32: 45164 | J32: 46898 | K32: 45071 | L32: 45071 | M32: 46898 | N32: 102.5251 | O32: 0.5 | P32: 7000 | Q32: 7000 | R32: 102 | S32: 6999.9 | T32: 5 | U32: 82 | V32: 920T凱基證券 | W32: 裕隆股務組 | X32: 發行滿三年 | Y32: 46167 | Z32: 100.7519 | AA32: 0.25 | AB32: 46898 | AC32: 102.5251 | AD32: 0.5 | AK32: 46167 | AL32: 100.7519 | AM32: 0.25 | AN32: 無 | AQ32: 45873 | AR32: 45898
A33: 22283 | B33: 劍麟三 | C33: IRON FORCE INDUSTRIAL CO., LTD. 3rd Unsecured Convertible Bond | D33: 0 | E33: 85.36 | F33: 45852 | G33: 2228 | H33: 劍麟 | I33: 45626 | J33: 46628 | K33: 45533 | L33: 45533 | M33: 46628 | N33: 100 | O33: 0 | P33: 300 | Q33: 300 | R33: 114.2 | S33: 278.7 | T33: 3 | U33: 95.51 | V33: 920T凱基證券 | W33: 元大證券股份有限公司股務代理部 | X33: 無 | Y33: 46628 | Z33: 100 | AA33: 0 | AK33: 46628 | AL33: 100 | AM33: 0 | AN33: 無 | AQ33: 45827 | AR33: 45852
A34: 22362 | B34: 百達二KY | C34: Patec Precision Industry Co., Ltd. 2nd Unsecured Convertible Bond | D34: 0 | E34: 63.1 | F34: 45985 | G34: 2236 | H34: 百達-KY | I34: 45249 | J34: 46252 | K34: 45156 | L34: 45156 | M34: 46252 | N34: 100 | O34: 0 | P34: 200 | Q34: 200 | R34: 103.79 | S34: 0.5 | T34: 3 | U34: 66 | V34: 815T台新綜合證券 | W34: 中國信託商業銀行代理部 | X34: 無 | Y34: 46252 | Z34: 100 | AA34: 0 | AK34: 46252 | AL34: 100 | AM34: 0 | AN34: 無 | AQ34: 45982 | AR34: 46007
A35: 22471 | B35: 汎德永業一 | C35: Pan German Universal Motors Ltd. 1st. Domestic Unsecured Convertible Bond | D35: 0 | E35: 289.4 | F35: 45872 | G35: 2247 | H35: 汎德永業 | I35: 45927 | J35: 46930 | K35: 45834 | L35: 45834 | M35: 46930 | N35: 100 | O35: 0 | P35: 1000 | Q35: 1000 | R35: 101 | S35: 1000 | T35: 3 | U35: 307.6 | V35: 群益金鼎券證股份有限公司 | W35: 群益金鼎券證股務代理部 | X35: 無 | Y35: 46930 | Z35: 100 | AA35: 0 | AK35: 46930 | AL35: 100 | AM35: 0 | AN35: 無 | AQ35: 46009 | AR35: 46036
A36: 22472 | B36: 汎德永業二 | C36: Pan German Universal Motors Ltd. 2nd. Domestic Unsecured Convertible Bond | D36: 0 | E36: 280.2 | F36: 45872 | G36: 2247 | H36: 汎德永業 | I36: 45931 | J36: 46934 | K36: 45838 | L36: 45838 | M36: 46934 | N36: 100 | O36: 0 | P36: 1000 | Q36: 1000 | R36: 102.37 | S36: 1000 | T36: 3 | U36: 297.8 | V36: 群益金鼎證券股份有限公司 | W36: 群益金鼎券證股務代理部 | X36: 無 | Y36: 46934 | Z36: 100 | AA36: 0 | AK36: 46934 | AL36: 100 | AM36: 0 | AN36: 無 | AQ36: 46009 | AR36: 46036
A37: 11011 | B37: 台泥一永 | C37: TCC Group Holdings Co., Ltd.1st Domestic Unsecured Convertible Bond | D37: 0 | E37: 35.2 | F37: 45846 | G37: 1101 | H37: 台泥 | I37: 45727 | J37: 47462 | K37: 45636 | L37: 45636 | M37: 47462 | N37: 100 | O37: 0 | P37: 8000 | Q37: 8000 | R37: 100 | S37: 8000 | T37: 5 | U37: 36.5 | V37: 980T元大證券 | W37: 中國信託商業銀行股份有限公司代理部 | X37: 發行滿三年 | Y37: 46731 | Z37: 100 | AA37: 0 | AB37: 47462 | AC37: 100 | AD37: 0 | AK37: 46731 | AL37: 100 | AM37: 0 | AN37: 無 | AQ37: 45821 | AR37: 45846
A38: 23372 | B38: 旺宏二 | C38: Macronix International Co., Ltd 2nd Domestic Unsecured Convertible Bond | D38: 0 | E38: 23 | F38: 45740 | G38: 2337 | H38: 旺宏 | I38: 45833 | J38: 46836 | K38: 45740 | L38: 45740 | M38: 46836 | N38: 100 | O38: 0 | P38: 3000 | Q38: 3000 | R38: 100.5 | S38: 1509.9 | T38: 3 | U38: 23 | V38: 920T凱基證券 | W38: 旺宏電子股份有限公司股務室 | X38: 無 | Y38: 46836 | Z38: 100 | AA38: 0 | AK38: 46836 | AL38: 100 | AM38: 0 | AN38: 無
A39: 23383 | B39: 光罩三 | C39: TAIWAN MASK CORP. 3rd Domestic Convertible Bond | D39: 0 | E39: 74.5 | F39: 45895 | G39: 2338 | H39: 光罩 | I39: 44504 | J39: 46237 | K39: 44411 | L39: 44411 | M39: 46237 | N39: 100 | O39: 0 | P39: 2000 | Q39: 2000 | R39: 115.23 | S39: 97.9 | T39: 5 | U39: 88.8 | V39: 凱基證券股份有限公司 | W39: 福邦證券股份有限公司股務代理部 | X39: 發行滿三、四年 | Y39: 45507 | Z39: 100 | AA39: 0 | AB39: 45872 | AC39: 100 | AD39: 0 | AE39: 46237 | AF39: 100 | AG39: 0 | AK39: 46237 | AL39: 100 | AM39: 0 | AN39: 無 | AQ39: 45746 | AR39: 45805
A40: 23511 | B40: 順德一 | C40: SDI Corporation 1st Domestic Unsecured Convertible Bond | D40: 0 | E40: 72.4 | F40: 45877 | G40: 2351 | H40: 順德 | I40: 45918 | J40: 46921 | K40: 45825 | L40: 45825 | M40: 46921 | N40: 100 | O40: 0 | P40: 1200 | Q40: 1200 | R40: 102.18 | S40: 1200 | T40: 3 | U40: 75 | V40: 815T台新綜合證券 | W40: 群益金鼎證券股份有限公司 | X40: 無 | Y40: 46921 | Z40: 100 | AA40: 0 | AK40: 46921 | AL40: 100 | AM40: 0 | AN40: 無
A41: 23682 | B41: 金像電二 | C41: GOLD CIRCUIT ELECTRONICS LTD. 2nd Domestic Unsecured Convertible Bond | D41: 0 | E41: 214 | F41: 45838 | G41: 2368 | H41: 金像電 | I41: 45357 | J41: 47092 | K41: 45265 | L41: 45265 | M41: 47092 | N41: 100 | O41: 0 | P41: 4000 | Q41: 4000 | R41: 107.16 | S41: 322.1 | T41: 5 | U41: 223.1 | V41: 960T富邦綜合證券 | W41: 中國信託商業銀行代理部 | X41: 發行滿三年 | Y41: 46361 | Z41: 100 | AA41: 0 | AB41: 47092 | AC41: 100 | AD41: 0 | AK41: 46361 | AL41: 100 | AM41: 0 | AN41: 無 | AQ41: 45813 | AR41: 45838 | AS41: 46021
A42: 23683 | B42: 金像電三 | C42: CIRCUIT ELECTRONICS LTD. 3rd Domestic Unsecured Convertible Bond | D42: 0 | E42: 450 | F42: 45985 | G42: 2368 | H42: 金像電 | I42: 46078 | J42: 47811 | K42: 45985 | L42: 45985 | M42: 47811 | N42: 100 | O42: 0 | P42: 9000 | Q42: 9000 | R42: 112.88 | S42: 9000 | T42: 5 | U42: 450 | V42: 960T富邦綜合證券 | W42: 中國信託商業銀行代理部 | X42: 發行滿三年 | Y42: 47081 | Z42: 100 | AA42: 0 | AB42: 47811 | AC42: 100 | AD42: 0 | AK42: 47081 | AL42: 100 | AM42: 0 | AN42: 無
A43: 24023 | B43: 毅嘉三 | C43: ICHIA TECHNOLOGIES INC 3rd Domestic Unsecured Convertible Bond | D43: 0 | E43: 55 | F43: 45980 | G43: 2402 | H43: 毅嘉 | I43: 46073 | J43: 47076 | K43: 45980 | L43: 45980 | M43: 47076 | N43: 100 | O43: 0 | P43: 1000 | Q43: 1000 | R43: 102 | S43: 1000 | T43: 3 | U43: 55 | V43: 700T兆豐證券 | W43: 台新綜合證券股份有限公司股務代理部 | X43: 發行滿二年 | Y43: 46710 | Z43: 100 | AA43: 0 | AB43: 47076 | AC43: 100 | AD43: 0 | AK43: 46710 | AL43: 100 | AM43: 0 | AN43: 無
A44: 24271 | B44: 三商電一 | C44: Mercuries Data Systems Ltd. 1st Domestic Unsecured Convertible Bond | D44: 0 | E44: 26.3 | F44: 45880 | G44: 2427 | H44: 三商電 | I44: 45365 | J44: 47100 | K44: 45273 | L44: 45273 | M44: 47100 | N44: 100 | O44: 0 | P44: 500 | Q44: 500 | R44: 102 | S44: 468.4 | T44: 5 | U44: 28 | V44: 815T台新綜合證券 | W44: 宏遠證券股份有限公司股務代理部 | X44: 發行滿三、四年 | Y44: 46369 | Z44: 101.51 | AA44: 0.5 | AB44: 46734 | AC44: 102.02 | AD44: 0.5 | AE44: 47100 | AF44: 100 | AG44: 0 | AK44: 46369 | AL44: 101.51 | AM44: 0.5 | AN44: 無 | AQ44: 45855 | AR44: 45880
A45: 24361 | B45: 偉詮電一 | C45: Weltrend Semiconductor, Inc. 1st Domestic Unsecured Convertible Bond | D45: 0 | E45: 53.3 | F45: 45908 | G45: 2436 | H45: 偉詮電 | I45: 45272 | J45: 46276 | K45: 45180 | L45: 45180 | M45: 46276 | N45: 100 | O45: 0 | P45: 1100 | Q45: 1100 | R45: 112.15 | S45: 1099.9 | T45: 3 | U45: 61.2 | V45: 815T台新綜合證券 | W45: 中國信託商業銀行 代理部 | X45: 發行滿二年 | Y45: 45911 | Z45: 100.50062 | AA45: 0.25 | AB45: 46276 | AC45: 100 | AD45: 0 | AK45: 46276 | AL45: 100 | AM45: 0 | AN45: 無 | AQ45: 45817 | AR45: 45842
A46: 24394 | B46: 美律四 | C46: MERRY ELECTRONICS CO.,LTD. Domestic 4th Unsecured Convertible Bonds | D46: 0 | E46: 128.9 | F46: 45905 | G46: 2439 | H46: 美律 | I46: 45576 | J46: 46578 | K46: 45483 | L46: 45483 | M46: 46578 | N46: 100 | O46: 0 | P46: 2500 | Q46: 2500 | R46: 100.5 | S46: 2500 | T46: 3 | U46: 143.1 | V46: 960T富邦綜合證券 | W46: 凱基證券股務代理部 | X46: 無 | Y46: 46578 | Z46: 100 | AA46: 0 | AK46: 46578 | AL46: 100 | AM46: 0 | AN46: 無 | AQ46: 45880 | AR46: 45905
A47: 24395 | B47: 美律五 | C47: MERRY ELECTRONICS CO.,LTD. Domestic 5th Unsecured Convertible Bonds | D47: 0 | E47: 125.2 | F47: 45905 | G47: 2439 | H47: 美律 | I47: 45588 | J47: 46590 | K47: 45495 | L47: 45495 | M47: 46590 | N47: 100 | O47: 0 | P47: 500 | Q47: 500 | R47: 120.31 | S47: 500 | T47: 3 | U47: 139 | V47: 960T富邦綜合證券 | W47: 凱基證券股份有限公司股務代理部 | X47: 無 | Y47: 46590 | Z47: 100 | AA47: 0 | AK47: 46590 | AL47: 100 | AM47: 0 | AN47: 無 | AQ47: 45880 | AR47: 45905
A48: 24423 | B48: 新美齊三 | C48: JEAN CO., LTD. 3rd Domestic Unsecured Convertible Bond | D48: 0 | E48: 25.6 | F48: 45915 | G48: 2442 | H48: 新美齊 | I48: 45717 | J48: 46720 | K48: 45625 | L48: 45625 | M48: 46720 | N48: 100 | O48: 0 | P48: 1000 | Q48: 1000 | R48: 100.5 | S48: 900.1 | T48: 3 | U48: 26.1 | V48: 815T台新綜合證券 | W48: 中國信託商業銀行代理部 | X48: 發行滿二年 | Y48: 46355 | Z48: 100.5 | AA48: 0.25 | AB48: 46720 | AC48: 100 | AD48: 0 | AK48: 46355 | AL48: 100.5 | AM48: 0.25 | AN48: 無 | AQ48: 45890 | AR48: 45915
A49: 24424 | B49: 新美齊四 | C49: JEAN CO., LTD. 4th Domestic Unsecured Convertible Bond | D49: 0 | E49: 25.9 | F49: 45915 | G49: 2442 | H49: 新美齊 | I49: 45742 | J49: 46746 | K49: 45651 | L49: 45651 | M49: 46746 | N49: 100 | O49: 0 | P49: 1000 | Q49: 600 | R49: 100 | S49: 592.8 | T49: 3 | U49: 26.4 | V49: 815T台新綜合證券 | W49: 中國信託商業銀行代理部 | X49: 發行滿二年 | Y49: 46381 | Z49: 100.5 | AA49: 0.25 | AB49: 46746 | AC49: 100 | AD49: 0 | AK49: 46381 | AL49: 100.5 | AM49: 0.25 | AN49: 無 | AQ49: 45890 | AR49: 45915
A50: 24616 | B50: 光群雷六 | C50: K Laser Technology Inc. 6th Domestic Secured Convertible Bonds | D50: 0 | E50: 14.5 | F50: 45852 | G50: 2461 | H50: 光群雷 | I50: 44372 | J50: 46105 | K50: 44279 | L50: 44279 | M50: 46105 | N50: 100 | O50: 0 | P50: 600 | Q50: 600 | R50: 101 | S50: 256.1 | T50: 5 | U50: 19.8 | V50: 920T凱基證券 | W50: 福邦證券股份有限公司 | X50: 發行滿三年 | Y50: 45375 | Z50: 101.51 | AA50: 0.5 | AB50: 46105 | AC50: 100 | AD50: 0 | AK50: 46105 | AL50: 100 | AM50: 0 | AN50: 有，台中商業銀行股份有限公司 | AQ50: 45827 | AR50: 45852
A51: 24624 | B51: 良得電四 | C51: TAIWAN LINE TEK ELECTRONIC CO., LTD 4th DOMESTIC CONVERTIBLE BOND | D51: 0 | E51: 30.09 | F51: 45872 | G51: 2462 | H51: 良得電 | I51: 45242 | J51: 46245 | K51: 45149 | L51: 45149 | M51: 46245 | N51: 100 | O51: 0 | P51: 400 | Q51: 400 | R51: 100 | S51: 244.3 | T51: 3 | U51: 33.53 | V51: 585T統一綜合證券 | W51: 統一綜合證券股份有限公司 | X51: 發行滿二年 | Y51: 45880 | Z51: 100.501 | AA51: 0.25 | AB51: 46245 | AC51: 100 | AD51: 0 | AK51: 46245 | AL51: 100 | AM51: 0 | AN51: 無 | AQ51: 45847 | AR51: 45872
A52: 24642 | B52: 盟立二 | C52: MIRLE AUTOMATION CORPORATION 2nd Unsecured Convertible Bond | D52: 0 | E52: 78.5 | F52: 45847 | G52: 2464 | H52: 盟立 | I52: 45643 | J52: 46646 | K52: 45551 | L52: 45551 | M52: 46646 | N52: 100 | O52: 0 | P52: 1000 | Q52: 1000 | R52: 117.64 | S52: 980.3 | T52: 3 | U52: 80 | V52: 616T中國信託綜合證券 | W52: 中國信託商業銀行股份有限公司股務代理部 | X52: 發行滿二年 | Y52: 46281 | Z52: 100.5 | AA52: 0.25 | AB52: 46646 | AC52: 100 | AD52: 0 | AK52: 46281 | AL52: 100.5 | AM52: 0.25 | AN52: 無 | AQ52: 45824 | AR52: 45847
A53: 24762 | B53: 鉅祥二 | C53: G-SHANK ENTERPRISE CO., LTD. 2nd Domestic Unsecured Convertible Bond | D53: 0 | E53: 66.5 | F53: 45889 | G53: 2476 | H53: 鉅祥 | I53: 45409 | J53: 46413 | K53: 45317 | L53: 45317 | M53: 46413 | N53: 100 | O53: 0 | P53: 1000 | Q53: 1000 | R53: 113.8 | S53: 389.5 | T53: 3 | U53: 72.2 | V53: 616T中國信託綜合證券 | W53: 群益金鼎證券股份有限公司股務代理部 | X53: 無 | Y53: 46413 | Z53: 100 | AA53: 0 | AK53: 46413 | AL53: 100 | AM53: 0 | AN53: 無 | AQ53: 45866 | AR53: 45889
A54: 24866 | B54: 一詮六 | C54: I-CHIUN PRECISION INDUSTRY CO., LTD. 6th Domestic Unsecured Convertible Bond | D54: 0 | E54: 125.2 | F54: 45842 | G54: 2486 | H54: 一詮 | I54: 45567 | J54: 46569 | K54: 45474 | L54: 45474 | M54: 46569 | N54: 100 | O54: 0 | P54: 600 | Q54: 600 | R54: 101 | S54: 600 | T54: 3 | U54: 126 | V54: 648T福邦證券 | W54: 福邦證券股份有限公司股務代理部 | X54: 發行滿二年 | Y54: 46204 | Z54: 101.0025 | AA54: 0.5 | AB54: 46569 | AC54: 100 | AD54: 0 | AK54: 46204 | AL54: 101.0025 | AM54: 0.5 | AN54: 無 | AQ54: 45817 | AR54: 45842
A55: 25283 | B55: 皇普三 | C55: CROWELL DEVELOPMENT CORP. 3rd Secured Convertible Bond | D55: 0 | E55: 42.4 | F55: 45874 | G55: 2528 | H55: 皇普 | I55: 45748 | J55: 47483 | K55: 45657 | L55: 45657 | M55: 47483 | N55: 102.53 | O55: 0.5 | P55: 600 | Q55: 600 | R55: 102.51 | S55: 600 | T55: 5 | U55: 46.4 | V55: 815T台新綜合證券 | W55: 福邦證券股份有限公司代理部 | X55: 發行滿三年 | Y55: 46752 | Z55: 100.752 | AA55: 0.25 | AB55: 47483 | AC55: 102.53 | AD55: 0.5 | AK55: 46752 | AL55: 100.752 | AM55: 0.25 | AN55: 有，元大商業銀行股份有限公司 | AQ55: 45849 | AR55: 45874
A56: 25284 | B56: 皇普四 | C56: CROWELL DEVELOPMENT CORP. 4th Unsecured Convertible Bond | D56: 0 | E56: 41 | F56: 45874 | G56: 2528 | H56: 皇普 | I56: 45765 | J56: 47500 | K56: 45674 | L56: 45674 | M56: 47500 | N56: 102.53 | O56: 0.5 | P56: 500 | Q56: 500 | R56: 101.12 | S56: 500 | T56: 5 | U56: 45 | V56: 815T台新綜合證券 | W56: 福邦證券股份有限公司代理部 | X56: 發行滿三年 | Y56: 46769 | Z56: 101.508 | AA56: 0.5 | AB56: 47500 | AC56: 102.53 | AD56: 0.5 | AK56: 46769 | AL56: 101.508 | AM56: 0.5 | AN56: 無 | AQ56: 45849 | AR56: 45874
A57: 25303 | B57: 華建三 | C57: DELPHA CONSTRUCTION CO.,LTD. 3rd Unsecured Convertible Bond | D57: 0 | E57: 33.1 | F57: 45914 | G57: 2530 | H57: 華建 | I57: 45924 | J57: 46927 | K57: 45831 | L57: 45831 | M57: 46927 | N57: 100 | O57: 0 | P57: 500 | Q57: 500 | R57: 100 | S57: 500 | T57: 3 | U57: 34.7 | V57: 920T凱基證券 | W57: 中國信託商業銀行代理部 | X57: 發行滿二年 | Y57: 46561 | Z57: 100.5 | AA57: 0.25 | AB57: 46927 | AC57: 100 | AD57: 0 | AK57: 46561 | AL57: 100.5 | AM57: 0.25 | AN57: 無 | AQ57: 45981 | AR57: 46006
A58: 25304 | B58: 華建四 | C58: DELPHA CONSTRUCTION CO.,LTD. 4th Unsecured Convertible Bond | D58: 0 | E58: 31 | F58: 45914 | G58: 2530 | H58: 華建 | I58: 45931 | J58: 46934 | K58: 45838 | L58: 45838 | M58: 46934 | N58: 100 | O58: 0 | P58: 1000 | Q58: 800 | R58: 100.37 | S58: 760.7 | T58: 3 | U58: 32.5 | V58: 920T凱基證券 | W58: 中國信託商業銀行代理部 | X58: 發行滿二年 | Y58: 46568 | Z58: 100.5 | AA58: 0.25 | AB58: 46934 | AC58: 100 | AD58: 0 | AK58: 46568 | AL58: 100.5 | AM58: 0.25 | AN58: 無 | AQ58: 45981 | AR58: 46006
A59: 25483 | B59: 華固三 | C59: HUAKU DEVELOPMENT CO., LTD. 3rd Unsecured Convertible Bond | D59: 0 | E59: 125 | F59: 45871 | G59: 2548 | H59: 華固 | I59: 45660 | J59: 47393 | K59: 45567 | L59: 45567 | M59: 47393 | N59: 100 | O59: 0 | P59: 4000 | Q59: 4000 | R59: 101 | S59: 4000 | T59: 5 | U59: 138 | V59: 960T富邦綜合證券 | W59: 台新綜和證券公司股務代理部 | X59: 發行滿三年 | Y59: 46662 | Z59: 100 | AA59: 0 | AB59: 47393 | AC59: 100 | AD59: 0 | AK59: 46662 | AL59: 100 | AM59: 0 | AN59: 無 | AQ59: 45846 | AR59: 45871
A60: 25484 | B60: 華固四 | C60: HUAKU DEVELOPMENT CO.,LTD 4th Unsecured Convertible Bond | D60: 0 | E60: 123.5 | F60: 45871 | G60: 2548 | H60: 華固 | I60: 45676 | J60: 47409 | K60: 45583 | L60: 45583 | M60: 47409 | N60: 100 | O60: 0 | P60: 2000 | Q60: 2000 | R60: 104.83 | S60: 2000 | T60: 5 | U60: 136.3 | V60: 960T富邦綜合證券 | W60: 台新綜和證券公司股務代理 | X60: 發行滿三年 | Y60: 46678 | Z60: 100 | AA60: 0 | AB60: 47409 | AC60: 100 | AD60: 0 | AK60: 46678 | AL60: 100 | AM60: 0 | AN60: 無 | AQ60: 45846 | AR60: 45871
A61: 26107 | B61: 華航七 | C61: China Airlines company domestic 7th Unsecured Convertible Bond | D61: 0 | E61: 16.9 | F61: 45860 | G61: 2610 | H61: 華航 | I61: 44406 | J61: 46140 | K61: 44314 | L61: 44314 | M61: 46140 | N61: 100 | O61: 0 | P61: 6000 | Q61: 4500 | R61: 100 | S61: 1034.9 | T61: 5 | U61: 19 | V61: 815T台新綜合證券 | W61: 中國信託商業銀行代理部 | X61: 發行滿三年 | Y61: 45410 | Z61: 100 | AA61: 0 | AB61: 46140 | AC61: 100 | AD61: 0 | AK61: 46140 | AL61: 100 | AM61: 0 | AN61: 無 | AQ61: 45835 | AR61: 45860
A62: 26417 | B62: 正德七 | C62: Franbo Lines Corp. 7th Unsecured Convertible Bond | D62: 0 | E62: 22.15 | F62: 45843 | G62: 2641 | H62: 正德 | I62: 45592 | J62: 46594 | K62: 45499 | L62: 45499 | M62: 46594 | N62: 100 | O62: 0 | P62: 590 | Q62: 590 | R62: 104.88 | S62: 576.7 | T62: 3 | U62: 22.7 | V62: 910T群益金鼎證券 | W62: 福邦證券股份有限公司股務代理部 | X62: 無 | Y62: 46594 | Z62: 100 | AA62: 0 | AK62: 46594 | AL62: 100 | AM62: 0 | AN62: 無 | AQ62: 45818 | AR62: 45843
A63: 26418 | B63: 正德八 | C63: Franbo Lines Corp. 8th Unsecured Convertible Bond | D63: 0 | E63: 19.3 | F63: 45875 | G63: 2641 | H63: 正德 | I63: 45968 | J63: 47701 | K63: 45875 | L63: 45875 | M63: 47701 | N63: 100 | O63: 0 | P63: 780 | Q63: 780 | R63: 100.5 | S63: 725.1 | T63: 5 | U63: 19.3 | V63: 910T群益金鼎證券 | W63: 福邦證券股份有限公司股務代理部 | X63: 發行滿三年 | Y63: 46971 | Z63: 100.7519 | AA63: 0.25 | AB63: 47701 | AC63: 100 | AD63: 0 | AK63: 46971 | AL63: 100.7519 | AM63: 0.25 | AN63: 無
A64: 27271 | B64: 王品一 | C64: Wowprime Co., Ltd. 1st Domestic Unsecured Convertible Bond | D64: 0 | E64: 233.4 | F64: 45849 | G64: 2727 | H64: 王品 | I64: 45107 | J64: 46841 | K64: 45014 | L64: 45014 | M64: 46841 | N64: 100 | O64: 0 | P64: 700 | Q64: 700 | R64: 101 | S64: 699.9 | T64: 5 | U64: 295 | V64: 富邦綜合證券股份有限公司 | W64: 永豐金證券股份有限公司股務代理部 | X64: 發行滿三年 | Y64: 46110 | Z64: 100.7519 | AA64: 0.25 | AB64: 46841 | AC64: 100 | AD64: 0 | AK64: 46110 | AL64: 100.7519 | AM64: 0.25 | AN64: 無 | AQ64: 45824 | AR64: 45849
A65: 27323 | B65: 六角三 | C65: La Kaffa International Co., LTD. 3rd Domestic Unsecured Convertible Bond | D65: 0 | E65: 124.8 | F65: 45913 | G65: 2732 | H65: 六角 | I65: 45409 | J65: 46413 | K65: 45317 | L65: 45317 | M65: 46413 | N65: 100 | O65: 0 | P65: 600 | Q65: 600 | R65: 100 | S65: 600 | T65: 3 | U65: 137.7 | V65: 920T凱基證券 | W65: 永豐金證券(股)公司股務代理部 | X65: 發行滿二年 | Y65: 46048 | Z65: 101 | AA65: 0.5 | AB65: 46413 | AC65: 100 | AD65: 0 | AK65: 46048 | AL65: 101 | AM65: 0.5 | AN65: 無 | AQ65: 45888 | AR65: 45913
A66: 27324 | B66: 六角四 | C66: La Kaffa International Co., LTD. 4th Domestic Unsecured Convertible Bond | D66: 0 | E66: 74.3 | F66: 45999 | G66: 2732 | H66: 六角 | I66: 46090 | J66: 47095 | K66: 45999 | L66: 45999 | M66: 47095 | N66: 100 | O66: 0 | P66: 600 | Q66: 600 | R66: 100 | S66: 600 | T66: 3 | U66: 74.3 | V66: 930T華南永昌綜合證券 | W66: 永豐金證券(股)公司股務代理部 | X66: 發行滿二年 | Y66: 46729 | Z66: 101 | AA66: 0.5 | AB66: 47095 | AC66: 100 | AD66: 0 | AK66: 46729 | AL66: 101 | AM66: 0.5 | AN66: 無
A67: 27431 | B67: 山富一 | C67: RICHMOND INTERNATIONAL TRAVEL AND TOUR CO.,LTD. 1st Unsecured Convertible Bond | D67: 0 | E67: 101.9 | F67: 45926 | G67: 2743 | H67: 山富 | I67: 45990 | J67: 46993 | K67: 45897 | L67: 45897 | M67: 46993 | N67: 100 | O67: 0 | P67: 300 | Q67: 300 | R67: 102 | S67: 300 | T67: 3 | U67: 135 | V67: 888T國泰綜合證券 | W67: 福邦證券股務代理部 | X67: 發行滿二年 | Y67: 46627 | Z67: 101.0025 | AA67: 0.5 | AB67: 46993 | AC67: 100 | AD67: 0 | AK67: 46627 | AL67: 101.0025 | AM67: 0.5 | AN67: 無
A68: 27531 | B68: 八方雲集一 | C68: Bafang Yunji International Co., Ltd. 1st Domestic Unsecured Convertible Bond | D68: 0 | E68: 212 | F68: 45939 | G68: 2753 | H68: 八方雲集 | I68: 46032 | J68: 47035 | K68: 45939 | L68: 45939 | M68: 47035 | N68: 100 | O68: 0 | P68: 800 | Q68: 800 | R68: 100.5 | S68: 800 | T68: 3 | U68: 212 | V68: 980T元大證券 | W68: 中國信託商業銀行股份有限公司代理部 | X68: 無 | Y68: 47035 | Z68: 100 | AA68: 0 | AK68: 47035 | AL68: 100 | AM68: 0 | AN68: 無
A69: 27532 | B69: 八方雲集二 | C69: Bafang Yunji International Co., Ltd. 2nd Domestic Unsecured Convertible Bond | D69: 0 | E69: 210 | F69: 45950 | G69: 2753 | H69: 八方雲集 | I69: 46043 | J69: 47046 | K69: 45950 | L69: 45950 | M69: 47046 | N69: 100 | O69: 0 | P69: 200 | Q69: 200 | R69: 107.18 | S69: 200 | T69: 3 | U69: 210 | V69: 980T元大證券 | W69: 中國信託商業銀行股份有限公司代理部 | X69: 無 | Y69: 47046 | Z69: 100 | AA69: 0 | AK69: 47046 | AL69: 100 | AM69: 0 | AN69: 無
A70: 27551 | B70: 揚秦一 | C70: YOUNGQIN INTERNATIONAL CO.,LTD 1st Domestic Unsecured Convertible Bond | D70: 0 | E70: 86.7 | F70: 45910 | G70: 2755 | H70: 揚秦 | I70: 45763 | J70: 46767 | K70: 45672 | L70: 45672 | M70: 46767 | N70: 100 | O70: 0 | P70: 200 | Q70: 200 | R70: 101 | S70: 121.2 | T70: 3 | U70: 106 | V70: 9A0T永豐金證券 | W70: 台新綜合證券(股)公司股務代理部 | X70: 無 | Y70: 46767 | Z70: 100 | AA70: 0 | AK70: 46767 | AL70: 100 | AM70: 0 | AN70: 無 | AQ70: 45887 | AR70: 45910
A71: 27561 | B71: 聯發國際一 | C71: LIAN FA INTERNATIONAL DINING BUSINESS CORP. Domestic First Convertible Bonds | D71: 0 | E71: 90.1 | F71: 45966 | G71: 2756 | H71: 聯發國際 | I71: 45535 | J71: 46537 | K71: 45442 | L71: 45442 | M71: 46537 | N71: 100 | O71: 0 | P71: 300 | Q71: 300 | R71: 101 | S71: 295 | T71: 3 | U71: 94.3 | V71: 585T統一綜合證券 | W71: 凱基證券股份有限公司股務代理部 | X71: 發行滿二年 | Y71: 46172 | Z71: 101.0025 | AA71: 0.5 | AB71: 46537 | AC71: 100 | AD71: 0 | AK71: 46172 | AL71: 101.0025 | AM71: 0.5 | AN71: 無 | AQ71: 45939 | AR71: 45966
A72: 29051 | B72: 三商一 | C72: Mercuries & Associates Holding, Ltd. 1st Domestic Unsecured Convertible Bond | D72: 0 | E72: 19.23 | F72: 45916 | G72: 2905 | H72: 三商 | I72: 44312 | J72: 46047 | K72: 44221 | L72: 44221 | M72: 46047 | N72: 100 | O72: 0 | P72: 2300 | Q72: 2300 | R72: 100.5 | S72: 254.7 | T72: 5 | U72: 22.5 | V72: 930T華南永昌綜合證券 | W72: 宏遠證券股份有限公司股務代理部 | X72: 發行滿三年 | Y72: 45316 | Z72: 100.75 | AA72: 0.25 | AB72: 46047 | AC72: 100 | AD72: 0 | AK72: 46047 | AL72: 100 | AM72: 0 | AN72: 無 | AQ72: 45891 | AR72: 45916
A73: 29061 | B73: 高林一 | C73: Collins Co., Ltd.1st Domestic Unsecured Convertible Bond | D73: 0 | E73: 16.8 | F73: 45859 | G73: 2906 | H73: 高林 | I73: 45281 | J73: 46285 | K73: 45189 | L73: 45189 | M73: 46285 | N73: 100 | O73: 0 | P73: 1000 | Q73: 1000 | R73: 105.28 | S73: 460 | T73: 3 | U73: 18 | V73: 592T元富證券 | W73: 元富證券股份有限公司股務代理部 | X73: 發行滿二年 | Y73: 45920 | Z73: 102.01 | AA73: 1 | AB73: 46285 | AC73: 100 | AD73: 0 | AK73: 46285 | AL73: 100 | AM73: 0 | AN73: 無 | AQ73: 45834 | AR73: 45859
A74: 30061 | B74: 晶豪科一 | C74: Elite Semiconductor Microelectronics Tech Inc. 1st Unsecured Convertible Bond | D74: 0 | E74: 83.6 | F74: 45853 | G74: 3006 | H74: 晶豪科 | I74: 45319 | J74: 46322 | K74: 45226 | L74: 45226 | M74: 46322 | N74: 100 | O74: 0 | P74: 1000 | Q74: 1000 | R74: 115.42 | S74: 999.9 | T74: 3 | U74: 85.6 | V74: 920T凱基證券 | W74: 群益金鼎證券股份有限公司股務代理部 | X74: 無 | Y74: 46322 | Z74: 100 | AA74: 0 | AK74: 46322 | AL74: 100 | AM74: 0 | AN74: 無 | AQ74: 45828 | AR74: 45853
A75: 30134 | B75: 晟銘電四 | C75: CHENMING ELECTRONIC TECHNOLOGY CORPORATION 4th Domestic Secured Convertible Bond | D75: 0 | E75: 143.8 | F75: 45858 | G75: 3013 | H75: 晟銘電 | I75: 45676 | J75: 46678 | K75: 45583 | L75: 45583 | M75: 46678 | N75: 100 | O75: 0 | P75: 500 | Q75: 500 | R75: 114.01 | S75: 500 | T75: 3 | U75: 144.5 | V75: 616T中國信託綜合證券 | W75: 中國信託商業銀行股份有限公司股務代理部 | X75: 無 | Y75: 46678 | Z75: 100 | AA75: 0 | AK75: 46678 | AL75: 100 | AM75: 0 | AN75: 有，兆豐國際商業銀行股份有限公司、中國信託商業銀行股份有限公司 | AQ75: 45833 | AR75: 45858
A76: 30165 | B76: 嘉晶五 | C76: Episil-Precision Inc. 5th Domestic Unsecured Convertible Bond | D76: 0 | E76: 71.4 | F76: 45853 | G76: 3016 | H76: 嘉晶 | I76: 45592 | J76: 46594 | K76: 45499 | L76: 45499 | M76: 46594 | N76: 100 | O76: 0 | P76: 500 | Q76: 500 | R76: 101 | S76: 500 | T76: 3 | U76: 72.6 | V76: 920T凱基證券 | W76: 永豐金證券股份有限公司股務代理部 | X76: 無 | Y76: 46594 | Z76: 100 | AA76: 0 | AK76: 46594 | AL76: 100 | AM76: 0 | AN76: 無 | AQ76: 45828 | AR76: 45853
A77: 30238 | B77: 信邦八 | C77: SINBON Electronics Co., Ltd. 8th Domestic Unsecured Convertible Bond | D77: 0 | E77: 259.5 | F77: 45896 | G77: 3023 | H77: 信邦 | I77: 44998 | J77: 46003 | K77: 44907 | L77: 44907 | M77: 46003 | N77: 100 | O77: 0 | P77: 1000 | Q77: 1000 | R77: 104.5 | S77: 816.7 | T77: 3 | U77: 286.5 | V77: 815T台新綜合證券 | W77: 台新綜合證券股份有限公司股務代理部 | X77: 發行滿二年 | Y77: 45638 | Z77: 101.0025 | AA77: 0.5 | AB77: 46003 | AC77: 100 | AD77: 0 | AK77: 46003 | AL77: 100 | AM77: 0 | AN77: 無 | AQ77: 45873 | AR77: 45896
A78: 30321 | B78: 偉訓一 | C78: COMPUCASE ENTERPRISE CO., LTD.. 1st Unsecured Convertible Bond | D78: 0 | E78: 105.9 | F78: 45974 | G78: 3032 | H78: 偉訓 | I78: 46067 | J78: 47070 | K78: 45974 | L78: 45974 | M78: 47070 | N78: 101.5075 | O78: 0.5 | P78: 1000 | Q78: 1000 | R78: 100 | S78: 1000 | T78: 3 | U78: 105.9 | V78: 585T統一綜合證券 | W78: 元大證券股務代理部 | X78: 發行滿二年 | Y78: 46704 | Z78: 101.0025 | AA78: 0.5 | AB78: 47070 | AC78: 101.5075 | AD78: 0.5 | AK78: 46704 | AL78: 101.0025 | AM78: 0.5 | AN78: 無
A79: 30322 | B79: 偉訓二 | C79: COMPUCASE ENTERPRISE CO., LTD.. 2nd Unsecured Convertible Bond | D79: 0 | E79: 101.9 | F79: 45986 | G79: 3032 | H79: 偉訓 | I79: 46079 | J79: 47812 | K79: 45986 | L79: 45986 | M79: 47812 | N79: 100 | O79: 0 | P79: 1000 | Q79: 1000 | R79: 104.73 | S79: 1000 | T79: 5 | U79: 101.9 | V79: 585T統一綜合證券 | W79: 元大證券股務代理部 | X79: 發行滿二、三、四年 | Y79: 46716 | Z79: 101.0025 | AA79: 0.5 | AB79: 47082 | AC79: 101.5075 | AD79: 0.5 | AE79: 47447 | AF79: 102.0151 | AG79: 0.5 | AH79: 47812 | AI79: 100 | AJ79: 0 | AK79: 46716 | AL79: 101.0025 | AM79: 0.5 | AN79: 無
A80: 30336 | B80: 威健六 | C80: Weikeng Industrial Co., Ltd. 6th Domestic Unsecured Convertible Bond | D80: 0 | E80: 24.84 | F80: 45886 | G80: 3033 | H80: 威健 | I80: 44806 | J80: 46539 | K80: 44713 | L80: 44713 | M80: 46539 | N80: 100 | O80: 0 | P80: 2000 | Q80: 2000 | R80: 100 | S80: 435.9 | T80: 5 | U80: 34.27 | V80: 930T華南永昌綜合證券 | W80: 元大證券(股)公司 | X80: 發行滿三、四年 | Y80: 45809 | Z80: 101.5 | AA80: 0.5 | AB80: 46174 | AC80: 102 | AD80: 0.5 | AE80: 46539 | AF80: 100 | AG80: 0 | AK80: 46174 | AL80: 102 | AM80: 0.5 | AN80: 無 | AQ80: 45861 | AR80: 45886
A81: 30337 | B81: 威健七 | C81: Weikeng Industrial Co., Ltd. 7th Domestic Unsecured Convertible Bond | D81: 0 | E81: 34.44 | F81: 45886 | G81: 3033 | H81: 威健 | I81: 45638 | J81: 47372 | K81: 45546 | L81: 45546 | M81: 47372 | N81: 100 | O81: 0 | P81: 2500 | Q81: 2500 | R81: 100 | S81: 2500 | T81: 5 | U81: 36.67 | V81: 930T華南永昌綜合證券 | W81: 元大證券(股)公司 | X81: 發行滿三、四年 | Y81: 46641 | Z81: 100 | AA81: 0 | AB81: 47007 | AC81: 100 | AD81: 0 | AE81: 47372 | AF81: 100 | AG81: 0 | AK81: 46641 | AL81: 100 | AM81: 0 | AN81: 無 | AQ81: 45861 | AR81: 45886
A82: 30371 | B82: 欣興一 | C82: Unimicron Technology Corp.1st unsecured convertible corporate bonds | D82: 0 | E82: 165.4 | F82: 45964 | G82: 3037 | H82: 欣興 | I82: 46057 | J82: 47790 | K82: 45964 | L82: 45964 | M82: 47790 | N82: 100 | O82: 0 | P82: 4000 | Q82: 4000 | R82: 101 | S82: 4000 | T82: 5 | U82: 165.4 | V82: 616T中國信託綜合證券 | W82: 宏遠證券股份有限公司 | X82: 發行滿三年 | Y82: 47060 | Z82: 100 | AA82: 0 | AB82: 47790 | AC82: 100 | AD82: 0 | AK82: 47060 | AL82: 100 | AM82: 0 | AN82: 無
A83: 30401 | B83: 遠見一 | C83: GLOBAL VIEW CO.,LTD 1st Domestic Unsecured Convertible Bond | D83: 0 | E83: 47.2 | F83: 45843 | G83: 3040 | H83: 遠見 | I83: 45931 | J83: 46934 | K83: 45838 | L83: 45838 | M83: 46934 | N83: 100 | O83: 0 | P83: 500 | Q83: 500 | R83: 100 | S83: 366.8 | T83: 3 | U83: 48.3 | V83: 585T統一綜合證券 | W83: 元大證券股份有限公司 股務代理部 | X83: 發行滿二年 | Y83: 46568 | Z83: 102.01 | AA83: 1 | AB83: 46934 | AC83: 100 | AD83: 0 | AK83: 46568 | AL83: 102.01 | AM83: 1 | AN83: 無
A84: 30454 | B84: 台灣大四 | C84: TAIWAN MOBILE 4th Domestic Unsecured Convertible Bond | D84: 0 | E84: 118.2 | F84: 45853 | G84: 3045 | H84: 台灣大 | I84: 45802 | J84: 47538 | K84: 45712 | L84: 45712 | M84: 47538 | N84: 100 | P84: 7000 | Q84: 7000 | R84: 100 | S84: 7000 | T84: 5 | U84: 123 | V84: 980T元大證券 | W84: 富邦綜合證券股務代理部 | X84: 發行滿三年 | Y84: 46807 | Z84: 100 | AA84: 0 | AB84: 47538 | AC84: 100 | AD84: 0 | AK84: 46807 | AL84: 100 | AM84: 0 | AN84: 無 | AQ84: 45828 | AR84: 45853
A85: 30455 | B85: 台灣大五 | C85: TAIWAN MOBILE 5th Domestic Unsecured Convertible Bond | D85: 0 | E85: 111.3 | F85: 45853 | G85: 3045 | H85: 台灣大 | I85: 45803 | J85: 47539 | K85: 45713 | L85: 45713 | M85: 47539 | N85: 100 | O85: 0 | P85: 3000 | Q85: 3000 | R85: 100.63 | S85: 3000 | T85: 5 | U85: 115.8 | V85: 980T元大證券 | W85: 富邦綜合證券股務代理部 | X85: 發行滿三年 | Y85: 46808 | Z85: 100 | AA85: 0 | AB85: 47539 | AC85: 100 | AD85: 0 | AK85: 46808 | AL85: 100 | AM85: 0 | AN85: 無 | AQ85: 45828 | AR85: 45853
A86: 30882 | B86: 艾訊二 | C86: Axiomtek Co., Ltd. Domestic 2nd Unsecured Convertible Bond | D86: 0 | E86: 88.5 | F86: 45877 | G86: 3088 | H86: 艾訊 | I86: 45259 | J86: 46262 | K86: 45166 | L86: 45166 | M86: 46262 | N86: 100 | O86: 0 | P86: 800 | Q86: 800 | R86: 106 | S86: 368.6 | T86: 3 | U86: 109.5 | V86: 920T凱基證券 | W86: 台新綜合證券股份有限公司股務代理部 | X86: 無 | Y86: 46262 | Z86: 100 | AA86: 0 | AK86: 46262 | AL86: 100 | AM86: 0 | AN86: 無 | AQ86: 45852 | AR86: 45877
A87: 30922 | B87: 鴻碩二 | C87: HOTRON PRECISION ELECTRONIC INDUSTRIAL CO.LTD. 2nd Unsecured Convertible Bond | D87: 0 | E87: 36 | F87: 45152 | G87: 3092 | H87: 鴻碩 | I87: 45204 | J87: 46207 | K87: 45111 | L87: 45111 | M87: 46207 | N87: 100 | O87: 0 | P87: 250 | Q87: 250 | R87: 107.33 | S87: 46.3 | T87: 3 | U87: 37.6 | V87: 凱基證券股份有限公司 | W87: 中國信託商業銀行代理部 | X87: 發行滿二年 | Y87: 45842 | Z87: 101.0025 | AA87: 0.5 | AB87: 46207 | AC87: 100 | AD87: 0 | AK87: 46207 | AL87: 100 | AM87: 0 | AN87: 無 | AQ87: 45746 | AR87: 45805
A88: 30954 | B88: 及成四 | C88: Taiwan CHI CHENG Enterprise Co., Ltd. 4th Secured Convertible Bond | D88: 0 | E88: 41.1 | F88: 45713 | G88: 3095 | H88: 及成 | I88: 45803 | J88: 46808 | K88: 45713 | L88: 45713 | M88: 46808 | N88: 100 | O88: 0 | P88: 150 | Q88: 150 | R88: 113.44 | S88: 150 | T88: 3 | U88: 41.1 | V88: 815T台新綜合證券 | W88: 中國信託商業銀行代理部 | X88: 發行滿二年 | Y88: 46443 | Z88: 100 | AA88: 0 | AB88: 46808 | AC88: 100 | AD88: 0 | AK88: 46443 | AL88: 100 | AM88: 0 | AN88: 有，陽信商業銀行股份有限公司 | AQ88: 45765 | AR88: 45824
A89: 31222 | B89: 笙泉二 | C89: Megawin Technology Co., Ltd. 2nd Domestic Unsecured Convertible Bond | D89: 0 | E89: 42.3 | F89: 45415 | G89: 3122 | H89: 笙泉 | I89: 45508 | J89: 46510 | K89: 45415 | L89: 45415 | M89: 46510 | N89: 101.5075 | O89: 0.5 | P89: 200 | Q89: 200 | R89: 101 | S89: 199.1 | T89: 3 | U89: 42.3 | V89: 群益金鼎證券股份有限公司 | W89: 群益金鼎證券股份有限公司股務代理部 | X89: 發行滿二年 | Y89: 46145 | Z89: 101.0025 | AA89: 0.5 | AB89: 46510 | AC89: 101.5075 | AD89: 0.5 | AK89: 46145 | AL89: 101.0025 | AM89: 0.5 | AN89: 無 | AQ89: 45739 | AR89: 45798
A90: 31282 | B90: 昇銳二 | C90: Hi Sharp Intelligence Technology Co.,Ltd. 2nd Unsecured Convertible Bond | D90: 0 | E90: 37.8 | F90: 45899 | G90: 3128 | H90: 昇銳 | I90: 45203 | J90: 46206 | K90: 45110 | L90: 45110 | M90: 46206 | N90: 100 | O90: 0 | P90: 300 | Q90: 300 | R90: 100 | S90: 108.3 | T90: 3 | U90: 44.1 | V90: 779T國票綜合證券 | W90: 群益金鼎證券股份有限公司股務代理部 | X90: 發行滿二年 | Y90: 45841 | Z90: 100.5006 | AA90: 0.25 | AB90: 46206 | AC90: 100 | AD90: 0 | AK90: 46206 | AL90: 100 | AM90: 0 | AN90: 無 | AQ90: 45874 | AR90: 45899
A91: 31311 | B91: 弘塑一 | C91: GRAND PROCESS TECHNOLOGY.CO.,LTD.1st Domestic Unsecured Convertible Bond | D91: 0 | E91: 1736.5 | F91: 45873 | G91: 3131 | H91: 弘塑 | I91: 45961 | J91: 47694 | K91: 45868 | L91: 45868 | M91: 47694 | N91: 100 | O91: 0 | P91: 1000 | Q91: 1000 | R91: 100.5 | S91: 1000 | T91: 5 | U91: 1762.2 | V91: 920T凱基證券 | W91: 群益金鼎證券股務代理部 | X91: 發行滿三年 | Y91: 46964 | Z91: 100 | AA91: 0 | AB91: 47694 | AC91: 100 | AD91: 0 | AK91: 46964 | AL91: 100 | AM91: 0 | AN91: 無
A92: 31312 | B92: 弘塑二 | C92: GRAND PROCESS TECHNOLOGY.CO.,LTD.2nd Unsecured Convertible Bond | D92: 0 | E92: 1626.6 | F92: 45874 | G92: 3131 | H92: 弘塑 | I92: 45967 | J92: 47700 | K92: 45874 | L92: 45874 | M92: 47700 | N92: 100 | O92: 0 | P92: 1000 | Q92: 1000 | R92: 110.5 | S92: 1000 | T92: 5 | U92: 1626.6 | V92: 920T凱基證券 | W92: 群益金鼎證券股務代理部 | X92: 發行滿三年 | Y92: 46970 | Z92: 100 | AA92: 0 | AB92: 47700 | AC92: 100 | AD92: 0 | AK92: 46970 | AL92: 100 | AM92: 0 | AN92: 無
A93: 31351 | B93: 凌航一 | C93: GoldKey Technology Corporation 1st Unsecured Convertible Bond | D93: 0 | E93: 52.19 | F93: 45995 | G93: 3135 | H93: 凌航 | I93: 46086 | J93: 47091 | K93: 45995 | L93: 45995 | M93: 47091 | N93: 100 | O93: 0 | P93: 1000 | Q93: 1000 | R93: 100 | S93: 1000 | T93: 3 | U93: 52.19 | V93: 585T統一綜合證券 | W93: 元大證券股份有限公司股務代理部 | X93: 發行滿二年 | Y93: 46725 | Z93: 102.01 | AA93: 1 | AB93: 47091 | AC93: 100 | AD93: 0 | AK93: 46725 | AL93: 102.01 | AM93: 1 | AN93: 無
A94: 31382 | B94: 耀登二 | C94: Auden Techno Corp.2nd Domestic Unsecured Convertible Bonds | D94: 0 | E94: 114.7 | F94: 45838 | G94: 3138 | H94: 耀登 | I94: 45758 | J94: 46762 | K94: 45667 | L94: 45667 | M94: 46762 | N94: 100 | O94: 0 | P94: 700 | Q94: 700 | R94: 100.5 | S94: 700 | T94: 3 | U94: 118 | V94: 960T富邦綜合證券 | W94: 國票綜合證券股務代理部 | X94: 無 | Y94: 46762 | Z94: 100 | AA94: 0 | AK94: 46762 | AL94: 100 | AM94: 0 | AN94: 無 | AQ94: 45813 | AR94: 45838
A95: 31413 | B95: 晶宏三 | C95: Ultra chip Inc. 3rd Unsecured convertible bond | D95: 0 | E95: 93.6 | F95: 45896 | G95: 3141 | H95: 晶宏 | I95: 45525 | J95: 46527 | K95: 45432 | L95: 45432 | M95: 46527 | N95: 100 | O95: 0 | P95: 800 | Q95: 800 | R95: 101 | S95: 800 | T95: 3 | U95: 95 | V95: 585T統一綜合證券 | W95: 福邦證券股務代理部 | X95: 發行滿二年 | Y95: 46162 | Z95: 100 | AA95: 0 | AB95: 46527 | AC95: 100 | AD95: 0 | AK95: 46162 | AL95: 100 | AM95: 0 | AN95: 無 | AQ95: 45873 | AR95: 45896
A96: 31672 | B96: 大量二 | C96: TA LIANG TECHNOLOGY CO., LTD. 2nd Domestic Unsecured Convertible Bond | D96: 0 | E96: 169.1 | F96: 45905 | G96: 3167 | H96: 大量 | I96: 45968 | J96: 46971 | K96: 45875 | L96: 45875 | M96: 46971 | N96: 100 | O96: 0 | P96: 500 | Q96: 500 | R96: 109.09 | S96: 500 | T96: 3 | U96: 170 | V96: 648T福邦證券 | W96: 福邦證券股份有限公司股務代理部 | X96: 無 | Y96: 46971 | Z96: 100 | AA96: 0 | AK96: 46971 | AL96: 100 | AM96: 0 | AN96: 無
A97: 31882 | B97: 鑫龍騰二 | C97: Golden Long Teng Development Co., Ltd. 2nd Unsecured Convertible Bond | D97: 0 | E97: 31.4 | F97: 45828 | G97: 3188 | H97: 鑫龍騰 | I97: 45921 | J97: 46924 | K97: 45828 | L97: 45828 | M97: 46924 | N97: 100 | O97: 0 | P97: 600 | Q97: 600 | R97: 100 | S97: 600 | T97: 3 | U97: 31.4 | V97: 920T凱基證券 | W97: 福邦證券股份有限公司 | X97: 發行滿二年 | Y97: 46558 | Z97: 102.01 | AA97: 1 | AB97: 46924 | AC97: 100 | AD97: 0 | AK97: 46558 | AL97: 102.01 | AM97: 1 | AN97: 無
A98: 32071 | B98: 耀勝一 | C98: YAO SHENG ELECTRONIC CO., LTD. 1st Domestic Unsecured Convertible Bond | D98: 0 | E98: 100.99 | F98: 45645 | G98: 3207 | H98: 耀勝 | I98: 45469 | J98: 46471 | K98: 45376 | L98: 45376 | M98: 46471 | N98: 100 | O98: 0 | P98: 500 | Q98: 500 | R98: 100 | S98: 487.1 | T98: 3 | U98: 105.47 | V98: 585T統一綜合證券 | W98: 福邦證券股份有限公司 | X98: 發行滿二年 | Y98: 46106 | Z98: 102.01 | AA98: 1 | AB98: 46471 | AC98: 100 | AD98: 0 | AK98: 46106 | AL98: 102.01 | AM98: 1 | AN98: 無 | AQ98: 45774 | AR98: 45833
A99: 32571 | B99: 虹冠電一 | C99: CHAMPION MICROELECTRONIC CORP. 1st Domestic Unsecured Convertible Bond | D99: 0 | E99: 72.2 | F99: 45758 | G99: 3257 | H99: 虹冠電 | I99: 45690 | J99: 47423 | K99: 45597 | L99: 45597 | M99: 47423 | N99: 100 | O99: 0 | P99: 500 | Q99: 500 | R99: 101 | S99: 500 | T99: 5 | U99: 75 | V99: 815T台新綜合證券 | W99: 福邦證券股份有限公司 股務代理部 | X99: 發行滿三、四年 | Y99: 46692 | Z99: 101.5075 | AA99: 0.5 | AB99: 47058 | AC99: 102.0151 | AD99: 0.5 | AE99: 47423 | AF99: 100 | AG99: 0 | AK99: 46692 | AL99: 101.5075 | AM99: 0.5 | AN99: 無 | AQ99: 45729 | AR99: 45813
A100: 32723 | B100: 東碩三 | C100: Good Way Technology Domestic 3rd Unsecured Convertible Bonds | D100: 0 | E100: 34.2 | F100: 45358 | G100: 3272 | H100: 東碩 | I100: 45451 | J100: 47184 | K100: 45358 | L100: 45358 | M100: 47184 | N100: 100 | O100: 0 | P100: 300 | Q100: 300 | R100: 108.93 | S100: 299.7 | T100: 5 | U100: 34.2 | V100: 920T凱基證券 | W100: 兆豐證券股份有限公司股務代理部 | X100: 發行滿三年 | Y100: 46453 | Z100: 100.7518 | AA100: 0.25 | AB100: 47184 | AC100: 100 | AD100: 0 | AK100: 46453 | AL100: 100.7518 | AM100: 0.25 | AN100: 無 | AQ100: 45766 | AR100: 45825
...

Sheet 09_最新動態每週日行情
A1: 代碼 | B1: 名稱 | C1: 產業 | D1: CB收盤價 | E1: 成交量 | F1: 股價 | G1: 轉換價格 | H1: 轉換價值 | I1: 溢(折)價% | J1: 停止轉 換起始日 | K1: 停止轉 換終迄日 | L1: 發行日 | M1: 最近賣回日 | N1: 賣回價格 | O1: 到期日 | P1: 到期價格 | Q1: YTP | R1: YTM | S1: 2025Q2公告基本每股盈餘(元) | T1: 股價波動率120天(%) | U1: 股價波動率240天(%) | V1: 自營商買張數 | W1: 自營商賣張數 | X1: 外資買張數 | Y1: 外資賣張數 | Z1: TCRI | AA1: 發行總量(張) | AB1: 流通在外餘額(張) | AC1: 剩餘未轉換比率% | AD1: 債券擔保情形 | AE1: 經營項目
A2: 11011 | B2: 台泥一永 | C2: 水泥工業 | D2: 97.2 | E2: 264 | F2: 22.7 | G2: 35.2 | H2: 64.488636 | I2: 50.724229 | J2: - | K2: - | L2: 45636 | M2: 46731 | N2: 100 | O2: 47462 | P2: 100 | Q2: 0.014344343 | R2: 0.0071819695 | S2: -1.36 | T2: 24.87 | U2: 25.5 | V2: - | W2: - | X2: - | Y2: - | Z2: 4 | AA2: 80000 | AB2: 80000 | AC2: 100.00 | AD2: 無 | AE2: 有關水泥及水泥製品之生產及運銷、有關水泥原料及水泥製品原料之開採製造運銷及附屬礦石之開採經銷、經營有關水泥工業及其附屬事業
A3: 12561 | B3: 鮮活果汁一KY | C3: 食品工業 | D3: 96.95 | E3: 21 | F3: 138.5 | G3: 189.1 | H3: 73.241671 | I3: 32.37 | J3: - | K3: - | L3: 45938 | M3: 46668 | N3: 100.5006 | O3: 47034 | P3: 100 | Q3: 0.019951337 | R3: 0.01108371 | S3: 4.98 | T3: 42.11 | U3: 43.18 | V3: - | W3: - | X3: - | Y3: - | Z3: 5 | AA3: 2000 | AB3: 2000 | AC3: 100.00 | AD3: 無 | AE3: 果汁、果粒、果粉類等產品之生產與銷售
A4: 13164 | B4: 上曜四 | C4: 建材營建 | D4: 104.6 | E4: 7 | F4: 15.15 | G4: 14.7 | H4: 103.06122 | I4: 1.4930693 | J4: - | K4: - | L4: 44225 | M4: 46051 | N4: 100 | O4: 46051 | P4: 100 | Q4: -0.30286085 | R4: -0.30286085 | S4: -0.13 | T4: 35.99 | U4: 46.98 | V4: 4 | W4: 7 | X4: 0 | Y4: 0 | Z4: 8 | AA4: 4000 | AB4: 1340 | AC4: 33.5 | AD4: 有，台北富邦商業銀行股份有限公司 | AE4: 住宅及大樓開發租售業務、不動產買賣業務、不動產租賃業務
A5: 13166 | B5: 上曜六 | C5: 建材營建 | D5: 112.5 | E5: 0 | F5: 15.15 | G5: 17.4 | H5: 87.068966 | I5: 29.207921 | J5: - | K5: - | L5: 45653 | M5: 46383 | N5: 100.5 | O5: 46748 | P5: 100 | Q5: -0.10112554 | R5: -0.054074074 | S5: -0.13 | T5: 35.99 | U5: 46.98 | V5: - | W5: - | X5: - | Y5: - | Z5: 8 | AA5: 4000 | AB5: 4000 | AC5: 100 | AD5: 有，板信商業銀行股份有限公司 | AE5: 住宅及大樓開發租售業務、不動產買賣業務、不動產租賃業務
A6: 13382 | B6: 廣華二KY | C6: 汽車工業 | D6: 100.4 | E6: 3 | F6: 20.6 | G6: 37.6 | H6: 54.787234 | I6: 83.254369 | J6: - | K6: - | L6: 45261 | M6: 46357 | N6: 106.1208 | O6: 47088 | P6: 100 | Q6: 0.057932393 | R6: -0.0013341131 | S6: 0.14 | T6: 20.77 | U6: 23.55 | V6: - | W6: - | X6: - | Y6: - | Z6: 6 | AA6: 6000 | AB6: 6000 | AC6: 100 | AD6: 無 | AE6: 汽車內飾件之曲面印刷、表面塗裝及射出成型等製造及銷售、汽車內飾件之模具製造及銷售、其他
A7: 140201 | B7: 遠東新E1永 | C7: 紡織纖維 | D7: 104.2 | E7: 0 | F7: 38.3 | G7: 43.1 | H7: 88.863109 | I7: 17.259008 | J7: - | K7: - | L7: 45512 | M7: 46607 | N7: 100 | O7: 47338 | P7: 100 | Q7: -0.024157787 | R7: -0.010979173 | S7: 0.42 | T7: 17.09 | U7: 23.11 | V7: - | W7: - | X7: - | Y7: - | Z7: 3 | AA7: 10000 | AB7: 10000 | AC7: 100 | AD7: 無 | AE7: 電信47.55%、生產事業45.99%、不動產開發3.82%、投資及其他2.64%(石化纖維原料、半成品及製成品、纖維紗(布)、混紡紗(布)、假撚絲、棉布、被單、紡織成衣、針織成衣、)
A8: 140202 | B8: 遠東新E2永 | C8: 紡織纖維 | D8: 97.95 | E8: 10 | F8: 23.65 | G8: 31.7 | H8: 74.605678 | I8: 31.290275 | J8: - | K8: - | L8: 45512 | M8: 46607 | N8: 100 | O8: 47338 | P8: 100 | Q8: 0.012543681 | R8: 0.0057008221 | S8: 0.42 | T8: 17.09 | U8: 23.11 | V8: - | W8: - | X8: - | Y8: - | Z8: 3 | AA8: 15000 | AB8: 14992 | AC8: 99.94 | AD8: 無 | AE8: 電信47.55%、生產事業45.99%、不動產開發3.82%、投資及其他2.64%(石化纖維原料、半成品及製成品、纖維紗(布)、混紡紗(布)、假撚絲、棉布、被單、紡織成衣、針織成衣、)
A9: 14363 | B9: 華友聯三 | C9: 建材營建 | D9: 98.95 | E9: 5 | F9: 64 | G9: 128.7 | H9: 49.72805 | I9: 98.982266 | J9: - | K9: - | L9: 45531 | M9: 46261 | N9: 103.0225 | O9: 46626 | P9: 104.5678 | Q9: 0.057119239 | R9: 0.032997702 | S9: 3.25 | T9: 29.8 | U9: 34.43 | V9: - | W9: - | X9: - | Y9: - | Z9: 8 | AA9: 6000 | AB9: 6000 | AC9: 100 | AD9: 無 | AE9: 住宅及大樓開發租售業、休閒活動場館業、餐館業
A10: 14364 | B10: 華友聯四 | C10: 建材營建 | D10: 95.3 | E10: 0 | F10: 64 | G10: 99 | H10: 64.646465 | I10: 47.417187 | J10: - | K10: - | L10: 45734 | M10: 46464 | N10: 103.0225 | O10: 46830 | P10: 104.5678 | Q10: 0.063470507 | R10: 0.042663187 | S10: 3.25 | T10: 29.8 | U10: 34.43 | V10: - | W10: - | X10: - | Y10: - | Z10: 8 | AA10: 20000 | AB10: 20000 | AC10: 100 | AD10: 無 | AE10: 住宅及大樓開發租售業、休閒活動場館業、餐館業
A11: 14381 | B11: 三地開發一 | C11: 建材營建 | D11: 119.7 | E11: 0 | F11: 33.6 | G11: 55.88 | H11: 60.128848 | I11: 99.0725 | J11: - | K11: - | L11: 45645 | M11: 46740 | N11: 101.5075 | O11: 47471 | P11: 102.5251 | Q11: -0.074763081 | R11: -0.03555414 | S11: -0.27 | T11: 27.67 | U11: 38.45 | V11: - | W11: - | X11: - | Y11: - | Z11: 8 | AA11: 9700 | AB11: 9700 | AC11: 100 | AD11: 有，台中商業銀行股份有限公司 | AE11: 委託營造廠商興建商業大樓、工業大樓及住宅出租出售業務、紡織工業之產銷及其附屬事業暨投資金融與其他經濟事業
A12: 14664 | B12: 聚隆四 | C12: 紡織纖維 | D12: 106.35 | E12: 0 | F12: 14.1 | G12: 18.8 | H12: 75 | I12: 41.8 | J12: - | K12: - | L12: 45828 | M12: 46924 | N12: 100 | O12: 46924 | P12: 100 | Q12: -0.023535212 | R12: -0.023535212 | S12: -0.26 | T12: 38.55 | U12: 48.71 | V12: - | W12: - | X12: - | Y12: - | Z12: 7 | AA12: 4000 | AB12: 4000 | AC12: 100 | AD12: 有，台中商業銀行股份有限公司 | AE12: 尼龍絲50.76%、Lyocell長纖絲21.69%、聚酯絲14.77%、複合絲4.41%、P.P絲3.87%(尼龍原絲、假撚絲、仿棉絲製造、加工及買賣、聚酯原絲、假撚絲、空氣打節絲製造、加工及買賣、超細纖維、超細纖維布、彈性纖維、彈性纖維布製造、加工及買賣)
A13: 14722 | B13: 三洋實業二 | C13: 建材營建 | D13: 106.2 | E13: 0 | F13: 90.7 | G13: 98.6 | H13: 91.98783 | I13: 15.450055 | J13: - | K13: - | L13: 45806 | M13: 46536 | N13: 101.0025 | O13: 46902 | P13: 100 | Q13: -0.033203248 | R13: -0.023571738 | S13: 1.62 | T13: 22.03 | U13: 32.3 | V13: - | W13: - | X13: - | Y13: - | Z13: 6 | AA13: 3000 | AB13: 3000 | AC13: 100 | AD13: 有，台中商業銀行股份有限公司 | AE13: 營建工程、營建工程
A14: 14723 | B14: 三洋實業三 | C14: 建材營建 | D14: 95.35 | E14: 2 | F14: 90.7 | G14: 101.5 | H14: 89.359606 | I14: 6.7036935 | J14: - | K14: - | L14: 45825 | M14: 46555 | N14: 102.01 | O14: 46921 | P14: 100 | Q14: 0.045771084 | R14: 0.019285168 | S14: 1.62 | T14: 22.03 | U14: 32.3 | V14: 0 | W14: 1 | X14: 0 | Y14: 0 | Z14: 6 | AA14: 4000 | AB14: 4000 | AC14: 100 | AD14: 無 | AE14: 營建工程、營建工程
A15: 14743 | B15: 弘裕三 | C15: 紡織纖維 | D15: 94 | E15: 0 | F15: 11.45 | G15: 14 | H15: 81.785714 | I15: 14.934498 | J15: - | K15: - | L15: 45747 | M15: 46843 | N15: 101.5075 | O15: 46843 | P15: 101.5075 | Q15: 0.034498773 | R15: 0.034498773 | S15: 0.15 | T15: 19.68 | U15: 28.56 | V15: - | W15: - | X15: - | Y15: - | Z15: 6 | AA15: 3000 | AB15: 3000 | AC15: 100 | AD15: 無 | AE15: 各種棉毛絲纖維織品之製造代織，買賣，印染，整理及加工內外銷、各種塑膠製品之加工製造買賣、有關行紀業務進出口貿易事業
A16: 15142 | B16: 亞力二 | C16: 電機機械 | D16: 112.5 | E16: 22 | F16: 96.3 | G16: 109.2 | H16: 88.186813 | I16: 27.570093 | J16: - | K16: - | L16: 45670 | M16: 46765 | N16: 100.7519 | O16: 47496 | P16: 100 | Q16: -0.049694991 | R16: -0.027073135 | S16: 0.89 | T16: 32.99 | U16: 42.48 | V16: 22 | W16: 22 | X16: 0 | Y16: 0 | Z16: 6 | AA16: 12000 | AB16: 12000 | AC16: 100 | AD16: 無 | AE16: 配電盤、電機器材、電子產品、變壓器
A17: 15261 | B17: 日馳一 | C17: 電機機械 | D17: 96.45 | E17: 0 | F17: 17 | G17: 37.29 | H17: 45.58863 | I17: 111.56591 | J17: - | K17: - | L17: 45188 | M17: 46284 | N17: 100 | O17: 46284 | P17: 100 | Q17: 0.046973503 | R17: 0.046973503 | S17: 0.08 | T17: 31.35 | U17: 38.19 | V17: - | W17: - | X17: - | Y17: - | Z17: 7 | AA17: 5000 | AB17: 5000 | AC17: 100 | AD17: 無 | AE17: 各種腳踏車之零件機械五金之加工製造買賣業務
A18: 15364 | B18: 和大四 | C18: 汽車工業 | D18: 98 | E18: 82 | F18: 58.5 | G18: 71.47 | H18: 81.852526 | I18: 19.727521 | J18: - | K18: - | L18: 45516 | M18: 46246 | N18: 100 | O18: 46611 | P18: 100 | Q18: 0.030036208 | R18: 0.01215168 | S18: -0.15 | T18: 35.37 | U18: 48.46 | V18: 11 | W18: 22 | X18: 0 | Y18: 0 | Z18: 7 | AA18: 15000 | AB18: 15000 | AC18: 100 | AD18: 無 | AE18: 汽、機車、農業機械等之齒輪、軸類製造及買賣、各種機械及零件之製造加工與代理經銷買賣業務、各種汽機車零件製造及代理經銷買賣
A19: 15601 | B19: 中砂一 | C19: 電機機械 | D19: 132.9 | E19: 110 | F19: 342 | G19: 284.6 | H19: 120.16866 | I19: 10.594561 | J19: - | K19: - | L19: 45467 | M19: 46562 | N19: 100 | O19: 47293 | P19: 100 | Q19: -0.16020818 | R19: -0.069774063 | S19: 2.24 | T19: 38.44 | U19: 47.06 | V19: 105 | W19: 68 | X19: 0 | Y19: 0 | Z19: 4 | AA19: 10000 | AB19: 9994 | AC19: 99.94 | AD19: 無 | AE19: 各種研磨品，各種切削刀具，之製造加工經銷及代理研磨加工、再生晶圓、其他金屬製品製造業－金屬台金，熱處理業，表面處理業，模具製造業
A20: 15864 | B20: 和勤四 | C20: 電機機械 | D20: 109.5 | E20: 0 | F20: 27.15 | G20: 30.74 | H20: 88.321405 | I20: 23.979006 | J20: - | K20: - | L20: 45168 | M20: 46264 | N20: 100 | O20: 46264 | P20: 100 | Q20: -0.11904762 | R20: -0.11904762 | S20: -0.04 | T20: 32.18 | U20: 29.78 | V20: - | W20: - | X20: - | Y20: - | Z20: 8 | AA20: 2000 | AB20: 2000 | AC20: 100 | AD20: 有，合作金庫商業銀行股份有限公司 | AE20: 汽機車另件78.57%、硬碟機另件18.68%、其他2.75%(各類電子及汽車零件之加工製造買賣之產品業務)
A21: 15865 | B21: 和勤五 | C21: 電機機械 | D21: 100.15 | E21: 0 | F21: 27.15 | G21: 30.14 | H21: 90.079628 | I21: 11.179411 | J21: - | K21: - | L21: 45169 | M21: 46265 | N21: 101.5075 | O21: 46265 | P21: 101.5075 | Q21: 0.01852979 | R21: 0.01852979 | S21: -0.04 | T21: 32.18 | U21: 29.78 | V21: - | W21: - | X21: - | Y21: - | Z21: 8 | AA21: 3000 | AB21: 2902 | AC21: 96.73 | AD21: 無 | AE21: 汽機車另件78.57%、硬碟機另件18.68%、其他2.75%(各類電子及汽車零件之加工製造買賣之產品業務)
A22: 15894 | B22: 永冠四KY | C22: 電機機械 | D22: 100.2 | E22: 3 | F22: 17.4 | G22: 60.7 | H22: 28.665568 | I22: 249.54828 | J22: - | K22: - | L22: 44977 | M22: 46073 | N22: 101.51 | O22: 46803 | P22: 100 | Q22: 0.063626081 | R22: -0.00090502225 | S22: -2.34 | T22: 37.43 | U22: 38.37 | V22: - | W22: - | X22: - | Y22: - | Z22: 8 | AA22: 15000 | AB22: 10316 | AC22: 68.77 | AD22: 無 | AE22: 主要從事球狀石墨鑄鐵/灰口鑄鐵之高級鑄件產品之製造及銷售業務
A23: 15952 | B23: 川寶二 | C23: 電子–電子零組件 | D23: 109.95 | E23: 0 | F23: 36.85 | G23: 37.7 | H23: 97.745358 | I23: 12.48616 | J23: - | K23: - | L23: 45537 | M23: 46632 | N23: 101.51 | O23: 47363 | P23: 100 | Q23: -0.044192729 | R23: -0.024198478 | S23: -0.41 | T23: 45.85 | U23: 52.62 | V23: - | W23: - | X23: - | Y23: - | Z23: 6 | AA23: 3000 | AB23: 910 | AC23: 30.33 | AD23: 無 | AE23: 電子零組件製造業、設計、研發、生產CCD自動對位曝光機
A24: 15984 | B24: 岱宇四 | C24: 運動休閒 | D24: 96.05 | E24: 0 | F24: 22.2 | G24: 32.7 | H24: 67.889908 | I24: 41.479054 | J24: - | K24: - | L24: 45719 | M24: 46449 | N24: 102.01 | O24: 46815 | P24: 100 | Q24: 0.050218671 | R24: 0.018372596 | S24: 0.36 | T24: 31.95 | U24: 39.27 | V24: - | W24: - | X24: - | Y24: - | Z24: 7 | AA24: 2000 | AB24: 2000 | AC24: 100 | AD24: 無 | AE24: 健身器材
A25: 16095 | B25: 大亞五 | C25: 電器電纜 | D25: 104.3 | E25: 0 | F25: 39.3 | G25: 51.3 | H25: 76.608187 | I25: 36.147328 | J25: - | K25: - | L25: 45565 | M25: 46660 | N25: 100.75 | O25: 47391 | P25: 100 | Q25: -0.018766311 | R25: -0.01080254 | S25: 0.44 | T25: 37.92 | U25: 40.35 | V25: - | W25: - | X25: - | Y25: - | Z25: 5 | AA25: 20000 | AB25: 20000 | AC25: 100 | AD25: 無 | AE25: 發電輸電配電機械製造業、電線電纜製造業、其他塑膠製品製造業、電子零組件製造業、配管工程業、其它工程業、塑膠膜、鋼線鋼纜、金屬結構建築組件製造業、電信器材電子材料批發業、國際貿易業
A26: 17813 | B26: 合世三 | C26: 生技醫療 | D26: 101.5 | E26: 0 | F26: 11.2 | G26: 18 | H26: 62.222222 | I26: 63.125 | J26: - | K26: - | L26: 45559 | M26: 46654 | N26: 100 | O26: 46654 | P26: 100 | Q26: -0.0082226961 | R26: -0.0082226961 | S26: -0.38 | T26: 18.69 | U26: 31.95 | V26: - | W26: - | X26: - | Y26: - | Z26: 7 | AA26: 2000 | AB26: 2000 | AC26: 100 | AD26: 有，華南商業銀行股份有限公司 | AE26: 電子血壓計、藥物微霧化器
A27: 17863 | B27: 科妍三 | C27: 生技醫療 | D27: 126 | E27: 0 | F27: 78.9 | G27: 116.5 | H27: 67.725322 | I27: 86.045627 | J27: - | K27: - | L27: 45870 | M27: 46600 | N27: 102.01 | O27: 46966 | P27: 100 | Q27: -0.11543994 | R27: -0.077807294 | S27: 0.81 | T27: 40.6 | U27: 42.91 | V27: - | W27: - | X27: - | Y27: - | Z27: 6 | AA27: 4000 | AB27: 4000 | AC27: 100 | AD27: 無 | AE27: 透明質酸(玻尿酸)醫療器材產品研發製造及銷售、透明質酸(玻尿酸)保養品研發製造及銷售
A28: 18156 | B28: 富喬六 | C28: 電子–電子零組件 | D28: 576 | E28: 0 | F28: 83.4 | G28: 13.82 | H28: 603.47323 | I28: -4.552518 | J28: - | K28: - | L28: 44271 | M28: 46097 | N28: 100 | O28: 46097 | P28: 100 | Q28: -3.0467873 | R28: -3.0467873 | S28: 0.54 | T28: 69.98 | U28: 64.69 | V28: - | W28: - | X28: - | Y28: - | Z28: 7 | AA28: 4000 | AB28: 85 | AC28: 2.12 | AD28: 無 | AE28: 電子級玻璃纖維、電子級玻璃纖維、電子級玻璃纖維
A29: 19094 | B29: 榮成四 | C29: 造紙工業 | D29: 96.2 | E29: 0 | F29: 10.85 | G29: 23.9 | H29: 45.39749 | I29: 111.90599 | J29: - | K29: - | L29: 44550 | M29: 46376 | N29: 100 | O29: 46376 | P29: 100 | Q29: 0.038142538 | R29: 0.038142538 | S29: -0.11 | T29: 32.87 | U29: 33.62 | V29: - | W29: - | X29: - | Y29: - | Z29: 7 | AA29: 7000 | AB29: 160 | AC29: 2.28 | AD29: 無 | AE29: 紙器及紙類之製造、印刷、加工、買賣、代理及進出口業務、造紙原料之製造、加工、買賣、代理及進出口業務、紙器及紙類加工設備之買賣
A30: 20343 | B30: 允強三 | C30: 鋼鐵工業 | D30: 102 | E30: 0 | F30: 20.2 | G30: 20.1 | H30: 100.49751 | I30: 1.4950495 | J30: - | K30: - | L30: 44180 | M30: 46006 | N30: 100 | O30: 46006 | P30: 100 | Q30: -0.89460784 | R30: -0.89460784 | S30: 0.4 | T30: 26.49 | U30: 39.58 | V30: - | W30: - | X30: - | Y30: - | Z30: 4 | AA30: 10000 | AB30: 1524 | AC30: 15.24 | AD30: 無 | AE30: 不銹鋼捲(板)裁切及買賣、不銹鋼焊接鋼管之製造加工及買賣、不銹鋼角鋼，扁鐵及槽鐵等之製造加工及買賣
A31: 20344 | B31: 允強四 | C31: 鋼鐵工業 | D31: 106.2 | E31: 0 | F31: 20.2 | G31: 24 | H31: 84.166667 | I31: 26.178218 | J31: - | K31: - | L31: 45567 | M31: 46662 | N31: 100 | O31: 47393 | P31: 100 | Q31: -0.032091643 | R31: -0.015275162 | S31: 0.4 | T31: 26.49 | U31: 39.58 | V31: - | W31: - | X31: - | Y31: - | Z31: 4 | AA31: 20000 | AB31: 20000 | AC31: 100 | AD31: 無 | AE31: 不銹鋼捲(板)裁切及買賣、不銹鋼焊接鋼管之製造加工及買賣、不銹鋼角鋼，扁鐵及槽鐵等之製造加工及買賣
A32: 20632 | B32: 世鎧二 | C32: 鋼鐵工業 | D32: 99.45 | E32: 1 | F32: 25.2 | G32: 47.9 | H32: 52.609603 | I32: 89.033929 | J32: - | K32: - | L32: 45240 | M32: 46336 | N32: 100 | O32: 46336 | P32: 100 | Q32: 0.0059721962 | R32: 0.0059721962 | S32: 0.53 | T32: 19.43 | U32: 25.76 | V32: 0 | W32: 1 | X32: 0 | Y32: 0 | Z32: 6 | AA32: 6000 | AB32: 145 | AC32: 2.41 | AD32: 無 | AE32: 螺絲、螺帽、螺絲釘及鉚釘等製品製造業、金屬線製品製造業
A33: 20662 | B33: 世德二 | C33: 電機機械 | D33: 97.6 | E33: 0 | F33: 50.5 | G33: 88.1 | H33: 57.321226 | I33: 70.268515 | J33: - | K33: - | L33: 45138 | M33: 46234 | N33: 100 | O33: 46234 | P33: 100 | Q33: 0.038031398 | R33: 0.038031398 | S33: 0.72 | T33: 29.33 | U33: 39.42 | V33: - | W33: - | X33: - | Y33: - | Z33: 6 | AA33: 4000 | AB33: 2378 | AC33: 59.45 | AD33: 無 | AE33: 汽車、機械用之特殊零件、配件生產及研發、汽車用之標準扣件(有螺紋及無螺紋產品)、電子、建築、家具及其他產業用之有螺紋扣件產品
A34: 21043 | B34: 國際中橡三 | C34: 橡膠工業 | D34: 98.05 | E34: 0 | F34: 10.3 | G34: 21.2 | H34: 48.584906 | I34: 101.81165 | J34: - | K34: - | L34: 45212 | M34: 46308 | N34: 100.9 | O34: 47039 | P34: 100 | Q34: 0.034223816 | R34: 0.0069731523 | S34: -2.86 | T34: 27.91 | U34: 31.59 | V34: - | W34: - | X34: - | Y34: - | Z34: 5 | AA34: 35000 | AB34: 35000 | AC34: 100 | AD34: 無 | AE34: 一般投資業
A35: 22013 | B35: 裕隆三 | C35: 汽車工業 | D35: 99.5 | E35: 0 | F35: 34.6 | G35: 75 | H35: 46.133333 | I35: 115.67919 | J35: - | K35: - | L35: 45071 | M35: 46167 | N35: 100.7519 | O35: 46898 | P35: 102.5251 | Q35: 0.027173947 | R35: 0.012330112 | S35: 0.24 | T35: 40.41 | U35: 42.18 | V35: - | W35: - | X35: - | Y35: - | Z35: 5 | AA35: 70000 | AB35: 69999 | AC35: 99.99 | AD35: 無 | AE35: 汽車、零件、保修及其他
A36: 22283 | B36: 劍麟三 | C36: 汽車工業 | D36: 123.5 | E36: 6 | F36: 101 | G36: 85.36 | H36: 118.3224 | I36: 4.3758416 | J36: - | K36: - | L36: 45533 | M36: 46628 | N36: 100 | O36: 46628 | P36: 100 | Q36: -0.11024356 | R36: -0.11024356 | S36: 1.12 | T36: 51.22 | U36: 45.54 | V36: 5 | W36: 5 | X36: 0 | Y36: 0 | Z36: 5 | AA36: 3000 | AB36: 2787 | AC36: 92.9 | AD36: 無 | AE36: CD01030汽車及其零件製造業、F401010國際貿易業、除許可業務外，得經營法令非禁止或限制之業務
A37: 22362 | B37: 百達二KY | C37: 汽車工業 | D37: 168 | E37: 0 | F37: 104.5 | G37: 63.1 | H37: 165.61014 | I37: 1.4430622 | J37: 2025/11/21 | K37: 2025/12/16 | L37: 45156 | M37: 46252 | N37: 100 | O37: 46252 | P37: 100 | Q37: -0.58164604 | R37: -0.58164604 | S37: 0 | T37: 33.67 | U37: 41.19 | V37: - | W37: - | X37: - | Y37: - | Z37: 7 | AA37: 2000 | AB37: 5 | AC37: 0.25 | AD37: 無 | AE37: 生產銷售沖壓機台及汽、機車用件、服務型機器人之銷售及租賃、HDD硬碟內夾取臂製造與組裝
A38: 22471 | B38: 汎德永業一 | C38: 汽車工業 | D38: 106.8 | E38: 10 | F38: 296 | G38: 289.4 | H38: 102.28058 | I38: 4.4186486 | J38: 2025/12/18 | K38: 2026/01/14 | L38: 45834 | M38: 46930 | N38: 100 | O38: 46930 | P38: 100 | Q38: -0.024935301 | R38: -0.024935301 | S38: 3.86 | T38: 24.61 | U38: 25.1 | V38: 8 | W38: 7 | X38: 0 | Y38: 0 | Z38: 4 | AA38: 10000 | AB38: 10000 | AC38: 100 | AD38: 無 | AE38: 汽車零售業務、汽、機車零件配備零售業務、汽車修理業務
A39: 22472 | B39: 汎德永業二 | C39: 汽車工業 | D39: 108.75 | E39: 14 | F39: 296 | G39: 280.2 | H39: 105.63883 | I39: 2.9451014 | J39: 2025/12/18 | K39: 2026/01/14 | L39: 45838 | M39: 46934 | N39: 100 | O39: 46934 | P39: 100 | Q39: -0.031375872 | R39: -0.031375872 | S39: 3.86 | T39: 24.61 | U39: 25.1 | V39: 6 | W39: 6 | X39: 0 | Y39: 0 | Z39: 4 | AA39: 10000 | AB39: 10000 | AC39: 100 | AD39: 無 | AE39: 汽車零售業務、汽、機車零件配備零售業務、汽車修理業務
A40: 23372 | B40: 旺宏二 | C40: 電子–半導體 | D40: 148.1 | E40: 31 | F40: 33.9 | G40: 23 | H40: 147.3913 | I40: 0.48082596 | J40: - | K40: - | L40: 45740 | M40: 46836 | N40: 100 | O40: 46836 | P40: 100 | Q40: -0.1414617 | R40: -0.1414617 | S40: -0.47 | T40: 57.85 | U40: 53.71 | V40: 25 | W40: 24 | X40: 0 | Y40: 0 | Z40: 5 | AA40: 30000 | AB40: 15099 | AC40: 50.33 | AD40: 無 | AE40: 積體電路、各種半導體零組件，及其系統應用產品之、研究發展、設計、製造、測試、銷售及顧問諮詢
A41: 23383 | B41: 光罩三 | C41: 電子–半導體 | D41: 97.3 | E41: 0 | F41: 35.4 | G41: 74.5 | H41: 47.516779 | I41: 104.76977 | J41: - | K41: - | L41: 44411 | M41: 46237 | N41: 100 | O41: 46237 | P41: 100 | Q41: 0.04237853 | R41: 0.04237853 | S41: -0.62 | T41: 50.13 | U41: 49.14 | V41: - | W41: - | X41: - | Y41: - | Z41: 9 | AA41: 20000 | AB41: 979 | AC41: 4.89 | AD41: 無 | AE41: 光罩之研究發展製造及銷售、提供有關前述產品之技術協助諮詢檢驗維修與修理服務
A42: 23511 | B42: 順德一 | C42: 電子–半導體 | D42: 125 | E42: 0 | F42: 78.5 | G42: 72.4 | H42: 108.42541 | I42: 15.286624 | J42: - | K42: - | L42: 45825 | M42: 46921 | N42: 100 | O42: 46921 | P42: 100 | Q42: -0.079089924 | R42: -0.079089924 | S42: 0.48 | T42: 44.96 | U42: 45.55 | V42: - | W42: - | X42: - | Y42: - | Z42: 5 | AA42: 12000 | AB42: 12000 | AC42: 100 | AD42: 無 | AE42: 半導體導線架、五金文具用品、模具及其他
A43: 23682 | B43: 金像電二 | C43: 電子–電子零組件 | D43: 280 | E43: 18 | F43: 596 | G43: 214 | H43: 278.50467 | I43: 0.53691275 | J43: - | K43: - | L43: 45265 | M43: 46361 | N43: 100 | O43: 47092 | P43: 100 | Q43: -0.64639906 | R43: -0.21448159 | S43: 6.49 | T43: 54.35 | U43: 56.18 | V43: 7 | W43: 18 | X43: 0 | Y43: 0 | Z43: 3 | AA43: 40000 | AB43: 3221 | AC43: 8.05 | AD43: 無 | AE43: 雙層、多層印刷電路板之製造加工及買賣業務、各種電腦、電子、通訊、資訊產品及其週邊設備與電子零件、加工
A44: 23683 | B44: 金像電三 | C44: 電子–電子零組件 | D44: 147.5 | E44: 673 | F44: 596 | G44: 450 | H44: 132.44444 | I44: 11.36745 | J44: - | K44: - | L44: 45985 | M44: 47081 | N44: 100 | O44: 47811 | P44: 100 | Q44: -0.10853405 | R44: -0.064833079 | S44: 6.49 | T44: 54.35 | U44: 56.18 | V44: 393 | W44: 270 | X44: 0 | Y44: 0 | Z44: 3 | AA44: 90000 | AB44: 90000 | AC44: 100 | AD44: 無 | AE44: 雙層、多層印刷電路板之製造加工及買賣業務、各種電腦、電子、通訊、資訊產品及其週邊設備與電子零件、加工
A45: 24023 | B45: 毅嘉三 | C45: 電子–電子零組件 | D45: 117 | E45: 113 | F45: 51.7 | G45: 55 | H45: 94 | I45: 24.468085 | J45: - | K45: - | L45: 45980 | M45: 46710 | N45: 100 | O45: 47076 | P45: 100 | Q45: -0.074486219 | R45: -0.049196835 | S45: 0.6 | T45: 44.64 | U45: 42.89 | V45: 110 | W45: 72 | X45: 0 | Y45: 0 | Z45: 5 | AA45: 10000 | AB45: 10000 | AC45: 100 | AD45: 無 | AE45: 各種電子塑膠、矽膠字鍵、鍵盤及其組裝、軟性電路版及其組裝、智慧財產權業
A46: 24271 | B46: 三商電一 | C46: 電子–資訊服務 | D46: 108.1 | E46: 0 | F46: 27.9 | G46: 26.3 | H46: 106.08365 | I46: 1.9007168 | J46: - | K46: - | L46: 45273 | M46: 46369 | N46: 101.51 | O46: 47100 | P46: 100 | Q46: -0.059976163 | R46: -0.024818218 | S46: 0.26 | T46: 37.24 | U46: 42.68 | V46: - | W46: - | X46: - | Y46: - | Z46: 7 | AA46: 5000 | AB46: 4684 | AC46: 93.68 | AD46: 無 | AE46: 金融自動化服務機器之銷售、租賃及維護、系統整合業務之軟、硬體規劃、開發建置及維護
A47: 24361 | B47: 偉詮電一 | C47: 電子–半導體 | D47: 108.6 | E47: 5 | F47: 45.8 | G47: 53.3 | H47: 85.928705 | I47: 26.383843 | J47: - | K47: - | L47: 45180 | M47: 46276 | N47: 100 | O47: 46276 | P47: 100 | Q47: -0.10397207 | R47: -0.10397207 | S47: 1.14 | T47: 40.21 | U47: 43.46 | V47: 5 | W47: 5 | X47: 0 | Y47: 0 | Z47: 5 | AA47: 11000 | AB47: 10999 | AC47: 99.99 | AD47: 無 | AE47: 研發生產銷售數位類比混合式特殊應用IC、研發生產銷售數位式積體電路、類比式IC、兼營與本公司業務相關之進出口貿易業務
A48: 24394 | B48: 美律四 | C48: 電子–通信網路 | D48: 106 | E48: 0 | F48: 100.5 | G48: 128.9 | H48: 77.967417 | I48: 35.954229 | J48: - | K48: - | L48: 45483 | M48: 46578 | N48: 100 | O48: 46578 | P48: 100 | Q48: -0.03562134 | R48: -0.03562134 | S48: 2.33 | T48: 23.74 | U48: 32.88 | V48: - | W48: - | X48: - | Y48: - | Z48: 3 | AA48: 25000 | AB48: 25000 | AC48: 100 | AD48: 無 | AE48: 娛樂性產品、揚聲器、電池產品、免持聽筒、及其他電子零件
A49: 24395 | B49: 美律五 | C49: 電子–通信網路 | D49: 106.9 | E49: 1 | F49: 100.5 | G49: 125.2 | H49: 80.271565 | I49: 33.172935 | J49: - | K49: - | L49: 45495 | M49: 46590 | N49: 100 | O49: 46590 | P49: 100 | Q49: -0.039796286 | R49: -0.039796286 | S49: 2.33 | T49: 23.74 | U49: 32.88 | V49: 1 | W49: 0 | X49: 0 | Y49: 0 | Z49: 3 | AA49: 5000 | AB49: 5000 | AC49: 100 | AD49: 無 | AE49: 娛樂性產品、揚聲器、電池產品、免持聽筒、及其他電子零件
A50: 24423 | B50: 新美齊三 | C50: 建材營建 | D50: 100.55 | E50: 1 | F50: 25.4 | G50: 25.6 | H50: 99.21875 | I50: 1.3417323 | J50: - | K50: - | L50: 45625 | M50: 46355 | N50: 100.5 | O50: 46720 | P50: 100 | Q50: -0.00050840824 | R50: -0.002765262 | S50: 0.12 | T50: 27.3 | U50: 33.14 | V50: 1 | W50: 0 | X50: 0 | Y50: 0 | Z50: 7 | AA50: 10000 | AB50: 9001 | AC50: 90.01 | AD50: 無 | AE50: 不動產買賣、租賃及營建開發、不動產買賣、租賃及營建開發
A51: 24424 | B51: 新美齊四 | C51: 建材營建 | D51: 99.05 | E51: 0 | F51: 25.4 | G51: 25.9 | H51: 98.069498 | I51: 0.99980315 | J51: - | K51: - | L51: 45651 | M51: 46381 | N51: 100.5 | O51: 46746 | P51: 100 | Q51: 0.013951073 | R51: 0.0046801567 | S51: 0.12 | T51: 27.3 | U51: 33.14 | V51: - | W51: - | X51: - | Y51: - | Z51: 7 | AA51: 6000 | AB51: 5928 | AC51: 98.8 | AD51: 無 | AE51: 不動產買賣、租賃及營建開發、不動產買賣、租賃及營建開發
A52: 24616 | B52: 光群雷六 | C52: 電子–其他電子 | D52: 140 | E52: 0 | F52: 15.5 | G52: 14.5 | H52: 106.89655 | I52: 30.967742 | J52: - | K52: - | L52: 44279 | M52: 46105 | N52: 100 | O52: 46105 | P52: 100 | Q52: -0.97463284 | R52: -0.97463284 | S52: 0.1 | T52: 17.06 | U52: 29.68 | V52: - | W52: - | X52: - | Y52: - | Z52: 6 | AA52: 6000 | AB52: 2561 | AC52: 42.68 | AD52: 有，台中商業銀行股份有限公司 | AE52: 全像術及光電相關產品
A53: 24624 | B53: 良得電四 | C53: 電子–電子零組件 | D53: 103.9 | E53: 0 | F53: 22.05 | G53: 30.09 | H53: 73.28016 | I53: 41.784626 | J53: - | K53: - | L53: 45149 | M53: 46245 | N53: 100 | O53: 46245 | P53: 100 | Q53: -0.055468315 | R53: -0.055468315 | S53: 0.54 | T53: 41.23 | U53: 39.89 | V53: - | W53: - | X53: - | Y53: - | Z53: 6 | AA53: 4000 | AB53: 2443 | AC53: 61.07 | AD53: 無 | AE53: 電腦系統及電器類電源傳輸線組資訊週邊產品訊號聯結線、通訊系統高效連接線組智能電動車充電線纜
A54: 24642 | B54: 盟立二 | C54: 電子–其他電子 | D54: 104.8 | E54: 40 | F54: 61.1 | G54: 78.5 | H54: 77.834395 | I54: 34.644845 | J54: - | K54: - | L54: 45551 | M54: 46281 | N54: 100.5 | O54: 46646 | P54: 100 | Q54: -0.05291924 | R54: -0.025798699 | S54: 0.01 | T54: 36.19 | U54: 43.04 | V54: 32 | W54: 2 | X54: 0 | Y54: 0 | Z54: 6 | AA54: 10000 | AB54: 9803 | AC54: 98.03 | AD54: 無 | AE54: 設計開發生產製造及銷售下列產品:自動化設備系統及其零組件、電腦控制設備及系統，醫療器材及其自動化生產設備，立體停車設備、前項產品工程之規劃安裝，技術咨詢顧問，維修及租賃
A55: 24762 | B55: 鉅祥二 | C55: 電子–電子零組件 | D55: 134 | E55: 0 | F55: 86.5 | G55: 66.5 | H55: 130.07519 | I55: 3.017341 | J55: - | K55: - | L55: 45317 | M55: 46413 | N55: 100 | O55: 46413 | P55: 100 | Q55: -0.2231613 | R55: -0.2231613 | S55: 1.61 | T55: 35.35 | U55: 39.16 | V55: - | W55: - | X55: - | Y55: - | Z55: 4 | AA55: 10000 | AB55: 3895 | AC55: 38.95 | AD55: 無 | AE55: 連續沖壓精密金屬零件與連續沖壓模具、機械零組件、刀具、夾具、自動化專用機
A56: 24866 | B56: 一詮六 | C56: 電子–光電 | D56: 106.1 | E56: 0 | F56: 96.9 | G56: 125.2 | H56: 77.396166 | I56: 37.086894 | J56: - | K56: - | L56: 45474 | M56: 46204 | N56: 101.0025 | O56: 46569 | P56: 100 | Q56: -0.085127033 | R56: -0.036751173 | S56: 0.22 | T56: 44.92 | U56: 50.81 | V56: - | W56: - | X56: - | Y56: - | Z56: 6 | AA56: 6000 | AB56: 6000 | AC56: 100 | AD56: 無 | AE56: 散熱元件32.81%、導線架28.27%、陶瓷電路板14.71%、TV背光模組10.1%、智能服務機器人8.26%(LED及SMD導線架、直下式電視背光模組、散熱片及IC導線架、其他電子零組件)
A57: 25283 | B57: 皇普三 | C57: 建材營建 | D57: 107.5 | E57: 0 | F57: 30.2 | G57: 42.4 | H57: 71.226415 | I57: 50.927152 | J57: - | K57: - | L57: 45657 | M57: 46752 | N57: 100.752 | O57: 47483 | P57: 102.53 | Q57: -0.030387021 | R57: -0.011363558 | S57: 1.58 | T57: 27.59 | U57: 35.25 | V57: - | W57: - | X57: - | Y57: - | Z57: 8 | AA57: 6000 | AB57: 6000 | AC57: 100 | AD57: 有，元大商業銀行股份有限公司 | AE57: 委託營造廠商興建商業大樓及國民住宅出租、出售業務、投資興闢都市計劃範圍內之停車場、餐廳、咖啡廳、旅館業務之經營
A58: 25284 | B58: 皇普四 | C58: 建材營建 | D58: 92.15 | E58: 0 | F58: 30.2 | G58: 41 | H58: 73.658537 | I58: 25.104305 | J58: - | K58: - | L58: 45674 | M58: 46769 | N58: 101.508 | O58: 47500 | P58: 102.53 | Q58: 0.048075763 | R58: 0.027373161 | S58: 1.58 | T58: 27.59 | U58: 35.25 | V58: - | W58: - | X58: - | Y58: - | Z58: 8 | AA58: 5000 | AB58: 5000 | AC58: 100 | AD58: 無 | AE58: 委託營造廠商興建商業大樓及國民住宅出租、出售業務、投資興闢都市計劃範圍內之停車場、餐廳、咖啡廳、旅館業務之經營
A59: 25303 | B59: 華建三 | C59: 建材營建 | D59: 93.95 | E59: 7 | F59: 28.45 | G59: 33.1 | H59: 85.951662 | I59: 9.3056239 | J59: 2025/11/20 | K59: 2025/12/15 | L59: 45831 | M59: 46561 | N59: 100.5 | O59: 46927 | P59: 100 | Q59: 0.045199017 | R59: 0.025300887 | S59: 0.82 | T59: 25.94 | U59: 29.91 | V59: - | W59: - | X59: - | Y59: - | Z59: 7 | AA59: 5000 | AB59: 5000 | AC59: 100 | AD59: 無 | AE59: 委託營造廠商興建商業大樓出租出售業務、委託營造廠商興建國民住宅出租出售業務、房屋租售之介紹業務
A60: 25304 | B60: 華建四 | C60: 建材營建 | D60: 97.05 | E60: 6 | F60: 28.45 | G60: 31 | H60: 91.774194 | I60: 5.7486819 | J60: 2025/11/20 | K60: 2025/12/15 | L60: 45838 | M60: 46568 | N60: 100.5 | O60: 46934 | P60: 100 | Q60: 0.022763632 | R60: 0.011853415 | S60: 0.82 | T60: 25.94 | U60: 29.91 | V60: - | W60: - | X60: - | Y60: - | Z60: 7 | AA60: 8000 | AB60: 7607 | AC60: 95.08 | AD60: 無 | AE60: 委託營造廠商興建商業大樓出租出售業務、委託營造廠商興建國民住宅出租出售業務、房屋租售之介紹業務
A61: 25483 | B61: 華固三 | C61: 建材營建 | D61: 101.7 | E61: 63 | F61: 104.5 | G61: 125 | H61: 83.6 | I61: 21.650718 | J61: - | K61: - | L61: 45567 | M61: 46662 | N61: 100 | O61: 47393 | P61: 100 | Q61: -0.0091886721 | R61: -0.0043736762 | S61: 1.1 | T61: 24.32 | U61: 30.98 | V61: 23 | W61: 33 | X61: 0 | Y61: 0 | Z61: 4 | AA61: 40000 | AB61: 40000 | AC61: 100 | AD61: 無 | AE61: 委託營造廠商興建商業大樓、國民住宅及廠辦之出租及出售、室內裝潢業務及建材機械買賣及進出口貿易業務、委託營造廠興建一般工業用地之廠房倉庫出租等業務
A62: 25484 | B62: 華固四 | C62: 建材營建 | D62: 103.75 | E62: 0 | F62: 104.5 | G62: 123.5 | H62: 84.615385 | I62: 22.613636 | J62: - | K62: - | L62: 45583 | M62: 46678 | N62: 100 | O62: 47409 | P62: 100 | Q62: -0.019401134 | R62: -0.0093499441 | S62: 1.1 | T62: 24.32 | U62: 30.98 | V62: - | W62: - | X62: - | Y62: - | Z62: 4 | AA62: 20000 | AB62: 20000 | AC62: 100 | AD62: 無 | AE62: 委託營造廠商興建商業大樓、國民住宅及廠辦之出租及出售、室內裝潢業務及建材機械買賣及進出口貿易業務、委託營造廠興建一般工業用地之廠房倉庫出租等業務
A63: 26107 | B63: 華航七 | C63: 航運業 | D63: 117.2 | E63: 0 | F63: 18.75 | G63: 16.9 | H63: 110.94675 | I63: 5.6362667 | J63: - | K63: - | L63: 44314 | M63: 46140 | N63: 100 | O63: 46140 | P63: 100 | Q63: -0.37722925 | R63: -0.37722925 | S63: 0.49 | T63: 16.97 | U63: 28.96 | V63: - | W63: - | X63: - | Y63: - | Z63: 4 | AA63: 45000 | AB63: 10349 | AC63: 22.99 | AD63: 無 | AE63: 客運收入60.67%、貨運收入30.64%、其他收入8.69%(客運、貨運、郵運、代理業務(包括營業、運務)及代理修護、倉儲業務之經營)
A64: 26417 | B64: 正德七 | C64: 航運業 | D64: 102.2 | E64: 1 | F64: 21.55 | G64: 22.15 | H64: 97.291196 | I64: 5.0454756 | J64: - | K64: - | L64: 45499 | M64: 46594 | N64: 100 | O64: 46594 | P64: 100 | Q64: -0.013183126 | R64: -0.013183126 | S64: 0.62 | T64: 30.69 | U64: 39.17 | V64: - | W64: - | X64: - | Y64: - | Z64: 6 | AA64: 5900 | AB64: 5767 | AC64: 97.74 | AD64: 無 | AE64: 船務代理業、海運承攬運送業、其他顧問服務業
A65: 26418 | B65: 正德八 | C65: 航運業 | D65: 111.25 | E65: 139 | F65: 21.55 | G65: 19.3 | H65: 111.65803 | I65: -0.36542923 | J65: - | K65: - | L65: 45875 | M65: 46971 | N65: 100.7519 | O65: 47701 | P65: 100 | Q65: -0.035398977 | R65: -0.021673583 | S65: 0.62 | T65: 30.69 | U65: 39.17 | V65: 55 | W65: 38 | X65: 0 | Y65: 0 | Z65: 6 | AA65: 7800 | AB65: 7251 | AC65: 92.96 | AD65: 無 | AE65: 船務代理業、海運承攬運送業、其他顧問服務業
A66: 27271 | B66: 王品一 | C66: 觀光餐旅 | D66: 107 | E66: 0 | F66: 212.5 | G66: 233.4 | H66: 91.045416 | I66: 17.523765 | J66: - | K66: - | L66: 45014 | M66: 46110 | N66: 100.7519 | O66: 46841 | P66: 100 | Q66: -0.19030011 | R66: -0.028325628 | S66: 4.13 | T66: 20.61 | U66: 24.88 | V66: - | W66: - | X66: - | Y66: - | Z66: 4 | AA66: 7000 | AB66: 6999 | AC66: 99.98 | AD66: 無 | AE66: 餐館業
A67: 27323 | B67: 六角三 | C67: 觀光餐旅 | D67: 100.25 | E67: 0 | F67: 74.9 | G67: 124.8 | H67: 60.016026 | I67: 67.038718 | J67: - | K67: - | L67: 45317 | M67: 46048 | N67: 101 | O67: 46413 | P67: 100 | Q67: 0.054613466 | R67: -0.0021933119 | S67: 0.59 | T67: 21.29 | U67: 26.52 | V67: - | W67: - | X67: - | Y67: - | Z67: 5 | AA67: 6000 | AB67: 6000 | AC67: 100 | AD67: 無 | AE67: 經營連鎖餐飲品牌
A68: 27431 | B68: 山富一 | C68: 觀光餐旅 | D68: 104.4 | E68: 0 | F68: 82 | G68: 101.9 | H68: 80.47105 | I68: 29.736098 | J68: - | K68: - | L68: 45897 | M68: 46627 | N68: 101.0025 | O68: 46993 | P68: 100 | Q68: -0.018884313 | R68: -0.015460444 | S68: 1.68 | T68: 34.76 | U68: 47.19 | V68: - | W68: - | X68: - | Y68: - | Z68: 4 | AA68: 3000 | AB68: 3000 | AC68: 100 | AD68: 無 | AE68: 團體、客製化旅遊、機票、訂房、自由行、高鐵假期、企業差旅等、團體旅行包括出境旅遊、入境旅遊、國內旅遊和遊覽車接送服務
A69: 27531 | B69: 八方雲集一 | C69: 觀光餐旅 | D69: 109.5 | E69: 10 | F69: 191.5 | G69: 212 | H69: 90.330189 | I69: 21.221932 | J69: - | K69: - | L69: 45939 | M69: 47035 | N69: 100 | O69: 47035 | P69: 100 | Q69: -0.030536805 | R69: -0.030536805 | S69: 3.53 | T69: 30.78 | U69: 31.2 | V69: 10 | W69: 0 | X69: 0 | Y69: 0 | Z69: 4 | AA69: 8000 | AB69: 8000 | AC69: 100 | AD69: 無 | AE69: 餐飲銷售及連鎖加盟
A70: 27532 | B70: 八方雲集二 | C70: 觀光餐旅 | D70: 110.85 | E70: 0 | F70: 191.5 | G70: 210 | H70: 91.190476 | I70: 21.558747 | J70: - | K70: - | L70: 45950 | M70: 47046 | N70: 100 | O70: 47046 | P70: 100 | Q70: -0.034089892 | R70: -0.034089892 | S70: 3.53 | T70: 30.78 | U70: 31.2 | V70: - | W70: - | X70: - | Y70: - | Z70: 4 | AA70: 2000 | AB70: 2000 | AC70: 100 | AD70: 無 | AE70: 餐飲銷售及連鎖加盟
A71: 27551 | B71: 揚秦一 | C71: 觀光餐旅 | D71: 137.35 | E71: 0 | F71: 121 | G71: 86.7 | H71: 139.56171 | I71: -1.5847521 | J71: - | K71: - | L71: 45672 | M71: 46767 | N71: 100 | O71: 46767 | P71: 100 | Q71: -0.12907094 | R71: -0.12907094 | S71: 1.8 | T71: 32.93 | U71: 36.89 | V71: - | W71: - | X71: - | Y71: - | Z71: 5 | AA71: 2000 | AB71: 1212 | AC71: 60.6 | AD71: 無 | AE71: 連鎖餐飲之經營及相關產品銷售
A72: 27561 | B72: 聯發國際一 | C72: 觀光餐旅 | D72: 115 | E72: 0 | F72: 90.5 | G72: 90.1 | H72: 100.44395 | I72: 14.491713 | J72: - | K72: - | L72: 45442 | M72: 46172 | N72: 101.0025 | O72: 46537 | P72: 100 | Q72: -0.25532671 | R72: -0.088327821 | S72: 1.5 | T72: 39.24 | U72: 39.58 | V72: - | W72: - | X72: - | Y72: - | Z72: 5 | AA72: 3000 | AB72: 2950 | AC72: 98.33 | AD72: 無 | AE72: 經營連鎖餐飲品牌
A73: 29051 | B73: 三商一 | C73: 貿易百貨 | D73: 99.7 | E73: 20 | F73: 16.9 | G73: 19.23 | H73: 87.883515 | I73: 13.445621 | J73: - | K73: - | L73: 44221 | M73: 46047 | N73: 100 | O73: 46047 | P73: 100 | Q73: 0.022414181 | R73: 0.022414181 | S73: 0.59 | T73: 30.88 | U73: 33.32 | V73: 20 | W73: 20 | X73: 0 | Y73: 0 | Z73: 5 | AA73: 23000 | AB73: 2547 | AC73: 11.07 | AD73: 無 | AE73: 壽險62.05%、民生用品17.42%、資訊服務13.31%、餐飲5.16%、其他1.05%(一般投資業、產業控股公司業、)
A74: 29061 | B74: 高林一 | C74: 貿易百貨 | D74: 99.45 | E74: 1 | F74: 13.1 | G74: 16.8 | H74: 77.97619 | I74: 27.538931 | J74: - | K74: - | L74: 45189 | M74: 46285 | N74: 100 | O74: 46285 | P74: 100 | Q74: 0.0070334575 | R74: 0.0070334575 | S74: -0.03 | T74: 13.47 | U74: 22.35 | V74: 1 | W74: 0 | X74: 0 | Y74: 0 | Z74: 5 | AA74: 10000 | AB74: 4600 | AC74: 46 | AD74: 無 | AE74: 國際貿易、進口服飾零售、生技醫療產業
A75: 30061 | B75: 晶豪科一 | C75: 電子–半導體 | D75: 114.95 | E75: 7 | F75: 80 | G75: 83.6 | H75: 95.69378 | I75: 20.12275 | J75: - | K75: - | L75: 45226 | M75: 46322 | N75: 100 | O75: 46322 | P75: 100 | Q75: -0.14651432 | R75: -0.14651432 | S75: 0.05 | T75: 55.36 | U75: 51.34 | V75: 7 | W75: 7 | X75: 0 | Y75: 0 | Z75: 5 | AA75: 10000 | AB75: 9999 | AC75: 99.99 | AD75: 無 | AE75: 積體電路收入100%(動、靜態隨機存取記憶體(DRAM/SRAM)、快閃記憶體(FLASH)、類比積體電路、類比與數位混合積體電路、與本公司業務相關之產品設計及研發之技術服務)
A76: 30134 | B76: 晟銘電四 | C76: 電子–電腦及週邊設備 | D76: 129 | E76: 5 | F76: 133.5 | G76: 143.8 | H76: 92.837274 | I76: 38.952809 | J76: - | K76: - | L76: 45583 | M76: 46678 | N76: 100 | O76: 46678 | P76: 100 | Q76: -0.12066803 | R76: -0.12066803 | S76: 1.06 | T76: 50.29 | U76: 55.73 | V76: 5 | W76: 5 | X76: 0 | Y76: 0 | Z76: 5 | AA76: 5000 | AB76: 5000 | AC76: 100 | AD76: 有，兆豐國際商業銀行股份有限公司、中國信託商業銀行股份有限公司 | AE76: PC、NB、Server、TV及行動產品等機構件與沖壓、射出、組裝、銷售、精密模具設計製造銷售
A77: 30165 | B77: 嘉晶五 | C77: 電子–半導體 | D77: 104 | E77: 0 | F77: 50.9 | G77: 71.4 | H77: 71.288515 | I77: 45.886051 | J77: - | K77: - | L77: 45499 | M77: 46594 | N77: 100 | O77: 46594 | P77: 100 | Q77: -0.023554466 | R77: -0.023554466 | S77: 0.05 | T77: 60.01 | U77: 57.1 | V77: - | W77: - | X77: - | Y77: - | Z77: 6 | AA77: 5000 | AB77: 5000 | AC77: 100 | AD77: 無 | AE77: 矽磊晶、化合物半導體磊晶晶圓之開發、製造與銷售
A78: 30238 | B78: 信邦八 | C78: 電子–電子零組件 | D78: 99.85 | E78: 1 | F78: 216.5 | G78: 259.5 | H78: 83.429672 | I78: 19.68164 | J78: - | K78: - | L78: 44907 | M78: 46003 | N78: 100 | O78: 46003 | P78: 100 | Q78: 0.1096645 | R78: 0.1096645 | S78: 3.05 | T78: 28.95 | U78: 39.25 | V78: - | W78: - | X78: - | Y78: - | Z78: 4 | AA78: 10000 | AB78: 8167 | AC78: 81.67 | AD78: 無 | AE78: 各種電子零件加工、製造及其成品之買賣業務、電腦週邊設備、通訊器材、電腦通訊網路及其零組件之製造加工買賣、代理各種電子零件有關產品之報價經銷
A79: 30321 | B79: 偉訓一 | C79: 電子–電子零組件 | D79: 104 | E79: 11 | F79: 80.1 | G79: 105.9 | H79: 75.637394 | I79: 37.498127 | J79: - | K79: - | L79: 45974 | M79: 46704 | N79: 101.0025 | O79: 47070 | P79: 101.5075 | Q79: -0.014900952 | R79: -0.0081601832 | S79: 0 | T79: 51.84 | U79: 55.58 | V79: 11 | W79: 2 | X79: 0 | Y79: 0 | Z79: 5 | AA79: 10000 | AB79: 10000 | AC79: 100 | AD79: 無 | AE79: 電腦機殼產品、電源供應器等資訊產品
A80: 30322 | B80: 偉訓二 | C80: 電子–電子零組件 | D80: 103.9 | E80: 63 | F80: 80.1 | G80: 101.9 | H80: 78.606477 | I80: 32.177403 | J80: - | K80: - | L80: 45986 | M80: 46716 | N80: 101.0025 | O80: 47812 | P80: 100 | Q80: -0.014176738 | R80: -0.0075527419 | S80: 0 | T80: 51.84 | U80: 55.58 | V80: 58 | W80: 18 | X80: 0 | Y80: 0 | Z80: 5 | AA80: 10000 | AB80: 10000 | AC80: 100 | AD80: 無 | AE80: 電腦機殼產品、電源供應器等資訊產品
A81: 30336 | B81: 威健六 | C81: 電子–電子通路 | D81: 127.1 | E81: 0 | F81: 30.1 | G81: 24.84 | H81: 121.17552 | I81: 4.8891694 | J81: - | K81: - | L81: 44713 | M81: 46174 | N81: 102 | O81: 46539 | P81: 100 | Q81: -0.40955136 | R81: -0.14385314 | S81: 0.69 | T81: 22.08 | U81: 24.83 | V81: - | W81: - | X81: - | Y81: - | Z81: 6 | AA81: 20000 | AB81: 4359 | AC81: 21.79 | AD81: 無 | AE81: 電子零組件暨周邊設備之代理銷售
A82: 30337 | B82: 威健七 | C82: 電子–電子通路 | D82: 103.6 | E82: 4 | F82: 30.1 | G82: 34.44 | H82: 87.398374 | I82: 18.537674 | J82: - | K82: - | L82: 45546 | M82: 46641 | N82: 100 | O82: 47372 | P82: 100 | Q82: -0.019725346 | R82: -0.0092310027 | S82: 0.69 | T82: 22.08 | U82: 24.83 | V82: 2 | W82: 0 | X82: 0 | Y82: 0 | Z82: 6 | AA82: 25000 | AB82: 25000 | AC82: 100 | AD82: 無 | AE82: 電子零組件暨周邊設備之代理銷售
A83: 30371 | B83: 欣興一 | C83: 電子–電子零組件 | D83: 145.5 | E83: 1132 | F83: 215 | G83: 165.4 | H83: 129.98791 | I83: 11.933488 | J83: - | K83: - | L83: 45964 | M83: 47060 | N83: 100 | O83: 47790 | P83: 100 | Q83: -0.1074773 | R83: -0.063694695 | S83: 1.44 | T83: 54.14 | U83: 54.57 | V83: 592 | W83: 740 | X83: 0 | Y83: 0 | Z83: 4 | AA83: 40000 | AB83: 40000 | AC83: 100 | AD83: 無 | AE83: PCB製造
A84: 30401 | B84: 遠見一 | C84: 其他 | D84: 135.8 | E84: 356 | F84: 63.4 | G84: 47.2 | H84: 134.32203 | I84: 1.1003155 | J84: - | K84: - | L84: 45838 | M84: 46568 | N84: 102.01 | O84: 46934 | P84: 100 | Q84: -0.15933326 | R84: -0.10280169 | S84: -0.08 | T84: 47.58 | U84: 48.1 | V84: 33 | W84: 339 | X84: 0 | Y84: 0 | Z84: 6 | AA84: 5000 | AB84: 3668 | AC84: 73.36 | AD84: 無 | AE84: 租賃服務收入、教育相關電子產品及軟件
A85: 30454 | B85: 台灣大四 | C85: 電子–通信網路 | D85: 98.6 | E85: 94 | F85: 105 | G85: 118.2 | H85: 88.832487 | I85: 10.995429 | J85: - | K85: - | L85: 45712 | M85: 46807 | N85: 100 | O85: 47538 | P85: 100 | Q85: 0.0064061258 | R85: 0.003365296 | S85: 1.19 | T85: 14.68 | U85: 15.49 | V85: 93 | W85: 0 | X85: 0 | Y85: 0 | Z85: 2 | AA85: 70000 | AB85: 70000 | AC85: 100 | AD85: 無 | AE85: 電信50.78%、零售相關服務49.91%、有線電視及寬頻3.15%、其他0.38%(通訊業)
A86: 30455 | B86: 台灣大五 | C86: 電子–通信網路 | D86: 100.7 | E86: 120 | F86: 105 | G86: 111.3 | H86: 94.339623 | I86: 6.742 | J86: - | K86: - | L86: 45713 | M86: 46808 | N86: 100 | O86: 47539 | P86: 100 | Q86: -0.0031323942 | R86: -0.0016464889 | S86: 1.19 | T86: 14.68 | U86: 15.49 | V86: 116 | W86: 33 | X86: 0 | Y86: 0 | Z86: 2 | AA86: 30000 | AB86: 30000 | AC86: 100 | AD86: 無 | AE86: 電信50.78%、零售相關服務49.91%、有線電視及寬頻3.15%、其他0.38%(通訊業)
A87: 30882 | B87: 艾訊二 | C87: 電子–電腦及週邊設備 | D87: 107.55 | E87: 0 | F87: 76 | G87: 88.5 | H87: 85.875706 | I87: 25.239145 | J87: - | K87: - | L87: 45166 | M87: 46262 | N87: 100 | O87: 46262 | P87: 100 | Q87: -0.09705669 | R87: -0.09705669 | S87: 1.81 | T87: 25.23 | U87: 41.07 | V87: - | W87: - | X87: - | Y87: - | Z87: 5 | AA87: 8000 | AB87: 3686 | AC87: 46.07 | AD87: 無 | AE87: 智能物聯網產品、智能設計服務產品、博奕產品
A88: 30922 | B88: 鴻碩二 | C88: 電子–電子零組件 | D88: 96.6 | E88: 13 | F88: 14.95 | G88: 36 | H88: 41.527778 | I88: 132.61538 | J88: - | K88: - | L88: 45111 | M88: 46207 | N88: 100 | O88: 46207 | P88: 100 | Q88: 0.061467899 | R88: 0.061467899 | S88: -1.09 | T88: 40.8 | U88: 41.79 | V88: 0 | W88: 13 | X88: 0 | Y88: 0 | Z88: 9 | AA88: 2500 | AB88: 463 | AC88: 18.52 | AD88: 無 | AE88: 連接線99.38%、不動產租賃0.62%(製造、銷售各種電腦訊號線，連接器，連接線)
A89: 30954 | B89: 及成四 | C89: 電子–通信網路 | D89: 107 | E89: 0 | F89: 28.5 | G89: 41.1 | H89: 69.343066 | I89: 54.305263 | J89: - | K89: - | L89: 45713 | M89: 46443 | N89: 100 | O89: 46808 | P89: 100 | Q89: -0.053659561 | R89: -0.029479635 | S89: -0.14 | T89: 47.71 | U89: 51.05 | V89: - | W89: - | X89: - | Y89: - | Z89: 9 | AA89: 1500 | AB89: 1500 | AC89: 100 | AD89: 有，陽信商業銀行股份有限公司 | AE89: 各種精密五金、塑膠電子零組件、精密嵌件(INSERTPARTS)之產製、五金模具、塑膠模具之設計、製造、上述相關材料之加工及買賣
A90: 31222 | B90: 笙泉二 | C90: 電子–半導體 | D90: 99 | E90: 0 | F90: 22.3 | G90: 42.3 | H90: 52.718676 | I90: 87.789238 | J90: - | K90: - | L90: 45415 | M90: 46145 | N90: 101.0025 | O90: 46510 | P90: 101.5075 | Q90: 0.050224181 | R90: 0.018056295 | S90: -0.39 | T90: 49.65 | U90: 49.33 | V90: - | W90: - | X90: - | Y90: - | Z90: 6 | AA90: 2000 | AB90: 1991 | AC90: 99.55 | AD90: 無 | AE90: 研發、設計及銷售各種積體電路
A91: 31282 | B91: 昇銳二 | C91: 電子–光電 | D91: 97.3 | E91: 0 | F91: 26.85 | G91: 37.8 | H91: 71.031746 | I91: 36.981006 | J91: - | K91: - | L91: 45110 | M91: 46206 | N91: 100 | O91: 46206 | P91: 100 | Q91: 0.048694561 | R91: 0.048694561 | S91: 0.36 | T91: 52.75 | U91: 60.23 | V91: - | W91: - | X91: - | Y91: - | Z91: 7 | AA91: 3000 | AB91: 1083 | AC91: 36.1 | AD91: 無 | AE91: 各種電子監視系統之製造加工、各種電子監視系統及其另件之買賣及安裝業務、前項有關產品及其原材料之進出口業務
A92: 31311 | B92: 弘塑一 | C92: 電子–其他電子 | D92: 117 | E92: 64 | F92: 1365 | G92: 1736.5 | H92: 78.606392 | I92: 48.842857 | J92: - | K92: - | L92: 45868 | M92: 46964 | N92: 100 | O92: 47694 | P92: 100 | Q92: -0.054900816 | R92: -0.031270158 | S92: 10.4 | T92: 56.97 | U92: 61.21 | V92: 62 | W92: 62 | X92: 0 | Y92: 0 | Z92: 5 | AA92: 10000 | AB92: 10000 | AC92: 100 | AD92: 無 | AE92: 半導體及積體電路製造設備之工程承包、製造、買賣及維修工程、化學品：工業級、試藥級、電子級混酸（蝕刻液）、電鑄藥液、半導體相關之機械安裝、電子零組件製造
A93: 31312 | B93: 弘塑二 | C93: 電子–其他電子 | D93: 121.2 | E93: 31 | F93: 1365 | G93: 1626.6 | H93: 83.917374 | I93: 44.42778 | J93: - | K93: - | L93: 45874 | M93: 46970 | N93: 100 | O93: 47700 | P93: 100 | Q93: -0.065684038 | R93: -0.037511683 | S93: 10.4 | T93: 56.97 | U93: 61.21 | V93: 21 | W93: 31 | X93: 0 | Y93: 0 | Z93: 5 | AA93: 10000 | AB93: 10000 | AC93: 100 | AD93: 無 | AE93: 半導體及積體電路製造設備之工程承包、製造、買賣及維修工程、化學品：工業級、試藥級、電子級混酸（蝕刻液）、電鑄藥液、半導體相關之機械安裝、電子零組件製造
A94: 31351 | B94: 凌航一 | C94: 電子–半導體 | D94: 121 | E94: 35 | F94: 67.3 | G94: 52.19 | H94: 128.95191 | I94: -6.1665676 | J94: - | K94: - | L94: 45995 | M94: 46725 | N94: 102.01 | O94: 47091 | P94: 100 | Q94: -0.078794889 | R94: -0.057957097 | S94: 1.05 | T94: 0 | U94: 0 | V94: 1 | W94: 1 | X94: 0 | Y94: 0 | Z94: 6 | AA94: 10000 | AB94: 10000 | AC94: 100.00 | AD94: 無 | AE94: 電子零組件製造業、資訊軟體服務業、國際貿易業務
A95: 31382 | B95: 耀登二 | C95: 電子–通信網路 | D95: 106 | E95: 0 | F95: 87.2 | G95: 114.7 | H95: 76.024412 | I95: 39.428899 | J95: - | K95: - | L95: 45667 | M95: 46762 | N95: 100 | O95: 46762 | P95: 100 | Q95: -0.027042379 | R95: -0.027042379 | S95: 1.24 | T95: 32.13 | U95: 41.47 | V95: - | W95: - | X95: - | Y95: - | Z95: 6 | AA95: 7000 | AB95: 7000 | AC95: 100 | AD95: 無 | AE95: 射頻應用產品之天線研發製造及相關進出口貿易業務、人體手持、穿戴與植入系統的安全性與電磁相容之評估服務、代理精密量測儀器及國內外廠商產品之投標報價經銷業務
A96: 31413 | B96: 晶宏三 | C96: 電子–半導體 | D96: 100 | E96: 0 | F96: 51.6 | G96: 93.6 | H96: 55.128205 | I96: 81.395349 | J96: - | K96: - | L96: 45432 | M96: 46162 | N96: 100 | O96: 46527 | P96: 100 | Q96: 0 | R96: 0 | S96: 0.38 | T96: 43.41 | U96: 43.3 | V96: - | W96: - | X96: - | Y96: - | Z96: 6 | AA96: 8000 | AB96: 8000 | AC96: 100 | AD96: 無 | AE96: LCD驅動IC之設計與產銷
A97: 31672 | B97: 大量二 | C97: 電機機械 | D97: 136 | E97: 88 | F97: 221 | G97: 169.1 | H97: 130.6919 | I97: 4.0615385 | J97: - | K97: - | L97: 45875 | M97: 46971 | N97: 100 | O97: 46971 | P97: 100 | Q97: -0.099298712 | R97: -0.099298712 | S97: 2.44 | T97: 69.81 | U97: 65.6 | V97: 33 | W97: 78 | X97: 0 | Y97: 0 | Z97: 6 | AA97: 5000 | AB97: 5000 | AC97: 100 | AD97: 無 | AE97: 各種機器之設計製造加工及買賣、各種模具之設計製造加工及買賣、上項有關業務之進出口貿易業務
A98: 31882 | B98: 鑫龍騰二 | C98: 建材營建 | D98: 100 | E98: 6 | F98: 31 | G98: 31.4 | H98: 98.726115 | I98: 1.2903226 | J98: - | K98: - | L98: 45828 | M98: 46558 | N98: 102.01 | O98: 46924 | P98: 100 | Q98: 0.013100893 | R98: 0 | S98: 2.58 | T98: 25.79 | U98: 34.72 | V98: - | W98: - | X98: - | Y98: - | Z98: 7 | AA98: 6000 | AB98: 6000 | AC98: 100 | AD98: 無 | AE98: 住宅及大樓開發租售業、建材批發業、一般廣告服務業
A99: 32071 | B99: 耀勝一 | C99: 電子–電子零組件 | D99: 100.2 | E99: 0 | F99: 67.2 | G99: 100.99 | H99: 66.541242 | I99: 50.583304 | J99: - | K99: - | L99: 45376 | M99: 46106 | N99: 102.01 | O99: 46471 | P99: 100 | Q99: 0.061049198 | R99: -0.0015402599 | S99: -0.05 | T99: 38.11 | U99: 47.17 | V99: - | W99: - | X99: - | Y99: - | Z99: 7 | AA99: 5000 | AB99: 4871 | AC99: 97.42 | AD99: 無 | AE99: 電視/伺服器/工業用/Inverter/汽機車/綠能等各式變壓器與線圈
A100: 32571 | B100: 虹冠電一 | C100: 電子–半導體 | D100: 112 | E100: 0 | F100: 61.4 | G100: 72.2 | H100: 85.041551 | I100: 31.700326 | J100: - | K100: - | L100: 45597 | M100: 46692 | N100: 101.5075 | O100: 47423 | P100: 100 | Q100: -0.049271337 | R100: -0.027443609 | S100: 1.12 | T100: 44.91 | U100: 50.58 | V100: - | W100: - | X100: - | Y100: - | Z100: 6 | AA100: 5000 | AB100: 5000 | AC100: 100 | AD100: 無 | AE100: 功率積體電路(PowerIC)、電源模組(PowerModule)、場效電晶體(MOSFET)
...

Sheet 10_最新動態每週餘額表
A1: 證券代號 | B1: 證券名稱 | C1: 本週股額 | D1: 上週股額 | E1: 增減數額 | F1: 增減比率 | G1: 發行比率(剩餘比率) | H1: 45996
A2: 11011 | B2: 台泥一永 | C2: 80000 | D2: 80000 | E2: 0 | F2: 0 | G2: 100
A3: 12561 | B3: 鮮活果汁一KY | C3: 2000 | D3: 2000 | E3: 0 | F3: 0 | G3: 100
A4: 13164 | B4: 上曜四 | C4: 1340 | D4: 1340 | E4: 0 | F4: 0 | G4: 33.5
A5: 13166 | B5: 上曜六 | C5: 4000 | D5: 4000 | E5: 0 | F5: 0 | G5: 100
A6: 13382 | B6: 廣華二KY | C6: 6000 | D6: 6000 | E6: 0 | F6: 0 | G6: 100
A7: 140201 | B7: 遠東新E1永 | C7: 10000 | D7: 10000 | E7: 0 | F7: 0 | G7: 100
A8: 140202 | B8: 遠東新E2永 | C8: 14992 | D8: 14992 | E8: 0 | F8: 0 | G8: 99.94
A9: 14363 | B9: 華友聯三 | C9: 6000 | D9: 6000 | E9: 0 | F9: 0 | G9: 100
A10: 14364 | B10: 華友聯四 | C10: 20000 | D10: 20000 | E10: 0 | F10: 0 | G10: 100
A11: 14381 | B11: 三地開發一 | C11: 9700 | D11: 9700 | E11: 0 | F11: 0 | G11: 100
A12: 14664 | B12: 聚隆四 | C12: 4000 | D12: 4000 | E12: 0 | F12: 0 | G12: 100
A13: 14722 | B13: 三洋實業二 | C13: 3000 | D13: 3000 | E13: 0 | F13: 0 | G13: 100
... A342: 99588 | B342: 世紀鋼八永 | C342: 20000 | D342: 20000 | E342: 0 | F342: 0 | G342: 100

Sheet 11_最新動態CBAS報價表
A1: 可轉債名稱 | B1: 可轉債代碼 | C1: 擔保銀行/信用評等(TCRI) | D1: 權利金(佰元報價) | E1: 選擇權到期日 | F1: 賣回價格(A) | G1: 賣回日期(B) | H1: 剩餘年期 | I1: 折現率(C) | J1: 權利金參考價 | K1: 現股參考價 | L1: 轉換價格 | M1: CB轉換價值 | N1: CB參考價 | O1: 溢(折)價% | P1: 股價波動率120天% | Q1: 股價波動率240天% | R1: 流通餘額占發行總額% | S1: 原始發行量 | T1: 產業
A3: 台泥一永 | B3: 11011 | C3: twA+ | D3: 6.32 | E3: 46717 | F3: 100 | G3: 46731 | H3: 2.0054795 | I3: 0.03 | J3: 3.32 | K3: 22.8 | L3: 35.2 | M3: 64.772727 | N3: 97 | O3: 49.754386 | P3: 24.87 | Q3: 25.5 | R3: 100 | S3: 8000000000 | T3: 水泥工業
A4: 上曜四 | B4: 13164 | C4: 富邦銀 | D4: 0.62 | E4: 46037 | F4: 100 | G4: 46051 | H4: 0.14246575 | I4: 0.022 | J4: 5.22 | K4: 14.95 | L4: 14.7 | M4: 101.70068 | N4: 104.6 | O4: 2.8508361 | P4: 35.99 | Q4: 46.98 | R4: 33.5 | S4: 400000000 | T4: 建材營建
A5: 上曜六 | B5: 13166 | C5: 板信銀 | D5: 2.22 | E5: 46369 | F5: 100.5 | G5: 46383 | H5: 1.0520548 | I5: 0.023 | J5: 14.72 | K5: 14.95 | L5: 17.4 | M5: 85.91954 | N5: 112.5 | O5: 30.936455 | P5: 35.99 | Q5: 46.98 | R5: 100 | S5: 400000000 | T5: 建材營建
A6: 遠東新E1永 | B6: 140201 | C6: 3 | D6: 4.47 | E6: 46593 | F6: 100 | G6: 46607 | H6: 1.6657534 | I6: 0.025 | J6: 8.67 | K6: 38.5 | L6: 43.1 | M6: 89.327146 | N6: 104.2 | O6: 16.64987 | P6: 17.09 | Q6: 23.11 | R6: 100 | S6: 1000000000 | T6: 紡織纖維
A7: 聚隆四 | B7: 14664 | C7: 台中商銀 | D7: 6.13 | E7: 46910 | F7: 100 | G7: 46924 | H7: 2.5342466 | I7: 0.023 | J7: 12.48 | K7: 14.2 | L7: 18.8 | M7: 75.531915 | N7: 106.35 | O7: 40.801408 | P7: 38.55 | Q7: 48.71 | R7: 100 | S7: 400000000 | T7: 紡織纖維
A8: 三洋實業二 | B8: 14722 | C8: 台中商銀 | D8: 2.54 | E8: 46522 | F8: 101.0025 | G8: 46536 | H8: 1.4712329 | I8: 0.022 | J8: 8.74 | K8: 91 | L8: 98.6 | M8: 92.292089 | N8: 106.2 | O8: 15.069451 | P8: 22.03 | Q8: 32.3 | R8: 100 | S8: 300000000 | T8: 建材營建
A9: 亞力二 | B9: 15142 | C9: 6 | D9: 6.37 | E9: 46751 | F9: 100.7519 | G9: 46765 | H9: 2.0986301 | I9: 0.0325 | J9: 19.37 | K9: 97.5 | L9: 109.2 | M9: 89.285714 | N9: 113 | O9: 26.56 | P9: 32.99 | Q9: 42.48 | R9: 100 | S9: 1200000000 | T9: 電機機械
A10: 中砂一 | B10: 15601 | C10: 4 | D10: 4.16 | E10: 46548 | F10: 100 | G10: 46562 | H10: 1.5424658 | I10: 0.025 | J10: 43.01 | K10: 359.5 | L10: 284.6 | M10: 126.31764 | N10: 138.85 | O10: 9.9213074 | P10: 38.44 | Q10: 47.06 | R10: 99.94 | S10: 1000000000 | T10: 電機機械
